Workbook

Sheet Cover
B3: Nestlé Group — FP&A Case Study
B4: FY2021–FY2024 Financial Foundation · FY2025 Budget (Adverse / Base / Favorable) · Budget vs Actual Variance · FY2026 Reforecast & Sensitivity
B5: Independent analysis based exclusively on Nestlé's publicly disclosed financial reports · CHF million unless stated
B8: Prepared by Thanh Vinh Dang | E8: Data as of Nestlé Half-Year Results 2026 (23 July 2026)
B10: FY2025 AT A GLANCE — ACTUAL VS BUDGET
B11: SALES | D11: ORGANIC GROWTH | F11: FX IMPACT ON SALES | H11: UTOP MARGIN
B12: ='3. Variance_Analysis'!C16 -> 89490 | D12: ='3. Variance_Analysis'!C8 -> 0.035 | F12: ='3. Variance_Analysis'!C10 -> -0.057 | H12: ='3. Variance_Analysis'!C37 -> 0.16078891
B13: ="Budget "&TEXT('3. Variance_Analysis'!B16,"#,##0")&" · Var "&TEXT('3. Variance_Analysis'!E16,"+0.0%;-0.0%") -> Budget 94,095 · Var -4.9% | D13: ="Budget "&TEXT('3. Variance_Analysis'!B8,"0.0%")&" · Var "&TEXT('3. Variance_Analysis'!D8,"+0;-0")&" bps" -> Budget 3.0% · Var +50 bps | F13: ="Budget "&TEXT('3. Variance_Analysis'!B10,"0.0%")&" · Var "&TEXT('3. Variance_Analysis'!D10,"+0;-0")&" bps" -> Budget 0.0% · Var -570 bps | H13: ="Budget "&TEXT('3. Variance_Analysis'!B37,"0.0%")&" · Var "&TEXT('3. Variance_Analysis'!D37,"+0;-0")&" bps" -> Budget 16.6% · Var -52 bps
B16: NET PROFIT | D16: BASIC EPS (CHF) | F16: OPERATING CASH FLOW | H16: FREE CASH FLOW (REPORTED)
B17: ='3. Variance_Analysis'!C35 -> 9033 | D17: ='3. Variance_Analysis'!C43 -> 3.51 | F17: ='3. Variance_Analysis'!C62 -> 15904 | H17: ='3. Variance_Analysis'!C90 -> 9154
B18: ="Budget "&TEXT('3. Variance_Analysis'!B35,"#,##0")&" · Var "&TEXT('3. Variance_Analysis'!E35,"+0.0%;-0.0%") -> Budget 10,608 · Var -14.8% | D18: ="Budget "&TEXT('3. Variance_Analysis'!B43,"0.00")&" · Var "&TEXT('3. Variance_Analysis'!E43,"+0.0%;-0.0%") -> Budget 4.15 · Var -15.5% | F18: ="Budget "&TEXT('3. Variance_Analysis'!B62,"#,##0")&" · Var "&TEXT('3. Variance_Analysis'!E62,"+0.0%;-0.0%") -> Budget 15,666 · Var +1.5% | H18: ="Budget "&TEXT('3. Variance_Analysis'!B90,"#,##0")&" · Var "&TEXT('3. Variance_Analysis'!E90,"+0.0%;-0.0%") -> Budget 9,455 · Var -3.2%
B21: KEY MESSAGE
B22: FY2025 was a currency story, not an execution miss. Organic growth beat the Budget (3.5% vs 3.0%), but with the opposite mix to plan — pricing (+2.8%) carried growth while volume (RIG +0.8%) disappointed. A -5.7% FX headwind against a flat Budget assumption turned a planned +3.0% reported sales growth into a -2.0% decline. UTOP margin of 16.1% still landed within Nestlé's guidance of "at or above 16.0%". The FY2026 reforecast uses Nestlé's latest guidance where it exists (FX about -3%, H2 margin similar to H1) and judgement elsewhere: 3.5% organic growth, a 16.5% UTOP margin and about CHF 10.7bn of free cash flow, but net profit down about 11% after a CHF 1.3bn write-down. Each 10 bps of COGS moves net profit as much as 0.8 pp of FX.
B24: CONTENTS
B25: Step | C25: Sheet | E25: What it contains
B26: — | C26: README | E26: Workbook guide, data sources, conventions and key caveats
B27: 1 | C27: 1. Segment_Data | E27: Sales & UTOP by reporting segment, FY2021–FY2024, with RIG/Pricing bridge
B28: 1 | C28: 1. Category_Data | E28: Sales & UTOP by product category, FY2021–FY2024
B29: 1 | C29: 1. Income_Statement | E29: Full consolidated Income Statement, FY2021–FY2024
B30: 1 | C30: 1. Cash_Flow_Statement | E30: Full consolidated Statement of Cash Flows, FY2021–FY2024
B31: 2 | C31: 2. Assumptions_FY2025 | E31: ~40 FY2025 drivers under Adverse / Base / Favorable scenarios, each sourced or explained
B32: 2 | C32: 2. Budget_FY2025_PL_CF | E32: Full-detail FY2025 Budget (P&L + Cash Flow), three scenarios vs FY2024 Actual
B33: 3 | C33: 3. Variance_Analysis | E33: Actual vs Base: RIG/Pricing/FX bridge, P&L & CF variance, scenario range, driver backtest
B34: 4 | C34: 4. Assumptions_FY2026 | E34: FY2026 drivers vs FY2025 Budget and Actual: Nestlé guidance where given, judgement elsewhere
B35: 4 | C35: 4. Reforecast_FY2026 | E35: FY2026 Reforecast vs FY2025 Actual (P&L + Cash Flow), checked against FY2026 guidance
B36: 4 | C36: 4. Sensitivity_FY2026 | E36: Sensitivity of FY2026 net profit, EPS and FCF to FX and COGS (one-way and two-way)
B38: Cell conventions: | C38: Blue = sourced input | E38: Black = formula | F38: Green = link to another sheet | H38: Yellow = budget assumption
B40: Disclaimer: this is an independent portfolio analysis. It is not prepared by, affiliated with, or endorsed by Nestlé S.A. All actual figures are taken from Nestlé's published Full-Year Results press releases and Financial Statements; budget figures are the author's own assumptions. "Nestlé" is a registered trademark of Société des Produits Nestlé S.A.

Sheet README
A1: Nestlé FP&A Case Study — Data Foundation
A3: Purpose
A4: This workbook covers the Excel steps of an end-to-end FP&A portfolio project: a Data Foundation built on Nestlé's real, publicly disclosed segment and product-category financials (FY2021–FY2024), a driver-based FY2025 Budget built under Adverse / Base / Favorable scenarios, a Variance Analysis of that Budget against Nestlé's actual FY2025 results, and a full-year FY2026 Reforecast with a Sensitivity Analysis on the two drivers that missed most in FY2025 (FX and COGS). Step 5, the Power BI dashboard, lives in the powerbi/ folder of the repository.
A6: Sheets in this workbook
A7: • 1. Segment_Data — Sales & Underlying Trading Operating Profit (UTOP) by reporting segment (5 geographic Zones + Nespresso + Nestlé Health Science + Other Businesses), FY2021–FY2024, with the organic growth bridge (RIG / Pricing / Net M&A / FX) for FY2022 and FY2024.
A8: • 1. Category_Data — Sales & UTOP by product category (7 categories: Powdered & liquid beverages, Water, Milk products & ice cream, Nutrition & Health Science, Prepared dishes & cooking aids, Confectionery, PetCare), FY2021–FY2024.
A9: • 1. Income_Statement — Full consolidated Income Statement, line by line (Sales, Other revenue, COGS, Distribution expenses, Marketing & admin expenses, R&D costs, Other trading/operating income & expenses, Financial income/expense, Income from associates & JVs, Taxes, NCI), FY2021–FY2024, with every subtotal (UTOP, Trading Operating Profit, Operating Profit, PBT, Profit for the Year, Net Profit) computed by formula from the disclosed line items above it — never hardcoded.
A10: • 1. Cash_Flow_Statement — Full consolidated Statement of Cash Flows, line by line across Operating, Investing and Financing activities plus the cash reconciliation and a Free Cash Flow memo, FY2021–FY2024, with every subtotal (Cash Generated from Operations, Operating/Investing/Financing Cash Flow) computed by formula.
A11: • 2. Assumptions_FY2025 — ~40 line-item FY2025 budget drivers covering the full Income Statement and Cash Flow Statement, in three columns: Adverse / Base / Favorable. Base follows Nestlé's own FY2025 guidance where available, or an explicit own-assumption with rationale where not. Adverse and Favorable flex ten key drivers (RIG, FX, COGS %, Marketing & Admin %, other trading items, net financial expense, associates income, tax rate, working capital, capex) using ranges sized from FY2021–FY2024 history; all other drivers are held at Base. Yellow cells are the editable levers.
A12: • 2. Budget_FY2025_PL_CF — Full-detail FY2025 Budget under the Adverse, Base and Favorable scenarios, side by side with FY2024 Actual, built at the same line-item level as 1. Income_Statement and 1. Cash_Flow_Statement and fully driven by 2. Assumptions_FY2025. Built from guidance disclosed BEFORE FY2025 actual results were known; the Base scenario is the plan that Step 3 (Variance Analysis) measures against.
A13: • 3. Variance_Analysis — FY2025 Actual versus the Base Budget: a Group Sales Growth Bridge decomposing the variance into RIG (Real Internal Growth), Pricing, Net M&A and FX — the same framework Nestlé uses in its own disclosures — a full line-item Income Statement and Cash Flow variance (CHF m and %), where Actual landed versus the Adverse / Base / Favorable scenarios, a backtest of each flexed driver against its scenario range, and written commentary. All FY2025 Actual figures are hardcoded inputs (blue), sourced from Nestlé's FY2025 Full-Year Results press release and Financial Statements, cited in Data sources below.
A14: • 4. Assumptions_FY2026 — every FY2026 driver next to the FY2025 Budget (Base), the FY2025 Actual and the H1-2026 actual. Numbers Nestlé has guided or already reported are used as published, with the source (latest: Half-Year Results 2026, 23-Jul-2026 — FX about -3%, organic growth 3%–4% with RIG accelerating, H2 UTOP margin broadly similar to H1, free cash flow above CHF 9bn, the CHF 1.3bn held-for-sale write-down). Every other driver is a judgement informed by the FY2025 variance, labelled [Judgement], never a copy of the FY2025 figure.
... A34: • 1. Income_Statement / 1. Cash_Flow_Statement sheets: sourced from Nestlé's full Financial Statements documents (not the condensed press releases used for 1. Segment_Data/1. Category_Data) for full line-item detail. FY2022's 'Cash generated from operations' section reflects the "Decrease/(increase) in working capital" and "Variation of other operating assets and liabilities" lines as disclosed that year. The 'Free Cash Flow (derived)' row will not tie exactly to Nestlé's own reported FCF figure — this is flagged on the 1. Cash_Flow_Statement sheet, not hidden.

Sheet 1. Segment_Data
A1: Nestlé — Segment Sales & Profitability, FY2021–FY2024 (CHF m unless %)
A3: Segment | B3: FY2021 Sales | C3: FY2022 Sales | D3: FY2023 Sales | E3: FY2024 Sales | F3: FY22 Sales YoY | G3: FY23 Sales YoY | H3: FY24 Sales YoY | I3: FY2021 UTOP | J3: FY2022 UTOP | K3: FY2023 UTOP | L3: FY2024 UTOP | M3: FY2021 UTOP Margin | N3: FY2022 UTOP Margin | O3: FY2023 UTOP Margin | P3: FY2024 UTOP Margin | Q3: FY22 RIG | R3: FY22 Pricing | S3: FY22 Organic Gr. | T3: FY22 Net M&A | U3: FY22 FX | V3: FY24 RIG | W3: FY24 Pricing | X3: FY24 Organic Gr. | Y3: FY24 Net M&A | Z3: FY24 FX
A4: Zone North America | B4: 23693 | C4: 26328 | D4: 25995 | E4: 25336 | F4: =IFERROR(C4/B4-1,"") -> 0.11121428 | G4: =IFERROR(D4/C4-1,"") -> -0.012648131 | H4: =IFERROR(E4/D4-1,"") -> -0.025351029 | I4: 4804 | J4: 5528 | K4: 5768 | L4: 5640 | M4: =IFERROR(I4/B4,"") -> 0.20276031 | N4: =IFERROR(J4/C4,"") -> 0.20996658 | O4: =IFERROR(K4/D4,"") -> 0.22188882 | P4: =IFERROR(L4/E4,"") -> 0.22260815 | Q4: -0.013 | R4: 0.116 | S4: 0.103 | T4: -0.038 | U4: 0.047 | V4: -0.008 | W4: 0.004 | X4: -0.005 | Y4: -0.001 | Z4: -0.02
A5: Zone Europe | B5: 18794 | C5: 19128 | D5: 19098 | E5: 18910 | F5: =IFERROR(C5/B5-1,"") -> 0.017771629 | G5: =IFERROR(D5/C5-1,"") -> -0.0015683814 | H5: =IFERROR(E5/D5-1,"") -> -0.0098439627 | I5: 3439 | J5: 3138 | K5: 3127 | L5: 3192 | M5: =IFERROR(I5/B5,"") -> 0.18298393 | N5: =IFERROR(J5/C5,"") -> 0.1640527 | O5: =IFERROR(K5/D5,"") -> 0.16373442 | P5: =IFERROR(L5/E5,"") -> 0.16879958 | Q5: 0.009 | R5: 0.064 | S5: 0.072 | T5: 0.021 | U5: -0.076 | V5: 0.008 | W5: 0.025 | X5: 0.033 | Y5: -0.019 | Z5: -0.025
A6: Zone AOA | B6: 17894 | C6: 18484 | D6: 17519 | E6: 16793 | F6: =IFERROR(C6/B6-1,"") -> 0.032971946 | G6: =IFERROR(D6/C6-1,"") -> -0.052207314 | H6: =IFERROR(E6/D6-1,"") -> -0.041440722 | I6: 4288 | J6: 4237 | K6: 4109 | L6: 3916 | M6: =IFERROR(I6/B6,"") -> 0.2396334 | N6: =IFERROR(J6/C6,"") -> 0.22922528 | O6: =IFERROR(K6/D6,"") -> 0.23454535 | P6: =IFERROR(L6/E6,"") -> 0.2331924 | Q6: 0.001 | R6: 0.081 | S6: 0.082 | T6: -0.001 | U6: -0.049 | V6: 0.006 | W6: 0.028 | X6: 0.034 | Y6: 0 | Z6: -0.075
A7: Zone Latin America | B7: 10086 | C7: 11819 | D7: 12196 | E7: 11933 | F7: =IFERROR(C7/B7-1,"") -> 0.17182233 | G7: =IFERROR(D7/C7-1,"") -> 0.031897792 | H7: =IFERROR(E7/D7-1,"") -> -0.021564447 | I7: 2208 | J7: 2501 | K7: 2520 | L7: 2429 | M7: =IFERROR(I7/B7,"") -> 0.21891731 | N7: =IFERROR(J7/C7,"") -> 0.21160843 | O7: =IFERROR(K7/D7,"") -> 0.20662512 | P7: =IFERROR(L7/E7,"") -> 0.20355317 | Q7: 0.015 | R7: 0.116 | S7: 0.131 | T7: 0.001 | U7: 0.04 | V7: -0.003 | W7: 0.027 | X7: 0.025 | Y7: 0.004 | Z7: -0.049
A8: Zone Greater China | B8: 5175 | C8: 5351 | D8: 5037 | E8: 4973 | F8: =IFERROR(C8/B8-1,"") -> 0.034009662 | G8: =IFERROR(D8/C8-1,"") -> -0.05868062 | H8: =IFERROR(E8/D8-1,"") -> -0.012705976 | I8: 700 | J8: 862 | K8: 832 | L8: 803 | M8: =IFERROR(I8/B8,"") -> 0.1352657 | N8: =IFERROR(J8/C8,"") -> 0.16109138 | O8: =IFERROR(K8/D8,"") -> 0.16517769 | P8: =IFERROR(L8/E8,"") -> 0.16147195 | Q8: 0.01 | R8: 0.025 | S8: 0.035 | T8: 0 | U8: -0.001 | V8: 0.043 | W8: -0.021 | X8: 0.021 | Y8: 0.001 | Z8: -0.035
A9: Nestlé Health Science | B9: 4822 | C9: 6602 | D9: 6498 | E9: 6739 | F9: =IFERROR(C9/B9-1,"") -> 0.36914144 | G9: =IFERROR(D9/C9-1,"") -> -0.015752802 | H9: =IFERROR(E9/D9-1,"") -> 0.037088335 | I9: 654 | J9: 899 | K9: 777 | L9: 943 | M9: =IFERROR(I9/B9,"") -> 0.13562837 | N9: =IFERROR(J9/C9,"") -> 0.13617086 | O9: =IFERROR(K9/D9,"") -> 0.11957525 | P9: =IFERROR(L9/E9,"") -> 0.13993174 | Q9: 0.006 | R9: 0.034 | S9: 0.04 | T9: 0.315 | U9: 0.015 | V9: 0.055 | W9: 0.007 | X9: 0.062 | Y9: 0.002 | Z9: -0.028
A10: Nespresso | B10: 6418 | C10: 6448 | D10: 6372 | E10: 6378 | F10: =IFERROR(C10/B10-1,"") -> 0.0046743534 | G10: =IFERROR(D10/C10-1,"") -> -0.0117866 | H10: =IFERROR(E10/D10-1,"") -> 0.00094161959 | I10: 1475 | J10: 1388 | K10: 1291 | L10: 1278 | M10: =IFERROR(I10/B10,"") -> 0.22982237 | N10: =IFERROR(J10/C10,"") -> 0.21526055 | O10: =IFERROR(K10/D10,"") -> 0.20260515 | P10: =IFERROR(L10/E10,"") -> 0.20037629 | Q10: -0.017 | R10: 0.052 | S10: 0.035 | T10: -0.003 | U10: -0.027 | V10: 0.016 | W10: 0.006 | X10: 0.022 | Y10: 0.002 | Z10: -0.024
A11: Other Businesses | B11: 206 | C11: 264 | D11: 283 | E11: 292 | F11: =IFERROR(C11/B11-1,"") -> 0.2815534 | G11: =IFERROR(D11/C11-1,"") -> 0.071969697 | H11: =IFERROR(E11/D11-1,"") -> 0.03180212 | I11: -32 | J11: -17 | K11: -12 | L11: -13 | M11: =IFERROR(I11/B11,"") -> -0.15533981 | N11: =IFERROR(J11/C11,"") -> -0.064393939 | O11: =IFERROR(K11/D11,"") -> -0.042402827 | P11: =IFERROR(L11/E11,"") -> -0.044520548 | Q11: 0.252 | R11: 0.032 | S11: 0.284 | T11: 0 | U11: -0.001 | V11: 0.053 | W11: 0.013 | X11: 0.066 | Y11: 0 | Z11: -0.027
A12: Total Group | B12: =SUM(B4:B11) -> 87088 | C12: =SUM(C4:C11) -> 94424 | D12: =SUM(D4:D11) -> 92998 | E12: =SUM(E4:E11) -> 91354 | F12: =IFERROR(C12/B12-1,"") -> 0.084236634 | G12: =IFERROR(D12/C12-1,"") -> -0.015102093 | H12: =IFERROR(E12/D12-1,"") -> -0.0176778 | I12: 15119 | J12: 16103 | K12: 16053 | L12: 15704 | M12: =IFERROR(I12/B12,"") -> 0.17360601 | N12: =IFERROR(J12/C12,"") -> 0.17053927 | O12: =IFERROR(K12/D12,"") -> 0.17261662 | P12: =IFERROR(L12/E12,"") -> 0.17190271 | Q12: 0.001 | R12: 0.082 | S12: 0.083 | T12: 0.011 | U12: -0.009 | V12: 0.008 | W12: 0.015 | X12: 0.022 | Y12: -0.003 | Z12: -0.037
A14: Source: Nestlé Full-Year Results press releases 2022 and 2024 (see README for links). FY21/FY22 RIG/Pricing/OG/M&A/FX exclude Russia.
A15: Note: Segment UTOP figures sum to more than the Group Total UTOP shown above — this is expected. Nestlé's Group total nets off unallocated central costs and eliminations that are not broken out by segment in the summary disclosure, so the Total row uses the company's reported Group figure directly rather than a SUM of segments.

Sheet 1. Category_Data
A1: Nestlé — Sales & Profitability by Product Category, FY2021–FY2024 (CHF m unless %)
A3: Category | B3: FY2021 Sales | C3: FY2022 Sales | D3: FY2023 Sales | E3: FY2024 Sales | F3: FY22 Sales YoY | G3: FY23 Sales YoY | H3: FY24 Sales YoY | I3: FY2021 UTOP | J3: FY2022 UTOP | K3: FY2023 UTOP | L3: FY2024 UTOP | M3: FY2021 UTOP Margin | N3: FY2022 UTOP Margin | O3: FY2023 UTOP Margin | P3: FY2024 UTOP Margin | Q3: FY22 RIG | R3: FY22 Pricing | S3: FY22 Organic Gr. | T3: FY24 RIG | U3: FY24 Pricing | V3: FY24 Organic Gr.
A4: Powdered & liquid beverages | B4: 23975 | C4: 25218 | D4: 24786 | E4: 24598 | F4: =IFERROR(C4/B4-1,"") -> 0.051845673 | G4: =IFERROR(D4/C4-1,"") -> -0.017130621 | H4: =IFERROR(E4/D4-1,"") -> -0.007584927 | I4: 5631 | J4: 5593 | K4: 5130 | L4: 4920 | M4: =IFERROR(I4/B4,"") -> 0.23486966 | N4: =IFERROR(J4/C4,"") -> 0.22178603 | O4: =IFERROR(K4/D4,"") -> 0.20697168 | P4: =IFERROR(L4/E4,"") -> 0.20001626 | Q4: 0.002 | R4: 0.078 | S4: 0.08 | T4: 0.016 | U4: 0.017 | V4: 0.033
A5: Water | B5: 4040 | C5: 3536 | D5: 3320 | E5: 3180 | F5: =IFERROR(C5/B5-1,"") -> -0.12475248 | G5: =IFERROR(D5/C5-1,"") -> -0.061085973 | H5: =IFERROR(E5/D5-1,"") -> -0.042168675 | I5: 364 | J5: 277 | K5: 351 | L5: 297 | M5: =IFERROR(I5/B5,"") -> 0.09009901 | N5: =IFERROR(J5/C5,"") -> 0.078337104 | O5: =IFERROR(K5/D5,"") -> 0.10572289 | P5: =IFERROR(L5/E5,"") -> 0.093396226 | Q5: 0.022 | R5: 0.089 | S5: 0.11 | T5: -0.01 | U5: 0.032 | V5: 0.023
A6: Milk products & ice cream | B6: 10700 | C6: 11289 | D6: 10981 | E6: 10397 | F6: =IFERROR(C6/B6-1,"") -> 0.055046729 | G6: =IFERROR(D6/C6-1,"") -> -0.027283196 | H6: =IFERROR(E6/D6-1,"") -> -0.05318277 | I6: 2707 | J6: 2568 | K6: 2688 | L6: 2442 | M6: =IFERROR(I6/B6,"") -> 0.25299065 | N6: =IFERROR(J6/C6,"") -> 0.22747808 | O6: =IFERROR(K6/D6,"") -> 0.24478645 | P6: =IFERROR(L6/E6,"") -> 0.23487544 | Q6: -0.043 | R6: 0.096 | S6: 0.054 | T6: -0.007 | U6: 0.001 | V6: -0.006
A7: Nutrition & Health Science | B7: 13157 | C7: 15678 | D7: 15278 | E7: 15137 | F7: =IFERROR(C7/B7-1,"") -> 0.19160903 | G7: =IFERROR(D7/C7-1,"") -> -0.025513458 | H7: =IFERROR(E7/D7-1,"") -> -0.0092289567 | I7: 2307 | J7: 2990 | K7: 2831 | L7: 3006 | M7: =IFERROR(I7/B7,"") -> 0.17534392 | N7: =IFERROR(J7/C7,"") -> 0.1907131 | O7: =IFERROR(K7/D7,"") -> 0.18529912 | P7: =IFERROR(L7/E7,"") -> 0.19858625 | Q7: 0.017 | R7: 0.057 | S7: 0.074 | T7: 0.019 | U7: 0.009 | V7: 0.028
A8: Prepared dishes & cooking aids | B8: 12146 | C8: 12484 | D8: 11666 | E8: 10711 | F8: =IFERROR(C8/B8-1,"") -> 0.027828092 | G8: =IFERROR(D8/C8-1,"") -> -0.065523871 | H8: =IFERROR(E8/D8-1,"") -> -0.081861821 | I8: 2040 | J8: 2038 | K8: 2136 | L8: 2137 | M8: =IFERROR(I8/B8,"") -> 0.16795653 | N8: =IFERROR(J8/C8,"") -> 0.16324896 | O8: =IFERROR(K8/D8,"") -> 0.18309618 | P8: =IFERROR(L8/E8,"") -> 0.19951452 | Q8: -0.069 | R8: 0.1 | S8: 0.031 | T8: -0.022 | U8: 0.005 | V8: -0.017
A9: Confectionery | B9: 7514 | C9: 8118 | D9: 8107 | E9: 8449 | F9: =IFERROR(C9/B9-1,"") -> 0.080383285 | G9: =IFERROR(D9/C9-1,"") -> -0.0013550136 | H9: =IFERROR(E9/D9-1,"") -> 0.042185765 | I9: 1205 | J9: 1364 | K9: 1364 | L9: 1299 | M9: =IFERROR(I9/B9,"") -> 0.16036731 | N9: =IFERROR(J9/C9,"") -> 0.16802168 | O9: =IFERROR(K9/D9,"") -> 0.16824966 | P9: =IFERROR(L9/E9,"") -> 0.15374601 | Q9: 0.048 | R9: 0.047 | S9: 0.094 | T9: -0.002 | U9: 0.064 | V9: 0.062
A10: PetCare | B10: 15556 | C10: 18101 | D10: 18860 | E10: 18882 | F10: =IFERROR(C10/B10-1,"") -> 0.16360247 | G10: =IFERROR(D10/C10-1,"") -> 0.041931385 | H10: =IFERROR(E10/D10-1,"") -> 0.0011664899 | I10: 3282 | J10: 3706 | K10: 3912 | L10: 4087 | M10: =IFERROR(I10/B10,"") -> 0.21097969 | N10: =IFERROR(J10/C10,"") -> 0.20474007 | O10: =IFERROR(K10/D10,"") -> 0.20742312 | P10: =IFERROR(L10/E10,"") -> 0.21644953 | Q10: 0.043 | R10: 0.102 | S10: 0.145 | T10: 0.021 | U10: 0.006 | V10: 0.027
A11: Total Group | B11: =SUM(B4:B10) -> 87088 | C11: =SUM(C4:C10) -> 94424 | D11: =SUM(D4:D10) -> 92998 | E11: =SUM(E4:E10) -> 91354 | F11: =IFERROR(C11/B11-1,"") -> 0.084236634 | G11: =IFERROR(D11/C11-1,"") -> -0.015102093 | H11: =IFERROR(E11/D11-1,"") -> -0.0176778 | I11: 15119 | J11: 16103 | K11: 16053 | L11: 15704 | M11: =IFERROR(I11/B11,"") -> 0.17360601 | N11: =IFERROR(J11/C11,"") -> 0.17053927 | O11: =IFERROR(K11/D11,"") -> 0.17261662 | P11: =IFERROR(L11/E11,"") -> 0.17190271
A13: Source: Nestlé Full-Year Results press releases 2022 and 2024 (see README for links).
A14: Note: as with the segment view, category UTOP figures sum to more than Group Total UTOP because unallocated central costs are not broken out by category. The Total row uses Nestlé's reported Group figure directly.

Sheet 1. Income_Statement
A1: Nestlé Group — Consolidated Income Statement, FY2021–FY2024 (CHF million unless per-share)
A3: Line Item | B3: FY2021 | C3: FY2022 | D3: FY2023 | E3: FY2024
A4: Sales | B4: 87088 | C4: 94424 | D4: 92998 | E4: 91354
A5: Other revenue | B5: 382 | C5: 356 | D5: 353 | E5: 366
A6: Cost of goods sold | B6: -45468 | C6: -51745 | D6: -50328 | E6: -48670
A7: Distribution expenses | B7: -7919 | C7: -8386 | D7: -7765 | E7: -7567
A8: Marketing and administration expenses | B8: -17294 | C8: -16850 | D8: -17549 | E8: -18112
A9: Research and development costs | B9: -1670 | C9: -1696 | D9: -1656 | E9: -1667
A10: Underlying Trading Operating Profit (UTOP)* | B10: =SUM(B4:B9) -> 15119 | C10: =SUM(C4:C9) -> 16103 | D10: =SUM(D4:D9) -> 16053 | E10: =SUM(E4:E9) -> 15704
A11: Other trading income | B11: 171 | C11: 107 | D11: 132 | E11: 124
A12: Other trading expenses | B12: -3131 | C12: -3015 | D12: -1665 | E12: -1195
A13: Trading Operating Profit | B13: =B10+B11+B12 -> 12159 | C13: =C10+C11+C12 -> 13195 | D13: =D10+D11+D12 -> 14520 | E13: =E10+E11+E12 -> 14633
A14: Other operating income | B14: 698 | C14: 340 | D14: 298 | E14: 474
A15: Other operating expenses | B15: -1178 | C15: -1209 | D15: -755 | E15: -383
A16: Operating Profit | B16: =B13+B14+B15 -> 11679 | C16: =C13+C14+C15 -> 12326 | D16: =D13+D14+D15 -> 14063 | E16: =E13+E14+E15 -> 14724
A17: Financial income | B17: 80 | C17: 210 | D17: 284 | E17: 358
A18: Financial expense | B18: -953 | C18: -1250 | D18: -1644 | E18: -1843
A19: Net Financial Income/(Expense) | B19: =B17+B18 -> -873 | C19: =C17+C18 -> -1040 | D19: =D17+D18 -> -1360 | E19: =E17+E18 -> -1485
A20: Profit Before Taxes, Associates and Joint Ventures | B20: =B16+B19 -> 10806 | C20: =C16+C19 -> 11286 | D20: =D16+D19 -> 12703 | E20: =E16+E19 -> 13239
A21: Income from associates and joint ventures | B21: 8651 | C21: 1040 | D21: 1120 | E21: 1249
A22: Taxes | B22: -2261 | C22: -2730 | D22: -2314 | E22: -3314
A23: Profit for the Year | B23: =B20+B21+B22 -> 17196 | C23: =C20+C21+C22 -> 9596 | D23: =D20+D21+D22 -> 11509 | E23: =E20+E21+E22 -> 11174
A24: Of which: non-controlling interests | B24: 291 | C24: 326 | D24: 300 | E24: 290
A25: Net Profit (attributable to shareholders of the parent) | B25: =B23-B24 -> 16905 | C25: =C23-C24 -> 9270 | D25: =D23-D24 -> 11209 | E25: =E23-E24 -> 10884
A27: UTOP Margin | B27: =IFERROR(B10/B4,"") -> 0.17360601 | C27: =IFERROR(C10/C4,"") -> 0.17053927 | D27: =IFERROR(D10/D4,"") -> 0.17261662 | E27: =IFERROR(E10/E4,"") -> 0.17190271
A28: Trading Operating Profit Margin | B28: =IFERROR(B13/B4,"") -> 0.1396174 | C28: =IFERROR(C13/C4,"") -> 0.13974201 | D28: =IFERROR(D13/D4,"") -> 0.15613239 | E28: =IFERROR(E13/E4,"") -> 0.16017908
A29: Operating Profit Margin | B29: =IFERROR(B16/B4,"") -> 0.13410573 | C29: =IFERROR(C16/C4,"") -> 0.13053885 | D29: =IFERROR(D16/D4,"") -> 0.15121831 | E29: =IFERROR(E16/E4,"") -> 0.16117521
A30: Net Profit Margin | B30: =IFERROR(B25/B4,"") -> 0.194114 | C30: =IFERROR(C25/C4,"") -> 0.098174193 | D30: =IFERROR(D25/D4,"") -> 0.12052947 | E30: =IFERROR(E25/E4,"") -> 0.11914092
A31: Effective Tax Rate (Taxes ÷ PBT) | B31: =IFERROR(-B22/B20,"") -> 0.20923561 | C31: =IFERROR(-C22/C20,"") -> 0.24189261 | D31: =IFERROR(-D22/D20,"") -> 0.18216169 | E31: =IFERROR(-E22/E20,"") -> 0.25032102
A33: Basic earnings per share (CHF) | B33: 6.06 | C33: 3.42 | D33: 4.24 | E33: 4.19
A34: Diluted earnings per share (CHF) | B34: 6.06 | C34: 3.42 | D34: 4.23 | E34: 4.19
A36: * "Underlying Trading Operating Profit" (UTOP) is Nestlé's own key profitability KPI. It is not printed as an explicit line in the statutory income statement, but is fully derivable as Sales + Other revenue − Cost of goods sold − Distribution expenses − Marketing & administration expenses − Research & development costs (computed here as a formula, not hardcoded) — it ties exactly to the UTOP figures Nestlé discloses separately (e.g. FY2024: CHF 15,704m, 17.2% margin).
A37: Sources: Nestlé Financial Statements 2024 (published 13-Feb-2025) for FY2024 and FY2023 — https://www.nestle.com/sites/default/files/2025-02/2024-financial-statements-en.pdf ; Nestlé Financial Statements 2022 (published 16-Feb-2023) for FY2022 and FY2021 — https://www.nestle.com/sites/default/files/2023-02/2022-financial-statements-en.pdf
A38: Shaded rows are subtotals computed by formula from the line items above them — never hardcoded — so every number here is traceable back to a disclosed line item.
A39: FY2021's unusually high Net Profit (CHF 16,905m) and 'Income from associates and joint ventures' (CHF 8,651m) reflect the one-off gain on Nestlé's disposal of part of its L'Oréal stake in 2021, not a recurring item.

Sheet 1. Cash_Flow_Statement
A1: Nestlé Group — Consolidated Statement of Cash Flows, FY2021–FY2024 (CHF million)
A3: Line Item | B3: FY2021 | C3: FY2022 | D3: FY2023 | E3: FY2024
A4: OPERATING ACTIVITIES
A5: Operating Profit (linked from Income_Statement) | B5: ='1. Income_Statement'!B16 -> 11679 | C5: ='1. Income_Statement'!C16 -> 12326 | D5: ='1. Income_Statement'!D16 -> 14063 | E5: ='1. Income_Statement'!E16 -> 14724
A6: Depreciation and amortization | B6: 3440 | C6: 3541 | D6: 3458 | E6: 3582
A7: Impairment | B7: 2614 | C7: 2726 | D7: 647 | E7: 580
A8: Net result on disposal of businesses | B8: -235 | C8: 79 | D8: 221 | E8: 62
A9: Other non-cash items of income and expense | B9: -253 | C9: 216 | D9: 82 | E9: -229
A10: Cash Flow Before Changes in Operating Assets and Liabilities | B10: =SUM(B5:B9) -> 17245 | C10: =SUM(C5:C9) -> 18888 | D10: =SUM(D5:D9) -> 18471 | E10: =SUM(E5:E9) -> 18719
A11: Decrease/(increase) in working capital | B11: -173 | C11: -3133 | D11: 1134 | E11: 1208
A12: Variation of other operating assets and liabilities | B12: -427 | C12: -514 | D12: -425 | E12: -334
A13: Cash Generated from Operations | B13: =B10+B11+B12 -> 16645 | C13: =C10+C11+C12 -> 15241 | D13: =D10+D11+D12 -> 19180 | E13: =E10+E11+E12 -> 19593
A14: Interest paid | B14: -753 | C14: -953 | D14: -1330 | E14: -1539
A15: Interest and dividends received | B15: 43 | C15: 118 | D15: 193 | E15: 273
A16: Taxes paid | B16: -2722 | C16: -3107 | D16: -2801 | E16: -2411
A17: Dividends and interest from associates and joint ventures | B17: 651 | C17: 608 | D17: 699 | E17: 759
A18: Operating Cash Flow | B18: =B13+B14+B15+B16+B17 -> 13864 | C18: =C13+C14+C15+C16+C17 -> 11907 | D18: =D13+D14+D15+D16+D17 -> 15941 | E18: =E13+E14+E15+E16+E17 -> 16675
A20: INVESTING ACTIVITIES
A21: Capital expenditure | B21: -4880 | C21: -5095 | D21: -5714 | E21: -5638
A22: Expenditure on intangible assets | B22: -461 | C22: -266 | D22: -489 | E22: -325
A23: Acquisition of businesses, net of cash acquired | B23: -6394 | C23: -1710 | D23: -211 | E23: -809
A24: Disposal of businesses, net of cash disposed of | B24: 3530 | C24: 160 | D24: 215 | E24: -23
A25: Investments (net) in associates and joint ventures | B25: -715 | C25: -918 | D25: -582 | E25: -532
A26: Divestments in associates and joint ventures | B26: 9294 | C26: 0 | D26: 0 | E26: 0
A27: Inflows/(outflows) from treasury investments | B27: -3610 | C27: 5902 | D27: -80 | E27: -1251
A28: Other investing activities | B28: 192 | C28: 24 | D28: 665 | E28: -46
A29: Investing Cash Flow | B29: =SUM(B21:B28) -> -3044 | C29: =SUM(C21:C28) -> -1903 | D29: =SUM(D21:D28) -> -6196 | E29: =SUM(E21:E28) -> -8624
A31: FINANCING ACTIVITIES
A32: Dividend paid to shareholders of the parent | B32: -7681 | C32: -7618 | D32: -7829 | E32: -7816
A33: Dividends paid to non-controlling interests | B33: -302 | C33: -284 | D33: -323 | E33: -174
A34: Acquisition of non-controlling interests | B34: -601 | C34: -605 | D34: -52 | E34: -27
A35: Purchase of treasury shares | B35: -6548 | C35: -10679 | D35: -5234 | E35: -4678
A36: Inflows from bonds and other long-term financial debt | B36: 11339 | C36: 10936 | D36: 9806 | E36: 7992
A37: Outflows from bonds, lease liabilities and other long-term financial debt | B37: -4474 | C37: -3283 | D37: -3589 | E37: -5055
A38: Inflows/(outflows) from short-term financial debt | B38: -885 | C38: 148 | D38: -2537 | E38: 2396
A39: Financing Cash Flow | B39: =SUM(B32:B38) -> -9152 | C39: =SUM(C32:C38) -> -11385 | D39: =SUM(D32:D38) -> -9758 | E39: =SUM(E32:E38) -> -7362
A41: CASH RECONCILIATION
A42: Currency retranslations | B42: 89 | C42: -100 | D42: -682 | E42: 53
A43: Increase/(Decrease) in Cash and Cash Equivalents | B43: =B18+B29+B39+B42 -> 1757 | C43: =C18+C29+C39+C42 -> -1481 | D43: =D18+D29+D39+D42 -> -695 | E43: =E18+E29+E39+E42 -> 742
A44: Cash and cash equivalents at beginning of year | B44: 5235 | C44: 6992 | D44: 5511 | E44: 4816
A45: Cash and Cash Equivalents at End of Year | B45: =B44+B43 -> 6992 | C45: =C44+C43 -> 5511 | D45: =D44+D43 -> 4816 | E45: =E44+E43 -> 5558
A46: Cash and cash equivalents classified as held for sale | B46: -4 | C46: 0 | D46: 0 | E46: -2
A47: Cash and Cash Equivalents per Balance Sheet | B47: =B45+B46 -> 6988 | C47: =C45+C46 -> 5511 | D47: =D45+D46 -> 4816 | E47: =E45+E46 -> 5556
A49: MEMO: FREE CASH FLOW
A50: Free Cash Flow (as reported by Nestlé) | B50: 8700 | C50: 6600 | D50: 10403 | E50: 10666
A51: Free Cash Flow (derived: Operating CF − Capex − Intangible capex) | B51: =B18+B21+B22 -> 8523 | C51: =C18+C21+C22 -> 6546 | D51: =D18+D21+D22 -> 9738 | E51: =E18+E21+E22 -> 10712
A52: Free Cash Flow Margin (reported FCF ÷ Sales) | B52: =IFERROR(B50/'1. Income_Statement'!B4,"") -> 0.099898953 | C52: =IFERROR(C50/'1. Income_Statement'!C4,"") -> 0.069897484 | D52: =IFERROR(D50/'1. Income_Statement'!D4,"") -> 0.11186262 | E52: =IFERROR(E50/'1. Income_Statement'!E4,"") -> 0.1167546
A54: Sources: Nestlé Financial Statements 2024 (13-Feb-2025) for FY2024/FY2023, and Nestlé Financial Statements 2022 (16-Feb-2023) for FY2022/FY2021 — same two documents cited on the Income_Statement sheet.
A55: "Free Cash Flow (as reported by Nestlé)" is the company's own headline FCF figure quoted in its results press releases. "Free Cash Flow (derived)" is a from-first-principles calculation (Operating Cash Flow − Capex − Intangible capex) using only the line items above — the two do not tie out exactly (Nestlé's own FCF definition includes some additional adjustments not separately disclosed), which is normal and is flagged here rather than silently forced to match.
A56: Shaded rows are subtotals computed by formula, never hardcoded, so every subtotal is traceable to a disclosed line item.
A57: "Divestments in associates and joint ventures" (CHF 9,294m in FY2021 only) reflects the one-off partial disposal of Nestlé's L'Oréal stake — see the matching note on the Income_Statement sheet.

Sheet 2. Assumptions_FY2025
A1: Nestlé — FY2025 Budget Assumptions: Adverse / Base / Favorable scenarios (full line-item detail, P&L + Cash Flow)
A3: Driver | B3: Adverse | C3: Base | D3: Favorable | E3: Source / Rationale
A4: A. INCOME STATEMENT DRIVERS
A5: Real Internal Growth (RIG) — volume/mix | B5: 0.005 | C5: 0.015 | D5: 0.025 | E5: Own split of the 3.0% organic growth assumption, using only information available on 13-Feb-2025. RIG improved from 0.1% in H1-2024 to 1.4% in H2-2024 (Full-Year Results 2024 press release), and FY2025 guidance calls for organic growth "strengthening through the year" backed by advertising & marketing spend rising toward 9% of sales. 1.5% assumes RIG holds just above its H2-2024 exit rate. Scenarios: Adverse 0.5% / Favorable 2.5% (±100 bps). Volume is the swing factor; Pricing is held at Base in all three scenarios, so Organic Growth ranges 2.0%–4.0%, spanning FY2024's actual 2.2% and a stronger recovery.
A6: Pricing | B6: =C6 -> 0.015 | C6: 0.015 | D6: =C6 -> 0.015 | E6: Own split: held at the FY2024 full-year level (1.5%). Upward pressure from coffee and cocoa cost inflation is balanced by guidance that Nestlé is "selectively investing in price as we focus on restoring competitiveness", with commodity increases offset by "accelerated delivery of cost efficiencies" (Full-Year Results 2024 press release). H2-2024 pricing had slowed to ~0.9% (organic 2.3% − RIG 1.4%).
A7: → Organic Sales Growth (RIG + Pricing) | B7: ='2. Assumptions_FY2025'!B5+'2. Assumptions_FY2025'!B6 -> 0.02 | C7: ='2. Assumptions_FY2025'!C5+'2. Assumptions_FY2025'!C6 -> 0.03 | D7: ='2. Assumptions_FY2025'!D5+'2. Assumptions_FY2025'!D6 -> 0.04 | E7: Formula: RIG + Pricing (not a separate input). Additive, per Nestlé's own definition ("OG combines Real internal growth and Pricing" — Alternative Performance Measures, Feb-2026); the small cross-effect (1.5% × 1.5% ≈ 2 bps) is ignored, consistent with how Nestlé reports its actuals. Nestlé FY2025 guidance (Full-Year Results 2024 press release, 13-Feb-2025): "organic sales growth expected to improve compared to 2024, strengthening through the year" (FY2024 organic growth was 2.2%). The resulting 3.0% is an illustrative point within that guided direction — Nestlé did not disclose a precise FY2025 organic growth number. The RIG/Pricing split was added in Step 3 without changing the 3.0% total, so the Budget figures are unchanged.
A8: Net M&A Impact | B8: =C8 -> 0 | C8: 0 | D8: =C8 -> 0 | E8: No acquisition/divestment guidance was disclosed for FY2025; assumed neutral (0.0%), consistent with FY2024's own -0.3% being a minor, non-recurring item.
A9: Foreign Exchange (FX) Impact | B9: -0.04 | C9: 0 | D9: 0.02 | E9: FY2025 guidance "assumes no significant change in key macroeconomic variables" — interpreted as a flat (0.0%) FX assumption. This is a simplifying assumption, not a forecast of currency markets. Scenarios: Adverse -4.0% / Favorable +2.0%. FX impact on Group sales was -0.9% in FY2022 and -3.7% in FY2024 (1. Segment_Data), with the Swiss franc structurally strong — so the adverse case sits near the worst recent year and the favorable case is smaller.
A10: → Implied Reported Sales Growth | B10: ='2. Assumptions_FY2025'!B7+'2. Assumptions_FY2025'!B8+'2. Assumptions_FY2025'!B9 -> -0.02 | C10: ='2. Assumptions_FY2025'!C7+'2. Assumptions_FY2025'!C8+'2. Assumptions_FY2025'!C9 -> 0.03 | D10: ='2. Assumptions_FY2025'!D7+'2. Assumptions_FY2025'!D8+'2. Assumptions_FY2025'!D9 -> 0.06 | E10: Formula: Organic Sales Growth + Net M&A Impact + FX Impact (not a separate input).
A11: Other Revenue (% of Sales) | B11: =C11 -> 0.004 | C11: 0.004 | D11: =C11 -> 0.004 | E11: Own assumption: held flat at the FY2024 ratio (366 / 91,354 = 0.40%) — an immaterial, stable line with no company guidance.
A12: Cost of Goods Sold (% of Sales) | B12: 0.539 | C12: 0.529 | D12: 0.519 | E12: Own assumption: modest improvement from FY2024's 53.3% ratio, reflecting continued procurement/input-cost savings under the "Fuel for Growth" cost-savings programme referenced in FY2025 guidance. No specific COGS-ratio guidance was disclosed. Scenarios: 53.9% / 51.9% (±100 bps). COGS ranged from 52.2% (FY2021) to 54.8% (FY2022) of sales; the range covers coffee/cocoa cost inflation versus faster Fuel for Growth savings.
A13: Distribution Expenses (% of Sales) | B13: =C13 -> 0.082 | C13: 0.082 | D13: =C13 -> 0.082 | E13: Own assumption: slight improvement from FY2024's 8.28% ratio, reflecting logistics/supply-chain efficiencies under Fuel for Growth. No specific guidance was disclosed for this line.
A14: Marketing & Administration Expenses (% of Sales) | B14: 0.214 | C14: 0.209 | D14: 0.204 | E14: Own assumption, the key driver of the guided margin step-down: FY2025 guidance states advertising & marketing spend is planned to increase toward ~9% of sales by end-2025 (from 8.1% in FY2024); this line also includes G&A, which is not separately guided, so the ratio is calibrated (from FY2024's 19.83%) so that the resulting UTOP margin lands at "or above 16.0%", per guidance — see the memo row below. Scenarios: 21.4% / 20.4% (±50 bps). Ranged 17.9%–19.9% of sales over FY2021–FY2024; reflects execution risk around the planned advertising & marketing step-up.
A15: Research & Development Costs (% of Sales) | B15: =C15 -> 0.018 | C15: 0.018 | D15: =C15 -> 0.018 | E15: Own assumption: held broadly flat versus FY2024's 1.82% ratio — Nestlé has not signalled a change in R&D investment intensity.
A16: → Resulting UTOP Margin (memo, not an input) | B16: =1+'2. Assumptions_FY2025'!B11-'2. Assumptions_FY2025'!B12-'2. Assumptions_FY2025'!B13-'2. Assumptions_FY2025'!B14-'2. Assumptions_FY2025'!B15 -> 0.151 | C16: =1+'2. Assumptions_FY2025'!C11-'2. Assumptions_FY2025'!C12-'2. Assumptions_FY2025'!C13-'2. Assumptions_FY2025'!C14-'2. Assumptions_FY2025'!C15 -> 0.166 | D16: =1+'2. Assumptions_FY2025'!D11-'2. Assumptions_FY2025'!D12-'2. Assumptions_FY2025'!D13-'2. Assumptions_FY2025'!D14-'2. Assumptions_FY2025'!D15 -> 0.181 | E16: Formula: 1 + Other Revenue% − COGS% − Distribution% − Marketing&Admin% − R&D%. Shown for reference against FY2025 guidance of "UTOP margin expected to be at or above 16.0%" (down from FY2024's 17.2%).
A17: Other Trading Items, net (% of Sales) | B17: -0.019 | C17: -0.014 | D17: -0.009 | E17: Own assumption: FY2023–FY2024 two-year average net ratio (-1.65% / -1.17%, avg ≈ -1.41%), reflecting continued but no-longer-escalating restructuring/one-off items as the prior large cost-reduction programme (2021–2022) winds down. Nestlé does not guide this line. Scenarios: -1.9% / -0.9% (±50 bps). Ranged from -3.4% (FY2021) to -1.2% (FY2024) of sales.
A18: Other Operating Items, net (% of Sales) | B18: =C18 -> -0.002 | C18: -0.002 | D18: =C18 -> -0.002 | E18: Own assumption: FY2023–FY2024 two-year average net ratio (-0.49% / +0.10%, avg ≈ -0.20%). This line is inherently one-off in nature (disposals, portfolio actions) and is not guided by the company.
A19: Financial Income Growth (vs FY2024) | B19: =C19 -> 0 | C19: 0 | D19: =C19 -> 0 | E19: Own assumption: held flat — no treasury-yield or cash-balance guidance was disclosed for FY2025.
A20: Net Financial Expense Growth (vs FY2024) | B20: 0.15 | C20: 0.05 | D20: -0.05 | E20: Own assumption (not company guidance): Nestlé's net debt rose to CHF 56.0bn at FY2024 year-end (from CHF 49.6bn a year earlier) and the company does not anticipate a new share buyback programme in 2025 — implying continued elevated net financial expenses. +5.0% growth vs FY2024's CHF 1,485m is assumed as a reasonable continuation of the FY2023→FY2024 trend (+9.2%), applied more conservatively. Financial expense is then derived as the balancing line versus the flat Financial Income assumption above. Scenarios: +15% / -5% (±10 percentage points). Net financial expense grew +19%, +31% and +9% in FY2022–FY2024 as net debt and rates rose.
A21: Income from Associates & JVs Growth | B21: -0.02 | C21: 0.08 | D21: 0.18 | E21: Own assumption: continuation of the FY2022–FY2024 recovery trend (CHF 1,040m → 1,120m → 1,249m, i.e. +7.7% then +11.5% YoY), moderated to +8.0% for FY2025. Excludes the FY2021 CHF 8,651m figure, which included the one-off L'Oréal-related gain and is not representative of a run rate. Scenarios: -2% / +18% (±10 percentage points). Grew +7.7% and +11.5% in FY2023–FY2024 (mainly L'Oréal).
A22: Effective Tax Rate | B22: 0.26 | C22: 0.24 | D22: 0.22 | E22: Own assumption: close to, but slightly below, FY2024's reported 25.0% rate, with modest normalization assumed as the one-off deferred-tax write-off that inflated the FY2024 rate is not expected to repeat. No FY2025 tax-rate guidance was disclosed. Scenarios: 26.0% / 22.0% (±200 bps). Ranged 18.2%–25.0% over FY2021–FY2024.
A23: Non-Controlling Interests (% of Profit for the Year) | B23: =C23 -> 0.026 | C23: 0.026 | D23: =C23 -> 0.026 | E23: Own assumption: held flat at the FY2024 ratio (290 / 11,174 = 2.60%) — this line has been stable (2.5%–3.4%) across FY2021–FY2024.
A24: Shares Outstanding for EPS (million) | B24: =C24 -> 2554.7 | C24: 2554.7 | D24: =C24 -> 2554.7 | E24: FY2024 weighted-average basic shares implied by reported EPS (Net Profit CHF 10,884m ÷ EPS CHF 4.19 ≈ 2,598m), reduced by the 43.5 million shares the Board proposed for cancellation in 2025. No new buyback programme is planned for 2025 per guidance, so the share count is held flat aside from that already-announced cancellation.
A26: B. CASH FLOW DRIVERS
A27: Depreciation & Amortization (% of Sales) | B27: =C27 -> 0.039 | C27: 0.039 | D27: =C27 -> 0.039 | E27: Own assumption: held flat at the FY2024 ratio (3,582 / 91,354 = 3.92%) — D&A has been stable at 3.7%–3.9% of sales across FY2021–FY2024, tracking the asset base rather than any single-year driver.
A28: Impairment (CHF m) | B28: =C28 -> 580 | C28: 580 | D28: =C28 -> 580 | E28: Own assumption: held flat at the FY2024 level, treated as a normalized run-rate figure. FY2021–FY2022 carried much larger impairments (CHF 2,614m / 2,726m) tied to a specific prior restructuring programme that has since wound down (FY2023: CHF 647m, FY2024: CHF 580m); no new large impairment is assumed.
A29: Net Disposal Result & Other Non-Cash Items (CHF m) | B29: =C29 -> 0 | C29: 0 | D29: =C29 -> 0 | E29: Own assumption: neutral placeholder. Both lines have swung between small positive and negative values FY2021–FY2024 with no discernible trend and no company guidance — modelling anything other than zero would be spurious precision.
A30: Working Capital & Other Operating Movements (CHF m) | B30: -1000 | C30: 0 | D30: 1000 | E30: Own assumption: neutral placeholder. Combined working-capital and other-operating-asset/liability movements have ranged from -CHF 3,647m (FY2022) to +CHF 874m (FY2024) with no stable trend; Nestlé gives no forward guidance on working capital, so a zero net assumption is used rather than an unsupported extrapolation. Scenarios: -CHF 1,000m / +CHF 1,000m. Ranged from -CHF 3,647m (FY2022) to +CHF 874m (FY2024).
A31: Interest Paid (% of Budgeted Financial Expense) | B31: =C31 -> 0.835 | C31: 0.835 | D31: =C31 -> 0.835 | E31: Own assumption: FY2024's historical cash-vs-accrual ratio (interest paid CHF 1,539m ÷ financial expense CHF 1,843m = 83.5%) applied to the FY2025 Budget's financial expense line.
A32: Interest Received (% of Budgeted Financial Income) | B32: =C32 -> 0.763 | C32: 0.763 | D32: =C32 -> 0.763 | E32: Own assumption: FY2024's historical ratio (interest & dividends received CHF 273m ÷ financial income CHF 358m = 76.3%) applied to the FY2025 Budget's financial income line.
A33: Taxes Paid (% of Budgeted Tax Expense) | B33: =C33 -> 0.727 | C33: 0.727 | D33: =C33 -> 0.727 | E33: Own assumption: FY2024's historical cash-vs-accrual ratio (taxes paid CHF 2,411m ÷ tax expense CHF 3,314m = 72.7%) applied to the FY2025 Budget's tax expense line, reflecting normal timing differences between accrued and cash tax.
A34: Associate Dividends Received (% of Budgeted Associate Income) | B34: =C34 -> 0.608 | C34: 0.608 | D34: =C34 -> 0.608 | E34: Own assumption: FY2024's historical ratio (dividends & interest from associates/JVs CHF 759m ÷ income from associates & JVs CHF 1,249m = 60.8%) applied to the FY2025 Budget's associate income line.
A35: Capital Expenditure (% of Sales) | B35: 0.067 | C35: 0.062 | D35: 0.057 | E35: Own assumption: continuation of the rising FY2021–FY2024 capex-intensity trend (5.6% → 5.4% → 6.1% → 6.2% of sales), held at the FY2024 level — Nestlé has not disclosed specific FY2025 capex guidance. Scenarios: 6.7% / 5.7% (±50 bps). Ranged 5.4%–6.2% of sales over FY2021–FY2024.
A36: Intangible Asset Capex (% of Sales) | B36: =C36 -> 0.004 | C36: 0.004 | D36: =C36 -> 0.004 | E36: Own assumption: four-year average ratio (0.53% / 0.28% / 0.53% / 0.36%, avg ≈ 0.42%), rounded to 0.40% of sales.
A37: Acquisitions/Disposals of Businesses, net (CHF m) | B37: =C37 -> 0 | C37: 0 | D37: =C37 -> 0 | E37: Own assumption: no acquisitions or disposals are budgeted, consistent with no M&A guidance being disclosed for FY2025 (mirrors the Net M&A Impact = 0.0% sales assumption above).
A38: Associate Investments, net (% of Sales) | B38: =C38 -> -0.006 | C38: -0.006 | D38: =C38 -> -0.006 | E38: Own assumption: continuation of the recent FY2023–FY2024 level (-CHF 582m / -CHF 532m, both ≈ -0.6% of sales), reflecting ongoing (but not accelerating) investment in associates/JVs such as coffee and pet care ventures.
A39: Divestments in Associates/JVs (CHF m) | B39: =C39 -> 0 | C39: 0 | D39: =C39 -> 0 | E39: Own assumption: zero, consistent with FY2022–FY2024 (all nil). FY2021's CHF 9,294m reflected the one-off partial disposal of Nestlé's L'Oréal stake and is not expected to recur.
A40: Treasury Investments & Other Investing (CHF m) | B40: =C40 -> 0 | C40: 0 | D40: =C40 -> 0 | E40: Own assumption: neutral placeholder. Both lines are treasury-management driven, have swung between large inflows and outflows FY2021–FY2024 (e.g. treasury investments from -CHF 3,610m to +CHF 5,902m), and are not forecastable from sales or guidance.
A41: Dividend Paid to Shareholders Growth (vs FY2024) | B41: =C41 -> 0.02 | C41: 0.02 | D41: =C41 -> 0.02 | E41: Own assumption: Nestlé has a long-standing progressive dividend policy (per-share dividend increased for over two decades); +2.0% is assumed as a modest continuation. No specific FY2025 dividend figure was available at the time of this budget (the dividend for a given year is proposed to shareholders the following February, i.e. after this budget is built).
A42: Dividends to Non-Controlling Interests (CHF m) | B42: =C42 -> -174 | C42: -174 | D42: =C42 -> -174 | E42: Own assumption: held flat at the FY2024 level. This line has ranged CHF -174m to -323m across FY2021–FY2024 with no clear trend and no guidance.
A43: Acquisition of Non-Controlling Interests (CHF m) | B43: =C43 -> 0 | C43: 0 | D43: =C43 -> 0 | E43: Own assumption: zero. This line reflects opportunistic buy-outs of minority stakes (CHF -601m to -27m across FY2021–FY2024, declining) and is not a plannable, recurring item.
A44: Purchase of Treasury Shares (CHF m) | B44: =C44 -> 0 | C44: 0 | D44: =C44 -> 0 | E44: Directly per FY2025 guidance: Nestlé stated it does not anticipate a new share buyback programme in 2025 (consistent with the Shares Outstanding assumption above, which holds the share count flat aside from the already-announced cancellation).
A45: Bond/Long-Term Debt Inflows (CHF m) | B45: =C45 -> 7992 | C45: 7992 | D45: =C45 -> 7992 | E45: Own assumption: held flat at the FY2024 level, reflecting a steady-state refinancing/issuance programme — Nestlé has not disclosed a specific FY2025 debt-issuance plan.
A46: Bond/Lease/Long-Term Debt Outflows (CHF m) | B46: =C46 -> -5055 | C46: -5055 | D46: =C46 -> -5055 | E46: Own assumption: held flat at the FY2024 level, for the same reason as the inflows line above. Net long-term debt financing therefore continues at roughly the FY2024 pace, consistent with the rising net-debt / rising net-financial-expense narrative used elsewhere in this budget.
A47: Short-Term Debt Movement (CHF m) | B47: =C47 -> 0 | C47: 0 | D47: =C47 -> 0 | E47: Own assumption: neutral placeholder. This is the most volatile line in the financing section (CHF -885m to +2,396m across FY2021–FY2024) and is a short-term treasury management decision, not a forecastable business driver.
A48: Currency Retranslation (CHF m) | B48: =C48 -> 0 | C48: 0 | D48: =C48 -> 0 | E48: Own assumption: zero, consistent with the flat (0.0%) FX Impact assumption used for Sales above — no currency-market forecast is being made.
A50: Yellow cells are the editable assumptions. Base is the plan built from Nestlé's FY2025 guidance; Adverse and Favorable flex ten drivers (yellow in those columns) using ranges sized from FY2021–FY2024 history, i.e. only information available on 13-Feb-2025. Every other driver is held at its Base value (grey =Base formulas). Rows marked "→" are memo/formula rows. Change any assumption and 2. Budget_FY2025_PL_CF recalculates.

Sheet 2. Budget_FY2025_PL_CF
A1: Nestlé Group — FY2025 Budget (Adverse / Base / Favorable scenarios) vs FY2024 Actual, full P&L + Cash Flow detail (CHF m unless % or per-share)
A3: Metric | B3: FY2024 Actual | C3: FY2025 Budget — Adverse | D3: FY2025 Budget — Base | E3: FY2025 Budget — Favorable | F3: Base YoY Growth
A4: INCOME STATEMENT
A5: Sales | B5: ='1. Income_Statement'!E4 -> 91354 | C5: =B5*(1+'2. Assumptions_FY2025'!B10) -> 89526.92 | D5: =B5*(1+'2. Assumptions_FY2025'!C10) -> 94094.62 | E5: =B5*(1+'2. Assumptions_FY2025'!D10) -> 96835.24 | F5: =IFERROR(D5/B5-1,"") -> 0.03
A6: Other revenue | B6: ='1. Income_Statement'!E5 -> 366 | C6: =C5*'2. Assumptions_FY2025'!B11 -> 358.10768 | D6: =D5*'2. Assumptions_FY2025'!C11 -> 376.37848 | E6: =E5*'2. Assumptions_FY2025'!D11 -> 387.34096 | F6: =IFERROR(D6/B6-1,"") -> 0.028356503
A7: Cost of goods sold | B7: ='1. Income_Statement'!E6 -> -48670 | C7: =-C5*'2. Assumptions_FY2025'!B12 -> -48255.01 | D7: =-D5*'2. Assumptions_FY2025'!C12 -> -49776.054 | E7: =-E5*'2. Assumptions_FY2025'!D12 -> -50257.49 | F7: =IFERROR(D7/B7-1,"") -> 0.02272558
A8: Distribution expenses | B8: ='1. Income_Statement'!E7 -> -7567 | C8: =-C5*'2. Assumptions_FY2025'!B13 -> -7341.2074 | D8: =-D5*'2. Assumptions_FY2025'!C13 -> -7715.7588 | E8: =-E5*'2. Assumptions_FY2025'!D13 -> -7940.4897 | F8: =IFERROR(D8/B8-1,"") -> 0.019658893
A9: Marketing and administration expenses | B9: ='1. Income_Statement'!E8 -> -18112 | C9: =-C5*'2. Assumptions_FY2025'!B14 -> -19158.761 | D9: =-D5*'2. Assumptions_FY2025'!C14 -> -19665.776 | E9: =-E5*'2. Assumptions_FY2025'!D14 -> -19754.389 | F9: =IFERROR(D9/B9-1,"") -> 0.085787079
A10: Research and development costs | B10: ='1. Income_Statement'!E9 -> -1667 | C10: =-C5*'2. Assumptions_FY2025'!B15 -> -1611.4846 | D10: =-D5*'2. Assumptions_FY2025'!C15 -> -1693.7032 | E10: =-E5*'2. Assumptions_FY2025'!D15 -> -1743.0343 | F10: =IFERROR(D10/B10-1,"") -> 0.016018692
A11: Underlying Trading Operating Profit (UTOP) | B11: ='1. Income_Statement'!E10 -> 15704 | C11: =SUM(C5:C10) -> 13518.565 | D11: =SUM(D5:D10) -> 15619.707 | E11: =SUM(E5:E10) -> 17527.178 | F11: =IFERROR(D11/B11-1,"") -> -0.0053676184
A12: Other trading items, net | B12: ='1. Income_Statement'!E11+'1. Income_Statement'!E12 -> -1071 | C12: =C5*'2. Assumptions_FY2025'!B17 -> -1701.0115 | D12: =D5*'2. Assumptions_FY2025'!C17 -> -1317.3247 | E12: =E5*'2. Assumptions_FY2025'!D17 -> -871.51716 | F12: =IFERROR(D12/B12-1,"") -> 0.22999503
A13: Trading Operating Profit | B13: ='1. Income_Statement'!E13 -> 14633 | C13: =C11+C12 -> 11817.553 | D13: =D11+D12 -> 14302.382 | E13: =E11+E12 -> 16655.661 | F13: =IFERROR(D13/B13-1,"") -> -0.022593983
A14: Other operating items, net | B14: ='1. Income_Statement'!E14+'1. Income_Statement'!E15 -> 91 | C14: =C5*'2. Assumptions_FY2025'!B18 -> -179.05384 | D14: =D5*'2. Assumptions_FY2025'!C18 -> -188.18924 | E14: =E5*'2. Assumptions_FY2025'!D18 -> -193.67048 | F14: =IFERROR(D14/B14-1,"") -> -3.0680136
A15: Operating Profit | B15: ='1. Income_Statement'!E16 -> 14724 | C15: =C13+C14 -> 11638.5 | D15: =D13+D14 -> 14114.193 | E15: =E13+E14 -> 16461.991 | F15: =IFERROR(D15/B15-1,"") -> -0.041415852
A16: Financial income | B16: ='1. Income_Statement'!E17 -> 358 | C16: =B16*(1+'2. Assumptions_FY2025'!B19) -> 358 | D16: =B16*(1+'2. Assumptions_FY2025'!C19) -> 358 | E16: =B16*(1+'2. Assumptions_FY2025'!D19) -> 358 | F16: =IFERROR(D16/B16-1,"") -> 0
A17: Financial expense | B17: ='1. Income_Statement'!E18 -> -1843 | C17: =('1. Income_Statement'!E19*(1+'2. Assumptions_FY2025'!B20))-C16 -> -2065.75 | D17: =('1. Income_Statement'!E19*(1+'2. Assumptions_FY2025'!C20))-D16 -> -1917.25 | E17: =('1. Income_Statement'!E19*(1+'2. Assumptions_FY2025'!D20))-E16 -> -1768.75 | F17: =IFERROR(D17/B17-1,"") -> 0.040287575
A18: Net Financial Income/(Expense) | B18: ='1. Income_Statement'!E19 -> -1485 | C18: =C16+C17 -> -1707.75 | D18: =D16+D17 -> -1559.25 | E18: =E16+E17 -> -1410.75 | F18: =IFERROR(D18/B18-1,"") -> 0.05
A19: Profit Before Taxes, Associates and Joint Ventures | B19: ='1. Income_Statement'!E20 -> 13239 | C19: =C15+C18 -> 9930.7496 | D19: =D15+D18 -> 12554.943 | E19: =E15+E18 -> 15051.241 | F19: =IFERROR(D19/B19-1,"") -> -0.051669839
A20: Income from associates and joint ventures | B20: ='1. Income_Statement'!E21 -> 1249 | C20: =B20*(1+'2. Assumptions_FY2025'!B21) -> 1224.02 | D20: =B20*(1+'2. Assumptions_FY2025'!C21) -> 1348.92 | E20: =B20*(1+'2. Assumptions_FY2025'!D21) -> 1473.82 | F20: =IFERROR(D20/B20-1,"") -> 0.08
A21: Taxes | B21: ='1. Income_Statement'!E22 -> -3314 | C21: =-C19*'2. Assumptions_FY2025'!B22 -> -2581.9949 | D21: =-D19*'2. Assumptions_FY2025'!C22 -> -3013.1863 | E21: =-E19*'2. Assumptions_FY2025'!D22 -> -3311.273 | F21: =IFERROR(D21/B21-1,"") -> -0.090770573
A22: Profit for the Year | B22: ='1. Income_Statement'!E23 -> 11174 | C22: =C19+C20+C21 -> 8572.7747 | D22: =D19+D20+D21 -> 10890.677 | E22: =E19+E20+E21 -> 13213.788 | F22: =IFERROR(D22/B22-1,"") -> -0.025355586
A23: Of which: non-controlling interests | B23: ='1. Income_Statement'!E24 -> 290 | C23: =C22*'2. Assumptions_FY2025'!B23 -> 222.89214 | D23: =D22*'2. Assumptions_FY2025'!C23 -> 283.15759 | E23: =E22*'2. Assumptions_FY2025'!D23 -> 343.55848 | F23: =IFERROR(D23/B23-1,"") -> -0.023594505
A24: Net Profit (attributable to shareholders of the parent) | B24: ='1. Income_Statement'!E25 -> 10884 | C24: =C22-C23 -> 8349.8826 | D24: =D22-D23 -> 10607.519 | E24: =E22-E23 -> 12870.229 | F24: =IFERROR(D24/B24-1,"") -> -0.02540251
A26: UTOP Margin | B26: =IFERROR(B11/B5,"") -> 0.17190271 | C26: =IFERROR(C11/C5,"") -> 0.151 | D26: =IFERROR(D11/D5,"") -> 0.166 | E26: =IFERROR(E11/E5,"") -> 0.181
A27: Trading Operating Profit Margin | B27: =IFERROR(B13/B5,"") -> 0.16017908 | C27: =IFERROR(C13/C5,"") -> 0.132 | D27: =IFERROR(D13/D5,"") -> 0.152 | E27: =IFERROR(E13/E5,"") -> 0.172
A28: Operating Profit Margin | B28: =IFERROR(B15/B5,"") -> 0.16117521 | C28: =IFERROR(C15/C5,"") -> 0.13 | D28: =IFERROR(D15/D5,"") -> 0.15 | E28: =IFERROR(E15/E5,"") -> 0.17
A29: Net Profit Margin | B29: =IFERROR(B24/B5,"") -> 0.11914092 | C29: =IFERROR(C24/C5,"") -> 0.093266724 | D29: =IFERROR(D24/D5,"") -> 0.11273247 | E29: =IFERROR(E24/E5,"") -> 0.13290853
A30: Effective Tax Rate | B30: =IFERROR(-B21/B19,"") -> 0.25032102 | C30: =IFERROR(-C21/C19,"") -> 0.26 | D30: =IFERROR(-D21/D19,"") -> 0.24 | E30: =IFERROR(-E21/E19,"") -> 0.22
A32: Basic EPS (CHF) | B32: ='1. Income_Statement'!E33 -> 4.19 | C32: =IFERROR(C24/'2. Assumptions_FY2025'!B24,"") -> 3.2684396 | D32: =IFERROR(D24/'2. Assumptions_FY2025'!C24,"") -> 4.1521584 | E32: =IFERROR(E24/'2. Assumptions_FY2025'!D24,"") -> 5.0378633
A34: CASH FLOW STATEMENT
A35: OPERATING ACTIVITIES
A36: Operating Profit (linked from Income Statement above) | B36: ='1. Cash_Flow_Statement'!E5 -> 14724 | C36: =C15 -> 11638.5 | D36: =D15 -> 14114.193 | E36: =E15 -> 16461.991 | F36: =IFERROR(D36/B36-1,"") -> -0.041415852
A37: Depreciation and amortization | B37: ='1. Cash_Flow_Statement'!E6 -> 3582 | C37: =C5*'2. Assumptions_FY2025'!B27 -> 3491.5499 | D37: =D5*'2. Assumptions_FY2025'!C27 -> 3669.6902 | E37: =E5*'2. Assumptions_FY2025'!D27 -> 3776.5744 | F37: =IFERROR(D37/B37-1,"") -> 0.024480787
A38: Impairment | B38: ='1. Cash_Flow_Statement'!E7 -> 580 | C38: ='2. Assumptions_FY2025'!B28 -> 580 | D38: ='2. Assumptions_FY2025'!C28 -> 580 | E38: ='2. Assumptions_FY2025'!D28 -> 580 | F38: =IFERROR(D38/B38-1,"") -> 0
A39: Net disposal result & other non-cash items | B39: ='1. Cash_Flow_Statement'!E8+'1. Cash_Flow_Statement'!E9 -> -167 | C39: ='2. Assumptions_FY2025'!B29 -> 0 | D39: ='2. Assumptions_FY2025'!C29 -> 0 | E39: ='2. Assumptions_FY2025'!D29 -> 0 | F39: =IFERROR(D39/B39-1,"") -> -1
A40: Cash Flow Before Changes in Operating Assets and Liabilities | B40: ='1. Cash_Flow_Statement'!E10 -> 18719 | C40: =SUM(C36:C39) -> 15710.049 | D40: =SUM(D36:D39) -> 18363.883 | E40: =SUM(E36:E39) -> 20818.565 | F40: =IFERROR(D40/B40-1,"") -> -0.018970929
A41: Working capital & other operating movements | B41: ='1. Cash_Flow_Statement'!E11+'1. Cash_Flow_Statement'!E12 -> 874 | C41: ='2. Assumptions_FY2025'!B30 -> -1000 | D41: ='2. Assumptions_FY2025'!C30 -> 0 | E41: ='2. Assumptions_FY2025'!D30 -> 1000 | F41: =IFERROR(D41/B41-1,"") -> -1
A42: Cash Generated from Operations | B42: ='1. Cash_Flow_Statement'!E13 -> 19593 | C42: =C40+C41 -> 14710.049 | D42: =D40+D41 -> 18363.883 | E42: =E40+E41 -> 21818.565 | F42: =IFERROR(D42/B42-1,"") -> -0.062732446
A43: Interest paid | B43: ='1. Cash_Flow_Statement'!E14 -> -1539 | C43: =C17*'2. Assumptions_FY2025'!B31 -> -1724.9012 | D43: =D17*'2. Assumptions_FY2025'!C31 -> -1600.9037 | E43: =E17*'2. Assumptions_FY2025'!D31 -> -1476.9062 | F43: =IFERROR(D43/B43-1,"") -> 0.040223359
A44: Interest and dividends received | B44: ='1. Cash_Flow_Statement'!E15 -> 273 | C44: =C16*'2. Assumptions_FY2025'!B32 -> 273.154 | D44: =D16*'2. Assumptions_FY2025'!C32 -> 273.154 | E44: =E16*'2. Assumptions_FY2025'!D32 -> 273.154 | F44: =IFERROR(D44/B44-1,"") -> 0.00056410256
A45: Taxes paid | B45: ='1. Cash_Flow_Statement'!E16 -> -2411 | C45: =C21*'2. Assumptions_FY2025'!B33 -> -1877.1103 | D45: =D21*'2. Assumptions_FY2025'!C33 -> -2190.5865 | E45: =E21*'2. Assumptions_FY2025'!D33 -> -2407.2955 | F45: =IFERROR(D45/B45-1,"") -> -0.091419969
A46: Dividends and interest from associates and joint ventures | B46: ='1. Cash_Flow_Statement'!E17 -> 759 | C46: =C20*'2. Assumptions_FY2025'!B34 -> 744.20416 | D46: =D20*'2. Assumptions_FY2025'!C34 -> 820.14336 | E46: =E20*'2. Assumptions_FY2025'!D34 -> 896.08256 | F46: =IFERROR(D46/B46-1,"") -> 0.080557787
A47: Operating Cash Flow | B47: ='1. Cash_Flow_Statement'!E18 -> 16675 | C47: =C42+C43+C44+C45+C46 -> 12125.396 | D47: =D42+D43+D44+D45+D46 -> 15665.69 | E47: =E42+E43+E44+E45+E46 -> 19103.6 | F47: =IFERROR(D47/B47-1,"") -> -0.060528316
A49: INVESTING ACTIVITIES
A50: Capital expenditure | B50: ='1. Cash_Flow_Statement'!E21 -> -5638 | C50: =-C5*'2. Assumptions_FY2025'!B35 -> -5998.3036 | D50: =-D5*'2. Assumptions_FY2025'!C35 -> -5833.8664 | E50: =-E5*'2. Assumptions_FY2025'!D35 -> -5519.6087 | F50: =IFERROR(D50/B50-1,"") -> 0.034740411
A51: Expenditure on intangible assets | B51: ='1. Cash_Flow_Statement'!E22 -> -325 | C51: =-C5*'2. Assumptions_FY2025'!B36 -> -358.10768 | D51: =-D5*'2. Assumptions_FY2025'!C36 -> -376.37848 | E51: =-E5*'2. Assumptions_FY2025'!D36 -> -387.34096 | F51: =IFERROR(D51/B51-1,"") -> 0.15808763
A52: Acquisition/disposal of businesses, net | B52: ='1. Cash_Flow_Statement'!E23+'1. Cash_Flow_Statement'!E24 -> -832 | C52: ='2. Assumptions_FY2025'!B37 -> 0 | D52: ='2. Assumptions_FY2025'!C37 -> 0 | E52: ='2. Assumptions_FY2025'!D37 -> 0 | F52: =IFERROR(D52/B52-1,"") -> -1
A53: Investments (net) in associates and joint ventures | B53: ='1. Cash_Flow_Statement'!E25 -> -532 | C53: =C5*'2. Assumptions_FY2025'!B38 -> -537.16152 | D53: =D5*'2. Assumptions_FY2025'!C38 -> -564.56772 | E53: =E5*'2. Assumptions_FY2025'!D38 -> -581.01144 | F53: =IFERROR(D53/B53-1,"") -> 0.061217519
A54: Divestments in associates and joint ventures | B54: ='1. Cash_Flow_Statement'!E26 -> 0 | C54: ='2. Assumptions_FY2025'!B39 -> 0 | D54: ='2. Assumptions_FY2025'!C39 -> 0 | E54: ='2. Assumptions_FY2025'!D39 -> 0 | F54: =IFERROR(D54/B54-1,"")
A55: Treasury investments & other investing | B55: ='1. Cash_Flow_Statement'!E27+'1. Cash_Flow_Statement'!E28 -> -1297 | C55: ='2. Assumptions_FY2025'!B40 -> 0 | D55: ='2. Assumptions_FY2025'!C40 -> 0 | E55: ='2. Assumptions_FY2025'!D40 -> 0 | F55: =IFERROR(D55/B55-1,"") -> -1
A56: Investing Cash Flow | B56: ='1. Cash_Flow_Statement'!E29 -> -8624 | C56: =SUM(C50:C55) -> -6893.5728 | D56: =SUM(D50:D55) -> -6774.8126 | E56: =SUM(E50:E55) -> -6487.9611 | F56: =IFERROR(D56/B56-1,"") -> -0.2144234
A58: FINANCING ACTIVITIES
A59: Dividend paid to shareholders of the parent | B59: ='1. Cash_Flow_Statement'!E32 -> -7816 | C59: =B59*(1+'2. Assumptions_FY2025'!B41) -> -7972.32 | D59: =B59*(1+'2. Assumptions_FY2025'!C41) -> -7972.32 | E59: =B59*(1+'2. Assumptions_FY2025'!D41) -> -7972.32 | F59: =IFERROR(D59/B59-1,"") -> 0.02
A60: Dividends paid to non-controlling interests | B60: ='1. Cash_Flow_Statement'!E33 -> -174 | C60: ='2. Assumptions_FY2025'!B42 -> -174 | D60: ='2. Assumptions_FY2025'!C42 -> -174 | E60: ='2. Assumptions_FY2025'!D42 -> -174 | F60: =IFERROR(D60/B60-1,"") -> 0
A61: Acquisition of non-controlling interests | B61: ='1. Cash_Flow_Statement'!E34 -> -27 | C61: ='2. Assumptions_FY2025'!B43 -> 0 | D61: ='2. Assumptions_FY2025'!C43 -> 0 | E61: ='2. Assumptions_FY2025'!D43 -> 0 | F61: =IFERROR(D61/B61-1,"") -> -1
A62: Purchase of treasury shares | B62: ='1. Cash_Flow_Statement'!E35 -> -4678 | C62: ='2. Assumptions_FY2025'!B44 -> 0 | D62: ='2. Assumptions_FY2025'!C44 -> 0 | E62: ='2. Assumptions_FY2025'!D44 -> 0 | F62: =IFERROR(D62/B62-1,"") -> -1
A63: Inflows from bonds and other long-term financial debt | B63: ='1. Cash_Flow_Statement'!E36 -> 7992 | C63: ='2. Assumptions_FY2025'!B45 -> 7992 | D63: ='2. Assumptions_FY2025'!C45 -> 7992 | E63: ='2. Assumptions_FY2025'!D45 -> 7992 | F63: =IFERROR(D63/B63-1,"") -> 0
A64: Outflows from bonds, lease liabilities and other long-term financial debt | B64: ='1. Cash_Flow_Statement'!E37 -> -5055 | C64: ='2. Assumptions_FY2025'!B46 -> -5055 | D64: ='2. Assumptions_FY2025'!C46 -> -5055 | E64: ='2. Assumptions_FY2025'!D46 -> -5055 | F64: =IFERROR(D64/B64-1,"") -> 0
A65: Inflows/(outflows) from short-term financial debt | B65: ='1. Cash_Flow_Statement'!E38 -> 2396 | C65: ='2. Assumptions_FY2025'!B47 -> 0 | D65: ='2. Assumptions_FY2025'!C47 -> 0 | E65: ='2. Assumptions_FY2025'!D47 -> 0 | F65: =IFERROR(D65/B65-1,"") -> -1
A66: Financing Cash Flow | B66: ='1. Cash_Flow_Statement'!E39 -> -7362 | C66: =SUM(C59:C65) -> -5209.32 | D66: =SUM(D59:D65) -> -5209.32 | E66: =SUM(E59:E65) -> -5209.32 | F66: =IFERROR(D66/B66-1,"") -> -0.29240424
A68: CASH RECONCILIATION
A69: Currency retranslations | B69: ='1. Cash_Flow_Statement'!E42 -> 53 | C69: ='2. Assumptions_FY2025'!B48 -> 0 | D69: ='2. Assumptions_FY2025'!C48 -> 0 | E69: ='2. Assumptions_FY2025'!D48 -> 0 | F69: =IFERROR(D69/B69-1,"") -> -1
A70: Increase/(Decrease) in Cash and Cash Equivalents | B70: ='1. Cash_Flow_Statement'!E43 -> 742 | C70: =C47+C56+C66+C69 -> 22.503261 | D70: =D47+D56+D66+D69 -> 3681.5577 | E70: =E47+E56+E66+E69 -> 7406.3189 | F70: =IFERROR(D70/B70-1,"") -> 3.9616681
A71: Cash and cash equivalents at beginning of year | B71: ='1. Cash_Flow_Statement'!E44 -> 4816 | C71: ='1. Cash_Flow_Statement'!E45 -> 5558 | D71: ='1. Cash_Flow_Statement'!E45 -> 5558 | E71: ='1. Cash_Flow_Statement'!E45 -> 5558 | F71: =IFERROR(D71/B71-1,"") -> 0.15406977
A72: Cash and Cash Equivalents at End of Year | B72: ='1. Cash_Flow_Statement'!E45 -> 5558 | C72: =C70+C71 -> 5580.5033 | D72: =D70+D71 -> 9239.5577 | E72: =E70+E71 -> 12964.319 | F72: =IFERROR(D72/B72-1,"") -> 0.66238893
A74: MEMO: FREE CASH FLOW
A75: Free Cash Flow (derived: Operating CF − Capex − Intangible capex) | B75: ='1. Cash_Flow_Statement'!E51 -> 10712 | C75: =C47+C50+C51 -> 5768.9848 | D75: =D47+D50+D51 -> 9455.4454 | E75: =E47+E50+E51 -> 13196.65 | F75: =IFERROR(D75/B75-1,"") -> -0.11730345
A76: Free Cash Flow Margin | B76: =IFERROR(B75/B5,"") -> 0.11725814 | C76: =IFERROR(C75/C5,"") -> 0.064438549 | D76: =IFERROR(D75/D5,"") -> 0.10048869 | E76: =IFERROR(E75/E5,"") -> 0.13627942
A78: Column B ("FY2024 Actual") links directly to 1. Income_Statement and 1. Cash_Flow_Statement — it is not retyped. Columns C–E are the FY2025 Budget under three scenarios, each driven by the matching column of 2. Assumptions_FY2025 (Adverse / Base / Favorable). Change any assumption there and this whole sheet recalculates. The Base scenario is the plan that 3. Variance_Analysis compares against FY2025 Actual.
A79: This budget is built at the same line-item level of detail as Income_Statement and Cash_Flow_Statement (full statutory P&L and Cash Flow). Lines with no forecastable business driver and no company guidance (e.g. treasury investments, short-term debt movements, non-cash disposal items) are explicitly assumed flat/neutral rather than given spurious precision — see each driver's rationale in Assumptions_FY2025.
A80: "Other trading items, net" and "Other operating items, net" are budgeted on a combined net basis (income − expense), unlike the split presentation in Income_Statement, since FY2025 guidance does not provide separate visibility into these one-off/restructuring components.
A81: In the Base scenario, budgeted ending cash rises materially (CHF 5,558m -> CHF 9,240m, +66%) versus FY2024 mainly because two large one-off FY2024 cash outflows are assumed not to repeat: the CHF 4,678m share buyback (per guidance, no new buyback programme is planned for 2025) and CHF 832m/1,297m of M&A and treasury-investment outflows (no acquisitions are budgeted for FY2025). This is a mechanical consequence of the guidance-based assumptions above, not a hidden cash-generation improvement in the underlying business — Operating Cash Flow is actually budgeted slightly lower than FY2024 (CHF 15,666m vs CHF 16,675m).
A82: This is a Budget built from Nestlé's own FY2025 guidance as disclosed on 13-Feb-2025, BEFORE FY2025 actual results were known — it deliberately does not use hindsight. Step 3 of this project (Variance Analysis) will compare this Budget against Nestlé's actual FY2025 results once published.

Sheet 3. Variance_Analysis
A1: Nestlé Group — FY2025 Budget vs FY2025 Actual — Variance Analysis (CHF m unless % or per-share)
A3: A. GROUP SALES GROWTH BRIDGE — FY2025 BUDGET VS ACTUAL (RIG / PRICING SPLIT)
A5: Component | B5: FY2025 Budget (Base) | C5: FY2025 Actual | D5: Variance (bps)
A6: Real Internal Growth (RIG) | B6: ='2. Assumptions_FY2025'!C5 -> 0.015 | C6: 0.008 | D6: =(C6-B6)*10000 -> -70
A7: Pricing | B7: ='2. Assumptions_FY2025'!C6 -> 0.015 | C7: 0.028 | D7: =(C7-B7)*10000 -> 130
A8: Organic Growth | B8: ='2. Assumptions_FY2025'!C7 -> 0.03 | C8: 0.035 | D8: =(C8-B8)*10000 -> 50
A9: Net M&A Impact | B9: ='2. Assumptions_FY2025'!C8 -> 0 | C9: 0.001 | D9: =(C9-B9)*10000 -> 10
A10: Foreign Exchange (FX) Impact | B10: ='2. Assumptions_FY2025'!C9 -> 0 | C10: -0.057 | D10: =(C10-B10)*10000 -> -570
A11: Reported Sales Growth | B11: =B8+B9+B10 -> 0.03 | C11: =C16/'2. Budget_FY2025_PL_CF'!B5-1 -> -0.020404142 | D11: =(C11-B11)*10000 -> -504.04142
A12: RIG, Pricing, Organic Growth, Net M&A and FX are Nestlé's own disclosed figures, each rounded to 0.1 percentage point, so they do not sum exactly; FY2025 Actual Reported Sales Growth is calculated directly from the Sales lines (Section B).
A14: B. FULL INCOME STATEMENT VARIANCE — FY2025 BUDGET VS ACTUAL (CHF m)
A15: Metric | B15: FY2025 Budget (Base) | C15: FY2025 Actual | D15: Variance (CHF m) | E15: Variance (%)
A16: Sales | B16: ='2. Budget_FY2025_PL_CF'!D5 -> 94094.62 | C16: 89490 | D16: =C16-B16 -> -4604.62 | E16: =IFERROR(C16/B16-1,"") -> -0.04893606
A17: Other revenue | B17: ='2. Budget_FY2025_PL_CF'!D6 -> 376.37848 | C17: 395 | D17: =C17-B17 -> 18.62152 | E17: =IFERROR(C17/B17-1,"") -> 0.049475517
A18: Cost of goods sold | B18: ='2. Budget_FY2025_PL_CF'!D7 -> -49776.054 | C18: -48694 | D18: =C18-B18 -> 1082.054 | E18: =IFERROR(C18/B18-1,"") -> -0.021738444
A19: Distribution expenses | B19: ='2. Budget_FY2025_PL_CF'!D8 -> -7715.7588 | C19: -7306 | D19: =C19-B19 -> 409.75884 | E19: =IFERROR(C19/B19-1,"") -> -0.053106745
A20: Marketing and administration expenses | B20: ='2. Budget_FY2025_PL_CF'!D9 -> -19665.776 | C20: -17883 | D20: =C20-B20 -> 1782.7756 | E20: =IFERROR(C20/B20-1,"") -> -0.090653713
A21: Research and development costs | B21: ='2. Budget_FY2025_PL_CF'!D10 -> -1693.7032 | C21: -1613 | D21: =C21-B21 -> 80.70316 | E21: =IFERROR(C21/B21-1,"") -> -0.04764894
A22: Underlying Trading Operating Profit (UTOP) | B22: ='2. Budget_FY2025_PL_CF'!D11 -> 15619.707 | C22: =SUM(C16:C21) -> 14389 | D22: =C22-B22 -> -1230.7069 | E22: =IFERROR(C22/B22-1,"") -> -0.078791934
A23: Other trading items, net | B23: ='2. Budget_FY2025_PL_CF'!D12 -> -1317.3247 | C23: -1714 | D23: =C23-B23 -> -396.67532 | E23: =IFERROR(C23/B23-1,"") -> 0.30112191
A24: Trading Operating Profit | B24: ='2. Budget_FY2025_PL_CF'!D13 -> 14302.382 | C24: =C22+C23 -> 12675 | D24: =C24-B24 -> -1627.3822 | E24: =IFERROR(C24/B24-1,"") -> -0.113784
A25: Other operating items, net | B25: ='2. Budget_FY2025_PL_CF'!D14 -> -188.18924 | C25: -398 | D25: =C25-B25 -> -209.81076 | E25: =IFERROR(C25/B25-1,"") -> 1.1148924
A26: Operating Profit | B26: ='2. Budget_FY2025_PL_CF'!D15 -> 14114.193 | C26: =C24+C25 -> 12277 | D26: =C26-B26 -> -1837.193 | E26: =IFERROR(C26/B26-1,"") -> -0.13016635
A27: Financial income | B27: ='2. Budget_FY2025_PL_CF'!D16 -> 358 | C27: 300 | D27: =C27-B27 -> -58 | E27: =IFERROR(C27/B27-1,"") -> -0.16201117
A28: Financial expense | B28: ='2. Budget_FY2025_PL_CF'!D17 -> -1917.25 | C28: -1826 | D28: =C28-B28 -> 91.25 | E28: =IFERROR(C28/B28-1,"") -> -0.04759421
A29: Net Financial Income/(Expense) | B29: ='2. Budget_FY2025_PL_CF'!D18 -> -1559.25 | C29: =C27+C28 -> -1526 | D29: =C29-B29 -> 33.25 | E29: =IFERROR(C29/B29-1,"") -> -0.021324355
A30: Profit Before Taxes, Associates and Joint Ventures | B30: ='2. Budget_FY2025_PL_CF'!D19 -> 12554.943 | C30: =C26+C29 -> 10751 | D30: =C30-B30 -> -1803.943 | E30: =IFERROR(C30/B30-1,"") -> -0.14368389
A31: Income from associates and joint ventures | B31: ='2. Budget_FY2025_PL_CF'!D20 -> 1348.92 | C31: 1143 | D31: =C31-B31 -> -205.92 | E31: =IFERROR(C31/B31-1,"") -> -0.15265546
A32: Taxes | B32: ='2. Budget_FY2025_PL_CF'!D21 -> -3013.1863 | C32: -2640 | D32: =C32-B32 -> 373.18632 | E32: =IFERROR(C32/B32-1,"") -> -0.12385106
A33: Profit for the Year | B33: ='2. Budget_FY2025_PL_CF'!D22 -> 10890.677 | C33: =C30+C31+C32 -> 9254 | D33: =C33-B33 -> -1636.6767 | E33: =IFERROR(C33/B33-1,"") -> -0.15028237
A34: Of which: non-controlling interests | B34: ='2. Budget_FY2025_PL_CF'!D23 -> 283.15759 | C34: 221 | D34: =C34-B34 -> -62.157594 | E34: =IFERROR(C34/B34-1,"") -> -0.2195159
A35: Net Profit (attributable to shareholders of the parent) | B35: ='2. Budget_FY2025_PL_CF'!D24 -> 10607.519 | C35: =C33-C34 -> 9033 | D35: =C35-B35 -> -1574.5191 | E35: =IFERROR(C35/B35-1,"") -> -0.14843424
A37: UTOP Margin | B37: =IFERROR(B22/B16,"") -> 0.166 | C37: =IFERROR(C22/C16,"") -> 0.16078891 | D37: =(C37-B37)*10000 -> -52.11085
A38: Trading Operating Profit Margin | B38: =IFERROR(B24/B16,"") -> 0.152 | C38: =IFERROR(C24/C16,"") -> 0.14163594 | D38: =(C38-B38)*10000 -> -103.64063
A39: Operating Profit Margin | B39: =IFERROR(B26/B16,"") -> 0.15 | C39: =IFERROR(C26/C16,"") -> 0.13718851 | D39: =(C39-B39)*10000 -> -128.11487
A40: Net Profit Margin | B40: =IFERROR(B35/B16,"") -> 0.11273247 | C40: =IFERROR(C35/C16,"") -> 0.10093865 | D40: =(C40-B40)*10000 -> -117.93819
A41: Effective Tax Rate | B41: =IFERROR(-B32/B30,"") -> 0.24 | C41: =IFERROR(-C32/C30,"") -> 0.24555855 | D41: =(C41-B41)*10000 -> 55.585527
A43: Basic EPS (CHF) | B43: ='2. Budget_FY2025_PL_CF'!D32 -> 4.1521584 | C43: 3.51 | D43: =C43-B43 -> -0.64215841 | E43: =IFERROR(C43/B43-1,"") -> -0.15465653
A45: "Other trading items, net" and "Other operating items, net" are shown net for FY2025 Actual (row 23: other trading income 135 − other trading expenses 1,849; row 25: other operating income 253 − other operating expenses 651), matching the combined-net convention already used for these lines in 2. Budget_FY2025_PL_CF.
A47: C. FULL CASH FLOW VARIANCE — FY2025 BUDGET VS ACTUAL (CHF m)
A48: Metric | B48: FY2025 Budget (Base) | C48: FY2025 Actual | D48: Variance (CHF m) | E48: Variance (%)
A50: OPERATING ACTIVITIES
A51: Operating Profit (linked from Income Statement above) | B51: ='2. Budget_FY2025_PL_CF'!D36 -> 14114.193 | C51: =C26 -> 12277 | D51: =C51-B51 -> -1837.193 | E51: =IFERROR(C51/B51-1,"") -> -0.13016635
A52: Depreciation and amortization | B52: ='2. Budget_FY2025_PL_CF'!D37 -> 3669.6902 | C52: 3633 | D52: =C52-B52 -> -36.69018 | E52: =IFERROR(C52/B52-1,"") -> -0.0099981683
A53: Impairment | B53: ='2. Budget_FY2025_PL_CF'!D38 -> 580 | C53: 923 | D53: =C53-B53 -> 343 | E53: =IFERROR(C53/B53-1,"") -> 0.59137931
A54: Net disposal result & other non-cash items | B54: ='2. Budget_FY2025_PL_CF'!D39 -> 0 | C54: 347 | D54: =C54-B54 -> 347 | E54: =IFERROR(C54/B54-1,"")
A55: Cash Flow Before Changes in Operating Assets and Liabilities | B55: ='2. Budget_FY2025_PL_CF'!D40 -> 18363.883 | C55: =SUM(C51:C54) -> 17180 | D55: =C55-B55 -> -1183.8832 | E55: =IFERROR(C55/B55-1,"") -> -0.06446802
A56: Working capital & other operating movements | B56: ='2. Budget_FY2025_PL_CF'!D41 -> 0 | C56: -319 | D56: =C56-B56 -> -319 | E56: =IFERROR(C56/B56-1,"")
A57: Cash Generated from Operations | B57: ='2. Budget_FY2025_PL_CF'!D42 -> 18363.883 | C57: =C55+C56 -> 16861 | D57: =C57-B57 -> -1502.8832 | E57: =IFERROR(C57/B57-1,"") -> -0.081839073
A58: Interest paid | B58: ='2. Budget_FY2025_PL_CF'!D43 -> -1600.9037 | C58: -1618 | D58: =C58-B58 -> -17.09625 | E58: =IFERROR(C58/B58-1,"") -> 0.010679124
A59: Interest and dividends received | B59: ='2. Budget_FY2025_PL_CF'!D44 -> 273.154 | C59: 205 | D59: =C59-B59 -> -68.154 | E59: =IFERROR(C59/B59-1,"") -> -0.2495076
A60: Taxes paid | B60: ='2. Budget_FY2025_PL_CF'!D45 -> -2190.5865 | C60: -2298 | D60: =C60-B60 -> -107.41355 | E60: =IFERROR(C60/B60-1,"") -> 0.04903415
A61: Dividends and interest from associates and joint ventures | B61: ='2. Budget_FY2025_PL_CF'!D46 -> 820.14336 | C61: 2754 | D61: =C61-B61 -> 1933.8566 | E61: =IFERROR(C61/B61-1,"") -> 2.3579495
A62: Operating Cash Flow | B62: ='2. Budget_FY2025_PL_CF'!D47 -> 15665.69 | C62: =C57+C58+C59+C60+C61 -> 15904 | D62: =C62-B62 -> 238.30966 | E62: =IFERROR(C62/B62-1,"") -> 0.015212203
A64: INVESTING ACTIVITIES
A65: Capital expenditure | B65: ='2. Budget_FY2025_PL_CF'!D50 -> -5833.8664 | C65: -4527 | D65: =C65-B65 -> 1306.8664 | E65: =IFERROR(C65/B65-1,"") -> -0.22401377
A66: Expenditure on intangible assets | B66: ='2. Budget_FY2025_PL_CF'!D51 -> -376.37848 | C66: -384 | D66: =C66-B66 -> -7.62152 | E66: =IFERROR(C66/B66-1,"") -> 0.020249617
A67: Acquisition/disposal of businesses, net | B67: ='2. Budget_FY2025_PL_CF'!D52 -> 0 | C67: -156 | D67: =C67-B67 -> -156 | E67: =IFERROR(C67/B67-1,"")
A68: Investments (net) in associates and joint ventures | B68: ='2. Budget_FY2025_PL_CF'!D53 -> -564.56772 | C68: 208 | D68: =C68-B68 -> 772.56772 | E68: =IFERROR(C68/B68-1,"") -> -1.3684235
A69: Divestments in associates and joint ventures | B69: ='2. Budget_FY2025_PL_CF'!D54 -> 0 | C69: 0 | D69: =C69-B69 -> 0 | E69: =IFERROR(C69/B69-1,"")
A70: Treasury investments & other investing | B70: ='2. Budget_FY2025_PL_CF'!D55 -> 0 | C70: 492 | D70: =C70-B70 -> 492 | E70: =IFERROR(C70/B70-1,"")
A71: Investing Cash Flow | B71: ='2. Budget_FY2025_PL_CF'!D56 -> -6774.8126 | C71: =SUM(C65:C70) -> -4367 | D71: =C71-B71 -> 2407.8126 | E71: =IFERROR(C71/B71-1,"") -> -0.35540653
A73: FINANCING ACTIVITIES
A74: Dividend paid to shareholders of the parent | B74: ='2. Budget_FY2025_PL_CF'!D59 -> -7972.32 | C74: -7849 | D74: =C74-B74 -> 123.32 | E74: =IFERROR(C74/B74-1,"") -> -0.015468521
A75: Dividends paid to non-controlling interests | B75: ='2. Budget_FY2025_PL_CF'!D60 -> -174 | C75: -172 | D75: =C75-B75 -> 2 | E75: =IFERROR(C75/B75-1,"") -> -0.011494253
A76: Acquisition of non-controlling interests | B76: ='2. Budget_FY2025_PL_CF'!D61 -> 0 | C76: -1190 | D76: =C76-B76 -> -1190 | E76: =IFERROR(C76/B76-1,"")
A77: Purchase of treasury shares | B77: ='2. Budget_FY2025_PL_CF'!D62 -> 0 | C77: -213 | D77: =C77-B77 -> -213 | E77: =IFERROR(C77/B77-1,"")
A78: Inflows from bonds and other long-term financial debt | B78: ='2. Budget_FY2025_PL_CF'!D63 -> 7992 | C78: 2803 | D78: =C78-B78 -> -5189 | E78: =IFERROR(C78/B78-1,"") -> -0.64927427
A79: Outflows from bonds, lease liabilities and other long-term financial debt | B79: ='2. Budget_FY2025_PL_CF'!D64 -> -5055 | C79: -4408 | D79: =C79-B79 -> 647 | E79: =IFERROR(C79/B79-1,"") -> -0.12799209
A80: Inflows/(outflows) from short-term financial debt | B80: ='2. Budget_FY2025_PL_CF'!D65 -> 0 | C80: -1036 | D80: =C80-B80 -> -1036 | E80: =IFERROR(C80/B80-1,"")
A81: Financing Cash Flow | B81: ='2. Budget_FY2025_PL_CF'!D66 -> -5209.32 | C81: =SUM(C74:C80) -> -12065 | D81: =C81-B81 -> -6855.68 | E81: =IFERROR(C81/B81-1,"") -> 1.3160412
A83: CASH RECONCILIATION
A84: Currency retranslations | B84: ='2. Budget_FY2025_PL_CF'!D69 -> 0 | C84: -435 | D84: =C84-B84 -> -435 | E84: =IFERROR(C84/B84-1,"")
A85: Increase/(Decrease) in Cash and Cash Equivalents | B85: ='2. Budget_FY2025_PL_CF'!D70 -> 3681.5577 | C85: =C62+C71+C81+C84 -> -963 | D85: =C85-B85 -> -4644.5577 | E85: =IFERROR(C85/B85-1,"") -> -1.2615741
A86: Cash and cash equivalents at beginning of year | B86: ='2. Budget_FY2025_PL_CF'!D71 -> 5558 | C86: ='1. Cash_Flow_Statement'!E45 -> 5558 | D86: =C86-B86 -> 0 | E86: =IFERROR(C86/B86-1,"") -> 0
A87: Cash and Cash Equivalents at End of Year | B87: ='2. Budget_FY2025_PL_CF'!D72 -> 9239.5577 | C87: =C85+C86 -> 4595 | D87: =C87-B87 -> -4644.5577 | E87: =IFERROR(C87/B87-1,"") -> -0.50268182
A89: MEMO: FREE CASH FLOW
A90: Free Cash Flow (as reported by Nestlé) | B90: ='2. Budget_FY2025_PL_CF'!D75 -> 9455.4454 | C90: 9154 | D90: =C90-B90 -> -301.44542 | E90: =IFERROR(C90/B90-1,"") -> -0.031880615
A91: Free Cash Flow (derived: Operating CF − Capex − Intangible capex) | B91: ='2. Budget_FY2025_PL_CF'!D75 -> 9455.4454 | C91: =C62+C65+C66 -> 10993 | D91: =C91-B91 -> 1537.5546 | E91: =IFERROR(C91/B91-1,"") -> 0.16261049
A92: Free Cash Flow Margin (as reported) | B92: =IFERROR(B90/B16,"") -> 0.10048869 | C92: =IFERROR(C90/C16,"") -> 0.10229076 | D92: =(C92-B92)*10000 -> 18.020654
A94: "Acquisition/disposal of businesses, net" (row 67) combines acquisitions (-75) and disposals of businesses (-81). "Treasury investments & other investing" (row 70) combines treasury investments (424), a new FY2025 "long-term investments acquisition" line (-70) not separately budgeted, and other investing items (138) — folded together for comparability with the Budget's combined structure.
A95: As with FY2021–FY2024 (see 1. Cash_Flow_Statement), Free Cash Flow "as reported" by Nestlé does not tie out exactly to the derived figure (Operating CF − Capex − Intangible capex) — Nestlé's own FCF definition includes further adjustments it does not separately disclose. Both are shown for FY2025 for the same reason.
A97: D. ACTUAL VS BUDGET SCENARIOS — WHERE DID FY2025 LAND?
A98: Metric | B98: Budget — Adverse | C98: Budget — Base | D98: Budget — Favorable | E98: FY2025 Actual | F98: Position
A99: Sales | B99: ='2. Budget_FY2025_PL_CF'!C5 -> 89526.92 | C99: ='2. Budget_FY2025_PL_CF'!D5 -> 94094.62 | D99: ='2. Budget_FY2025_PL_CF'!E5 -> 96835.24 | E99: =C16 -> 89490 | F99: =IF(E99<MIN(B99,D99),"Below Adverse",IF(E99>MAX(B99,D99),"Above Favorable",IF(E99<C99,"Between Adverse and Base","Between Base and Favorable"))) -> Below Adverse
A100: Underlying Trading Operating Profit (UTOP) | B100: ='2. Budget_FY2025_PL_CF'!C11 -> 13518.565 | C100: ='2. Budget_FY2025_PL_CF'!D11 -> 15619.707 | D100: ='2. Budget_FY2025_PL_CF'!E11 -> 17527.178 | E100: =C22 -> 14389 | F100: =IF(E100<MIN(B100,D100),"Below Adverse",IF(E100>MAX(B100,D100),"Above Favorable",IF(E100<C100,"Between Adverse and Base","Between Base and Favorable"))) -> Between Adverse and Base
A101: UTOP Margin | B101: ='2. Budget_FY2025_PL_CF'!C26 -> 0.151 | C101: ='2. Budget_FY2025_PL_CF'!D26 -> 0.166 | D101: ='2. Budget_FY2025_PL_CF'!E26 -> 0.181 | E101: =C37 -> 0.16078891 | F101: =IF(E101<MIN(B101,D101),"Below Adverse",IF(E101>MAX(B101,D101),"Above Favorable",IF(E101<C101,"Between Adverse and Base","Between Base and Favorable"))) -> Between Adverse and Base
A102: Operating Profit | B102: ='2. Budget_FY2025_PL_CF'!C15 -> 11638.5 | C102: ='2. Budget_FY2025_PL_CF'!D15 -> 14114.193 | D102: ='2. Budget_FY2025_PL_CF'!E15 -> 16461.991 | E102: =C26 -> 12277 | F102: =IF(E102<MIN(B102,D102),"Below Adverse",IF(E102>MAX(B102,D102),"Above Favorable",IF(E102<C102,"Between Adverse and Base","Between Base and Favorable"))) -> Between Adverse and Base
A103: Net Profit | B103: ='2. Budget_FY2025_PL_CF'!C24 -> 8349.8826 | C103: ='2. Budget_FY2025_PL_CF'!D24 -> 10607.519 | D103: ='2. Budget_FY2025_PL_CF'!E24 -> 12870.229 | E103: =C35 -> 9033 | F103: =IF(E103<MIN(B103,D103),"Below Adverse",IF(E103>MAX(B103,D103),"Above Favorable",IF(E103<C103,"Between Adverse and Base","Between Base and Favorable"))) -> Between Adverse and Base
A104: Basic EPS (CHF) | B104: ='2. Budget_FY2025_PL_CF'!C32 -> 3.2684396 | C104: ='2. Budget_FY2025_PL_CF'!D32 -> 4.1521584 | D104: ='2. Budget_FY2025_PL_CF'!E32 -> 5.0378633 | E104: =C43 -> 3.51 | F104: =IF(E104<MIN(B104,D104),"Below Adverse",IF(E104>MAX(B104,D104),"Above Favorable",IF(E104<C104,"Between Adverse and Base","Between Base and Favorable"))) -> Between Adverse and Base
A105: Operating Cash Flow | B105: ='2. Budget_FY2025_PL_CF'!C47 -> 12125.396 | C105: ='2. Budget_FY2025_PL_CF'!D47 -> 15665.69 | D105: ='2. Budget_FY2025_PL_CF'!E47 -> 19103.6 | E105: =C62 -> 15904 | F105: =IF(E105<MIN(B105,D105),"Below Adverse",IF(E105>MAX(B105,D105),"Above Favorable",IF(E105<C105,"Between Adverse and Base","Between Base and Favorable"))) -> Between Base and Favorable
A106: Free Cash Flow (derived) | B106: ='2. Budget_FY2025_PL_CF'!C75 -> 5768.9848 | C106: ='2. Budget_FY2025_PL_CF'!D75 -> 9455.4454 | D106: ='2. Budget_FY2025_PL_CF'!E75 -> 13196.65 | E106: =C91 -> 10993 | F106: =IF(E106<MIN(B106,D106),"Below Adverse",IF(E106>MAX(B106,D106),"Above Favorable",IF(E106<C106,"Between Adverse and Base","Between Base and Favorable"))) -> Between Base and Favorable
A107: Budget scenarios link to 2. Budget_FY2025_PL_CF (columns C–E); FY2025 Actual links to Sections B–C above. Base is the plan the variance in Sections A–C is measured against; Adverse and Favorable were built at the same time (13-Feb-2025) from FY2021–FY2024 history.
A109: E. ASSUMPTION BACKTEST — FY2025 ACTUAL DRIVERS VS SCENARIO RANGES
A110: Driver | B110: Adverse | C110: Base | D110: Favorable | E110: FY2025 Actual | F110: Result
A111: ='2. Assumptions_FY2025'!A5 -> Real Internal Growth (RIG) — volume/mix | B111: ='2. Assumptions_FY2025'!B5 -> 0.005 | C111: ='2. Assumptions_FY2025'!C5 -> 0.015 | D111: ='2. Assumptions_FY2025'!D5 -> 0.025 | E111: =C6 -> 0.008 | F111: =IF(AND(E111>=MIN(B111,D111),E111<=MAX(B111,D111)),"Within scenario range",IF((E111-C111)*(B111-C111)>0,"Worse than Adverse","Better than Favorable")) -> Within scenario range
A112: ='2. Assumptions_FY2025'!A9 -> Foreign Exchange (FX) Impact | B112: ='2. Assumptions_FY2025'!B9 -> -0.04 | C112: ='2. Assumptions_FY2025'!C9 -> 0 | D112: ='2. Assumptions_FY2025'!D9 -> 0.02 | E112: =C10 -> -0.057 | F112: =IF(AND(E112>=MIN(B112,D112),E112<=MAX(B112,D112)),"Within scenario range",IF((E112-C112)*(B112-C112)>0,"Worse than Adverse","Better than Favorable")) -> Worse than Adverse
A113: ='2. Assumptions_FY2025'!A12 -> Cost of Goods Sold (% of Sales) | B113: ='2. Assumptions_FY2025'!B12 -> 0.539 | C113: ='2. Assumptions_FY2025'!C12 -> 0.529 | D113: ='2. Assumptions_FY2025'!D12 -> 0.519 | E113: =-C18/C16 -> 0.54412784 | F113: =IF(AND(E113>=MIN(B113,D113),E113<=MAX(B113,D113)),"Within scenario range",IF((E113-C113)*(B113-C113)>0,"Worse than Adverse","Better than Favorable")) -> Worse than Adverse
A114: ='2. Assumptions_FY2025'!A14 -> Marketing & Administration Expenses (% of Sales) | B114: ='2. Assumptions_FY2025'!B14 -> 0.214 | C114: ='2. Assumptions_FY2025'!C14 -> 0.209 | D114: ='2. Assumptions_FY2025'!D14 -> 0.204 | E114: =-C20/C16 -> 0.19983238 | F114: =IF(AND(E114>=MIN(B114,D114),E114<=MAX(B114,D114)),"Within scenario range",IF((E114-C114)*(B114-C114)>0,"Worse than Adverse","Better than Favorable")) -> Better than Favorable
A115: ='2. Assumptions_FY2025'!A17 -> Other Trading Items, net (% of Sales) | B115: ='2. Assumptions_FY2025'!B17 -> -0.019 | C115: ='2. Assumptions_FY2025'!C17 -> -0.014 | D115: ='2. Assumptions_FY2025'!D17 -> -0.009 | E115: =C23/C16 -> -0.019152978 | F115: =IF(AND(E115>=MIN(B115,D115),E115<=MAX(B115,D115)),"Within scenario range",IF((E115-C115)*(B115-C115)>0,"Worse than Adverse","Better than Favorable")) -> Worse than Adverse
...

Sheet 4. Assumptions_FY2026
A1: Nestlé — FY2026 Reforecast Assumptions (full year, as of 23-Jul-2026)
A2: Where Nestlé has guided a number (latest: Half-Year Results 2026, 23-Jul-2026), the reforecast uses it. Everything else is a judgement informed by the FY2025 variance and the H1-2026 actuals, never a copy of FY2025.
A3: Driver | B3: FY2025 Budget (Base) | C3: FY2025 Actual | D3: FY2026 Reforecast | E3: H1-2026 Actual | F3: Source / rationale
A4: A. INCOME STATEMENT DRIVERS
A5: Real Internal Growth (RIG) | B5: ='2. Assumptions_FY2025'!C5 -> 0.015 | C5: ='3. Variance_Analysis'!C6 -> 0.008 | D5: 0.016 | E5: 0.015 | F5: [Judgement] Guidance (23-Jul-2026): RIG "accelerating versus 2025" (0.8%). H1-2026 RIG was 1.5% (Q1 1.2%, Q2 1.8%) and the infant-formula recall drag is fading (-90 bps on OG in Q1, -30 bps in Q2): 1.6% for the year. The FY2025 budget over-estimated volume (1.5% vs 0.8%), so this stays below the Q2 run-rate.
A6: Pricing | B6: ='2. Assumptions_FY2025'!C6 -> 0.015 | C6: ='3. Variance_Analysis'!C7 -> 0.028 | D6: 0.019 | E6: 0.021 | F6: [Judgement] The FY2025 budget under-estimated pricing by 130 bps. Pricing is now easing as coffee and cocoa costs fall (Q1-2026 2.3%, Q2 1.9%), so 1.9% for the year.
A7: → Organic Sales Growth (RIG + Pricing) | B7: ='2. Assumptions_FY2025'!C7 -> 0.03 | C7: ='3. Variance_Analysis'!C8 -> 0.035 | D7: =D5+D6 -> 0.035 | E7: 0.036 | F7: Formula: 3.5%, inside Nestlé's guidance "OG expected to be in the range of 3% to 4%" (Half-Year Results press release, 23-Jul-2026).
A8: Net M&A Impact | B8: ='2. Assumptions_FY2025'!C8 -> 0 | C8: ='3. Variance_Analysis'!C9 -> 0.001 | D8: 0.001 | E8: 0.001 | F8: [Judgement] H1-2026 net M&A was +0.1%; no disposal is expected to close in 2026 (the waters JV is expected to close in H1-2027; the VMS and ice cream processes are still in progress), so +0.1% for the year.
A9: Foreign Exchange (FX) Impact | B9: ='2. Assumptions_FY2025'!C9 -> 0 | C9: ='3. Variance_Analysis'!C10 -> -0.057 | D9: ='4. Assumptions_FY2026'!D56 -> -0.03 | E9: -0.062 | F9: [Guided] "Based on current spot rates, we expect the impact of foreign exchange movements on sales to be approximately -3%" (Half-Year Results press release, 23-Jul-2026). FX was the largest FY2025 miss (0% budgeted vs -5.7% actual) and is one of the two drivers stress-tested in 4. Sensitivity_FY2026.
A10: → Implied Reported Sales Growth | B10: ='2. Assumptions_FY2025'!C10 -> 0.03 | C10: ='3. Variance_Analysis'!C11 -> -0.020404142 | D10: =D7+D8+D9 -> 0.006 | E10: -0.025 | F10: Formula: Organic Sales Growth + Net M&A + FX, applied to FY2025 actual sales.
A11: Other Revenue (% of Sales) | B11: ='2. Assumptions_FY2025'!C11 -> 0.004 | C11: ='3. Variance_Analysis'!C17/'3. Variance_Analysis'!C16 -> 0.004413901 | D11: 0.0045 | E11: 0.0044 | F11: [Judgement] Small and stable line (0.44% in FY2025 and in H1-2026), edging up with the H1 trend (+4% in CHF while sales fell 2.5%): 0.45%.
A12: Cost of Goods Sold (% of Sales) | B12: ='2. Assumptions_FY2025'!C12 -> 0.529 | C12: =-'3. Variance_Analysis'!C18/'3. Variance_Analysis'!C16 -> 0.54412784 | D12: 0.536 | E12: 0.536 | F12: [Guided] Guidance: UTOP margin to improve versus 2025, with the "second half margin now expected to be broadly similar to the first half" — so the full-year cost ratios follow H1-2026. COGS 53.6% vs 54.4% in FY2025: lower coffee and cocoa costs flow through. The FY2025 budget missed COGS by 151 bps; COGS is tested in 4. Sensitivity_FY2026.
A13: Distribution Expenses (% of Sales) | B13: ='2. Assumptions_FY2025'!C13 -> 0.082 | C13: =-'3. Variance_Analysis'!C19/'3. Variance_Analysis'!C16 -> 0.081640407 | D13: 0.084 | E13: 0.084 | F13: [Judgement] 8.4% (FY2025 8.2%): Nestlé flags "higher transportation and energy costs arising from the Middle East conflict" in H2, so no easing from the H1-2026 level.
A14: Marketing & Administration Expenses (% of Sales) | B14: ='2. Assumptions_FY2025'!C14 -> 0.209 | C14: =-'3. Variance_Analysis'!C20/'3. Variance_Analysis'!C16 -> 0.19983238 | D14: 0.201 | E14: 0.202 | F14: [Judgement] 20.1%: H1-2026 level (20.2%) less further Fuel for Growth savings in H2 (CHF 1.7bn achieved, CHF 2.0bn targeted for 2026); FY2025 was 20.0% on a smaller cost base.
A15: Research & Development Costs (% of Sales) | B15: ='2. Assumptions_FY2025'!C15 -> 0.018 | C15: =-'3. Variance_Analysis'!C21/'3. Variance_Analysis'!C16 -> 0.01802436 | D15: 0.018 | E15: 0.018 | F15: [Judgement] 1.8%, unchanged share of sales in FY2024, FY2025 and H1-2026.
A16: → Resulting UTOP Margin (memo, not an input) | B16: ='2. Assumptions_FY2025'!C16 -> 0.166 | C16: ='3. Variance_Analysis'!C37 -> 0.16078891 | D16: =1+D11-D12-D13-D14-D15 -> 0.1655 | E16: 0.164 | F16: Formula: 16.5%, up almost 50 bps on FY2025 (16.1%) and close to H1-2026 (16.4%) — consistent with both parts of the margin guidance.
A17: Other Trading Items, net (% of Sales) | B17: ='2. Assumptions_FY2025'!C17 -> -0.014 | C17: ='3. Variance_Analysis'!C23/'3. Variance_Analysis'!C16 -> -0.019152978 | D17: -0.022 | E17: -0.019 | F17: [Judgement] Restructuring for Fuel for Growth (about 16,000 headcount reductions by end-2027) doubled in H1-2026 (CHF 0.8bn vs 0.4bn); in FY2025 the second half was the heavier one. -2.2% (about CHF 2.0bn) vs -1.9% in FY2025. The FY2025 budget under-estimated this line.
A18: Other Operating Items, net (% of Sales) | B18: ='2. Assumptions_FY2025'!C18 -> -0.002 | C18: ='3. Variance_Analysis'!C25/'3. Variance_Analysis'!C16 -> -0.0044474243 | D18: -0.015 | E18: -0.028 | F18: [Guided] Includes the known "non-cash write-down of CHF 1.3 billion" taken in H1-2026 when the businesses being divested were classified as held for sale (Half-Year Results press release). No further write-down assumed: about CHF -1.35bn for the year (-1.5%) vs -0.4% in FY2025.
A19: Financial Income Growth (vs prior year) | B19: ='2. Assumptions_FY2025'!C19 -> 0 | C19: ='3. Variance_Analysis'!C27/'2. Budget_FY2025_PL_CF'!B16-1 -> -0.16201117 | D19: 0.02 | E19: 0.024 | F19: [Judgement] +2%, in line with H1-2026 (CHF 174m vs 170m).
A20: Net Financial Expense Growth (vs prior year) | B20: ='2. Assumptions_FY2025'!C20 -> 0.05 | C20: ='3. Variance_Analysis'!C29/'2. Budget_FY2025_PL_CF'!B18-1 -> 0.027609428 | D20: -0.08 | E20: -0.094 | F20: [Judgement] "Net financial expenses decreased to CHF 688 million from CHF 759 million in H1-25, reflecting a lower level of average net debt" (-9%). -8% for the year, as net debt at end-2025 (CHF 51.4bn) was already lower.
A21: Income from Associates & JVs Growth (vs prior year) | B21: ='2. Assumptions_FY2025'!C21 -> 0.08 | C21: ='3. Variance_Analysis'!C31/'2. Budget_FY2025_PL_CF'!B20-1 -> -0.084867894 | D21: -0.25 | E21: -0.28 | F21: [Judgement] H1-2026 fell 28% (CHF 507m vs 704m). FY2025 already came in worse than the budget's Adverse case, so the decline is carried into the full year: -25% (H2-2025 was a lower base).
A22: Effective Tax Rate | B22: ='2. Assumptions_FY2025'!C22 -> 0.24 | C22: ='3. Variance_Analysis'!C41 -> 0.24555855 | D22: 0.265 | E22: 0.287 | F22: [Judgement] H1-2026 reported 28.7% (underlying 22.3%) because of the "limited tax deductibility on the write-down of assets held for sale". Spread over full-year profit the effect is smaller: 26.5% vs 24.6% in FY2025.
A23: Non-Controlling Interests (% of Profit for the Year) | B23: ='2. Assumptions_FY2025'!C23 -> 0.026 | C23: ='3. Variance_Analysis'!C34/'3. Variance_Analysis'!C33 -> 0.023881565 | D23: 0.03 | E23: 0.034 | F23: [Judgement] 3.0%: between FY2025 (2.4%) and H1-2026 (3.4%, lifted by lower group profit after the write-down).
A24: Shares Outstanding for EPS (million) | B24: ='2. Assumptions_FY2025'!C24 -> 2554.7 | C24: ='3. Variance_Analysis'!C35/'3. Variance_Analysis'!C43 -> 2573.5043 | D24: 2572 | E24: 2572 | F24: [Judgement] H1-2026 net profit / basic EPS (3,472 / 1.35); no share buyback programme.
A26: B. CASH FLOW DRIVERS
A27: Depreciation & Amortization (% of Sales) | B27: ='2. Assumptions_FY2025'!C27 -> 0.039 | C27: ='3. Variance_Analysis'!C52/'3. Variance_Analysis'!C16 -> 0.040596715 | D27: 0.041 | E27: 0.041 | F27: [Judgement] 4.1% of sales (FY2025 4.06%, H1-2026 4.10%); lower capex keeps it from rising.
A28: Impairment (CHF m) | B28: ='2. Assumptions_FY2025'!C28 -> 580 | C28: ='3. Variance_Analysis'!C53 -> 923 | D28: 700 | E28: 181 | F28: [Judgement] H1-2026 CHF 181m; most impairments are booked at year end (H2-2025 CHF 835m). CHF 700m for the year: below FY2025 (923) because the businesses being sold were already written down in H1.
A29: Net Disposal Result & Other Non-Cash Items (CHF m) | B29: ='2. Assumptions_FY2025'!C29 -> 0 | C29: ='3. Variance_Analysis'!C54 -> 347 | D29: 1250 | E29: 1224 | F29: [Guided] Add-back of the CHF 1.3bn held-for-sale write-down recognised in H1-2026 (reported on this line: CHF 1,250m); other non-cash items assumed nil.
A30: Working Capital & Other Operating Movements (CHF m) | B30: ='2. Assumptions_FY2025'!C30 -> 0 | C30: ='3. Variance_Analysis'!C56 -> -319 | D30: 400 | E30: -1840 | F30: [Judgement] H1-2026 outflow was CHF 0.7bn smaller than in H1-2025 ("lower working capital outflow") and Nestlé keeps "continuing to reduce working capital": +CHF 400m for the year vs -319m in FY2025.
A31: Interest Paid (% of Financial Expense) | B31: ='2. Assumptions_FY2025'!C31 -> 0.835 | C31: ='3. Variance_Analysis'!C58/'3. Variance_Analysis'!C28 -> 0.88608981 | D31: 0.9 | E31: 0.958 | F31: [Judgement] 90%: between FY2025 (88.6%) and H1-2026 (95.8%; coupons are front-loaded).
A32: Interest Received (% of Financial Income) | B32: ='2. Assumptions_FY2025'!C32 -> 0.763 | C32: ='3. Variance_Analysis'!C59/'3. Variance_Analysis'!C27 -> 0.68333333 | D32: 0.66 | E32: 0.644 | F32: [Judgement] 66%: between FY2025 (68.3%) and H1-2026 (64.4%).
A33: Taxes Paid (% of Tax Expense) | B33: ='2. Assumptions_FY2025'!C33 -> 0.727 | C33: ='3. Variance_Analysis'!C60/'3. Variance_Analysis'!C32 -> 0.87045455 | D33: 0.8 | E33: 0.837 | F33: [Judgement] 80% (FY2025 87%): part of the 2026 tax charge is not deductible and the write-down creates no cash tax.
A34: Associate Dividends Received (% of Associates Income) | B34: ='2. Assumptions_FY2025'!C34 -> 0.608 | C34: ='3. Variance_Analysis'!C61/'3. Variance_Analysis'!C31 -> 2.4094488 | D34: 0.93 | E34: 1.467 | F34: [Judgement] Associates dividends arrive almost entirely in H1: CHF 744m already received in H1-2026. Allowing a small H2 amount gives about CHF 0.8bn (93% of the lower associates income). FY2025 (241%) included about CHF 2.0bn of exceptional H2 distributions and is not a guide.
A35: Capital Expenditure (% of Sales) | B35: ='2. Assumptions_FY2025'!C35 -> 0.062 | C35: =-'3. Variance_Analysis'!C65/'3. Variance_Analysis'!C16 -> 0.050586658 | D35: 0.043 | E35: 0.041 | F35: [Guided] "Capex will normalize within the range of 4% to 5% of sales" (FY2025 results call); H1-2026 was 4.1% ("capex discipline is tightened"). 4.3%, allowing for the usual H2 catch-up. The FY2025 budget over-estimated capex (6.2% vs 5.1%).
A36: Intangible Asset Capex (% of Sales) | B36: ='2. Assumptions_FY2025'!C36 -> 0.004 | C36: =-'3. Variance_Analysis'!C66/'3. Variance_Analysis'!C16 -> 0.0042909822 | D36: 0.004 | E36: 0.0037 | F36: [Judgement] 0.4% (FY2025 0.43%, H1-2026 0.37%).
A37: Acquisitions/Disposals of Businesses, net (CHF m) | B37: ='2. Assumptions_FY2025'!C37 -> 0 | C37: ='3. Variance_Analysis'!C67 -> -156 | D37: 126 | E37: 126 | F37: [Judgement] H1-2026 net inflow (CHF 126m); nothing further expected to close in 2026.
A38: Associate Investments, net (% of Sales) | B38: ='2. Assumptions_FY2025'!C38 -> -0.006 | C38: ='3. Variance_Analysis'!C68/'3. Variance_Analysis'!C16 -> 0.002324282 | D38: 0.001 | E38: 0.0017 | F38: [Judgement] 0.1%: H1-2026 net inflow of CHF 73m, no further movement assumed.
A39: Divestments in Associates/JVs (CHF m) | B39: ='2. Assumptions_FY2025'!C39 -> 0 | C39: ='3. Variance_Analysis'!C69 -> 0 | D39: 0 | E39: 0 | F39: [Judgement] Nil.
A40: Treasury Investments & Other Investing (CHF m) | B40: ='2. Assumptions_FY2025'!C40 -> 0 | C40: ='3. Variance_Analysis'!C70 -> 492 | D40: -782 | E40: -782 | F40: [Judgement] H1-2026 net outflow (CHF -782m); H2 treasury placements not forecast.
A41: Dividend Paid to Shareholders Growth (vs prior year) | B41: ='2. Assumptions_FY2025'!C41 -> 0.02 | C41: ='3. Variance_Analysis'!C74/'2. Budget_FY2025_PL_CF'!B59-1 -> 0.0042221085 | D41: =7976/7849-1 -> 0.016180405 | E41: 0.016 | F41: [Guided] Already paid: CHF 7,976m in H1-2026 for the CHF 3.10 dividend per share (vs CHF 7,849m in 2025).
A42: Dividends to Non-Controlling Interests (CHF m) | B42: ='2. Assumptions_FY2025'!C42 -> -174 | C42: ='3. Variance_Analysis'!C75 -> -172 | D42: -180 | E42: -92 | F42: [Judgement] H1-2026 CHF -92m, roughly half the annual amount (FY2025 -172m): -180m.
A43: Acquisition of Non-Controlling Interests (CHF m) | B43: ='2. Assumptions_FY2025'!C43 -> 0 | C43: ='3. Variance_Analysis'!C76 -> -1190 | D43: -51 | E43: -51 | F43: [Judgement] H1-2026 actual; FY2025's CHF 1,190m was a one-off.
A44: Purchase of Treasury Shares (CHF m) | B44: ='2. Assumptions_FY2025'!C44 -> 0 | C44: ='3. Variance_Analysis'!C77 -> -213 | D44: -60 | E44: -49 | F44: [Judgement] No buyback programme; small purchases for share plans (H1-2026 CHF -49m, FY2025 -213m).
A45: Bond/Long-Term Debt Inflows (CHF m) | B45: ='2. Assumptions_FY2025'!C45 -> 7992 | C45: ='3. Variance_Analysis'!C78 -> 2803 | D45: 2500 | E45: 1581 | F45: [Judgement] H1-2026 CHF 1,581m plus modest H2 issuance; Nestlé wants leverage back toward the middle of its 2–3x range.
A46: Bond/Lease/Long-Term Debt Outflows (CHF m) | B46: ='2. Assumptions_FY2025'!C46 -> -5055 | C46: ='3. Variance_Analysis'!C79 -> -4408 | D46: -5500 | E46: -4125 | F46: [Judgement] H1-2026 CHF -4,125m of maturities plus lease payments in H2.
A47: Short-Term Debt Movement (CHF m) | B47: ='2. Assumptions_FY2025'!C47 -> 0 | C47: ='3. Variance_Analysis'!C80 -> -1036 | D47: 0 | E47: 6865 | F47: [Judgement] H1-2026 borrowing (CHF 6.9bn) funded the April dividend and is assumed repaid by year end.
A48: Currency Retranslation (CHF m) | B48: ='2. Assumptions_FY2025'!C48 -> 0 | C48: ='3. Variance_Analysis'!C84 -> -435 | D48: 0 | E48: 29 | F48: [Judgement] Not forecast.
A50: C. NESTLÉ FY2026 GUIDANCE (LATEST, 23-JUL-2026) — USED IN THE REFORECAST AND THE GUIDANCE CHECK
A51: Organic growth — low end | D51: 0.03 | F51: "OG is expected to be in the range of 3% to 4%, with RIG accelerating versus 2025" (Half-Year Results 2026 press release, 23-Jul-2026; unchanged since February).
A52: Organic growth — high end | D52: 0.04 | F52: Same statement.
A53: Free cash flow — above (CHF m) | D53: 9000 | F53: "Free cash flow is expected to be above CHF 9 billion" (same release).
A54: Capex — low end of range (% of sales) | D54: 0.04 | F54: "Capex will normalize within the range of 4% to 5% of sales going forward" (FY2025 results call, 19-Feb-2026).
A55: Capex — high end of range (% of sales) | D55: 0.05 | F55: Same statement.
A56: FX impact on sales (full year) | D56: -0.03 | F56: "Based on current spot rates, we expect the impact of foreign exchange movements on sales to be approximately -3%" (Half-Year Results 2026 press release, 23-Jul-2026). In February the estimate was about -6%.
A57: H1-2026 UTOP margin (H2 guided broadly similar) | D57: 0.164 | F57: "UTOP margin expected to improve versus 2025; second half margin now expected to be broadly similar to the first half" — H1-2026 UTOP margin 16.4%.
A58: FX estimate in February 2026 (superseded) | D58: -0.06 | F58: "A further headwind in 2026, in the region of minus 6%, assuming today's spot rates" (CFO, FY2025 results call, 19-Feb-2026). Kept only to show what the July update is worth in 4. Sensitivity_FY2026.
A59: D. WHAT THE FY2025 VARIANCE ANALYSIS CHANGED
A60: • FX: the budget assumed no currency effect and FX took 5.7% off sales. → The reforecast uses Nestlé's own latest spot-rate estimate (about -3%), and FX is stress-tested in 4. Sensitivity_FY2026.
A61: • COGS: 151 bps worse than budget as coffee and cocoa costs peaked. → Cost ratios follow the H1-2026 level that Nestlé guides the second half to match, and COGS is the second driver in the sensitivity analysis.
A62: • Growth mix: volume was over-estimated and pricing under-estimated. → RIG and pricing are set from the 2026 quarterly run-rates, inside the guided 3%–4% organic growth.
A63: • One-offs and associates came in worse than the Adverse case. → The known CHF 1.3bn write-down is included, restructuring rises, and associates income keeps falling.
A64: • Capex came in below the Favorable case. → Capex follows management's 4%–5% of sales range.
A66: [Guided] = number taken from Nestlé's guidance or already reported; [Judgement] = own assumption. Yellow cells are the editable FY2026 assumptions (blue = hardcoded input); green cells link to other sheets.

Sheet 4. Reforecast_FY2026
A1: Nestlé Group — FY2026 Reforecast vs FY2025 Actual, full P&L + Cash Flow detail (CHF m unless % or per-share)
A2: As of 23-Jul-2026. Column B links to 3. Variance_Analysis (FY2025 actual); column C is driven by 4. Assumptions_FY2026 with the same formulas as the FY2025 Budget.
A3: Metric | B3: FY2025 Actual | C3: FY2026 Reforecast | D3: YoY Growth
A4: INCOME STATEMENT
A5: Sales | B5: ='3. Variance_Analysis'!C16 -> 89490 | C5: =B5*(1+'4. Assumptions_FY2026'!D10) -> 90026.94 | D5: =IFERROR(C5/B5-1,"") -> 0.006
A6: Other revenue | B6: ='3. Variance_Analysis'!C17 -> 395 | C6: =C5*'4. Assumptions_FY2026'!D11 -> 405.12123 | D6: =IFERROR(C6/B6-1,"") -> 0.025623367
A7: Cost of goods sold | B7: ='3. Variance_Analysis'!C18 -> -48694 | C7: =-C5*'4. Assumptions_FY2026'!D12 -> -48254.44 | D7: =IFERROR(C7/B7-1,"") -> -0.0090269881
A8: Distribution expenses | B8: ='3. Variance_Analysis'!C19 -> -7306 | C8: =-C5*'4. Assumptions_FY2026'!D13 -> -7562.263 | D8: =IFERROR(C8/B8-1,"") -> 0.035075686
A9: Marketing and administration expenses | B9: ='3. Variance_Analysis'!C20 -> -17883 | C9: =-C5*'4. Assumptions_FY2026'!D14 -> -18095.415 | D9: =IFERROR(C9/B9-1,"") -> 0.011878037
A10: Research and development costs | B10: ='3. Variance_Analysis'!C21 -> -1613 | C10: =-C5*'4. Assumptions_FY2026'!D15 -> -1620.4849 | D10: =IFERROR(C10/B10-1,"") -> 0.004640372
A11: Underlying Trading Operating Profit (UTOP) | B11: ='3. Variance_Analysis'!C22 -> 14389 | C11: =SUM(C5:C10) -> 14899.459 | D11: =IFERROR(C11/B11-1,"") -> 0.035475611
A12: Other trading items, net | B12: ='3. Variance_Analysis'!C23 -> -1714 | C12: =C5*'4. Assumptions_FY2026'!D17 -> -1980.5927 | D12: =IFERROR(C12/B12-1,"") -> 0.15553832
A13: Trading Operating Profit | B13: ='3. Variance_Analysis'!C24 -> 12675 | C13: =C11+C12 -> 12918.866 | D13: =IFERROR(C13/B13-1,"") -> 0.019239912
A14: Other operating items, net | B14: ='3. Variance_Analysis'!C25 -> -398 | C14: =C5*'4. Assumptions_FY2026'!D18 -> -1350.4041 | D14: =IFERROR(C14/B14-1,"") -> 2.3929751
A15: Operating Profit | B15: ='3. Variance_Analysis'!C26 -> 12277 | C15: =C13+C14 -> 11568.462 | D15: =IFERROR(C15/B15-1,"") -> -0.05771265
A16: Financial income | B16: ='3. Variance_Analysis'!C27 -> 300 | C16: =B16*(1+'4. Assumptions_FY2026'!D19) -> 306 | D16: =IFERROR(C16/B16-1,"") -> 0.02
A17: Financial expense | B17: ='3. Variance_Analysis'!C28 -> -1826 | C17: =(B18*(1+'4. Assumptions_FY2026'!D20))-C16 -> -1709.92 | D17: =IFERROR(C17/B17-1,"") -> -0.063570646
A18: Net Financial Income/(Expense) | B18: ='3. Variance_Analysis'!C29 -> -1526 | C18: =C16+C17 -> -1403.92 | D18: =IFERROR(C18/B18-1,"") -> -0.08
A19: Profit Before Taxes, Associates and Joint Ventures | B19: ='3. Variance_Analysis'!C30 -> 10751 | C19: =C15+C18 -> 10164.542 | D19: =IFERROR(C19/B19-1,"") -> -0.054549178
A20: Income from associates and joint ventures | B20: ='3. Variance_Analysis'!C31 -> 1143 | C20: =B20*(1+'4. Assumptions_FY2026'!D21) -> 857.25 | D20: =IFERROR(C20/B20-1,"") -> -0.25
A21: Taxes | B21: ='3. Variance_Analysis'!C32 -> -2640 | C21: =-C19*'4. Assumptions_FY2026'!D22 -> -2693.6036 | D21: =IFERROR(C21/B21-1,"") -> 0.020304384
A22: Profit for the Year | B22: ='3. Variance_Analysis'!C33 -> 9254 | C22: =C19+C20+C21 -> 8328.1882 | D22: =IFERROR(C22/B22-1,"") -> -0.1000445
A23: Of which: non-controlling interests | B23: ='3. Variance_Analysis'!C34 -> 221 | C23: =C22*'4. Assumptions_FY2026'!D23 -> 249.84565 | D23: =IFERROR(C23/B23-1,"") -> 0.13052329
A24: Net Profit (attributable to shareholders of the parent) | B24: ='3. Variance_Analysis'!C35 -> 9033 | C24: =C22-C23 -> 8078.3426 | D24: =IFERROR(C24/B24-1,"") -> -0.10568553
A26: UTOP Margin | B26: =IFERROR(B11/B5,"") -> 0.16078891 | C26: =IFERROR(C11/C5,"") -> 0.1655 | D26: =IFERROR((C26-B26)*10000,"") -> 47.11085
A27: Trading Operating Profit Margin | B27: =IFERROR(B13/B5,"") -> 0.14163594 | C27: =IFERROR(C13/C5,"") -> 0.1435 | D27: =IFERROR((C27-B27)*10000,"") -> 18.64063
A28: Operating Profit Margin | B28: =IFERROR(B15/B5,"") -> 0.13718851 | C28: =IFERROR(C15/C5,"") -> 0.1285 | D28: =IFERROR((C28-B28)*10000,"") -> -86.885127
A29: Net Profit Margin | B29: =IFERROR(B24/B5,"") -> 0.10093865 | C29: =IFERROR(C24/C5,"") -> 0.089732502 | D29: =IFERROR((C29-B29)*10000,"") -> -112.0615
A30: Effective Tax Rate | B30: =IFERROR(-B21/B19,"") -> 0.24555855 | C30: =IFERROR(-C21/C19,"") -> 0.265 | D30: =IFERROR((C30-B30)*10000,"") -> 194.41447
A32: Basic EPS (CHF) | B32: ='3. Variance_Analysis'!C43 -> 3.51 | C32: =IFERROR(C24/'4. Assumptions_FY2026'!D24,"") -> 3.1408797 | D32: =IFERROR(C32/B32-1,"") -> -0.10516248
A34: CASH FLOW STATEMENT
A35: OPERATING ACTIVITIES
A36: Operating Profit (linked from Income Statement above) | B36: ='3. Variance_Analysis'!C51 -> 12277 | C36: =C15 -> 11568.462 | D36: =IFERROR(C36/B36-1,"") -> -0.05771265
A37: Depreciation and amortization | B37: ='3. Variance_Analysis'!C52 -> 3633 | C37: =C5*'4. Assumptions_FY2026'!D27 -> 3691.1045 | D37: =IFERROR(C37/B37-1,"") -> 0.015993543
A38: Impairment | B38: ='3. Variance_Analysis'!C53 -> 923 | C38: ='4. Assumptions_FY2026'!D28 -> 700 | D38: =IFERROR(C38/B38-1,"") -> -0.24160347
A39: Net disposal result & other non-cash items | B39: ='3. Variance_Analysis'!C54 -> 347 | C39: ='4. Assumptions_FY2026'!D29 -> 1250 | D39: =IFERROR(C39/B39-1,"") -> 2.6023055
A40: Cash Flow Before Changes in Operating Assets and Liabilities | B40: ='3. Variance_Analysis'!C55 -> 17180 | C40: =SUM(C36:C39) -> 17209.566 | D40: =IFERROR(C40/B40-1,"") -> 0.0017209738
A41: Working capital & other operating movements | B41: ='3. Variance_Analysis'!C56 -> -319 | C41: ='4. Assumptions_FY2026'!D30 -> 400 | D41: =IFERROR(C41/B41-1,"") -> -2.2539185
A42: Cash Generated from Operations | B42: ='3. Variance_Analysis'!C57 -> 16861 | C42: =C40+C41 -> 17609.566 | D42: =IFERROR(C42/B42-1,"") -> 0.044396319
A43: Interest paid | B43: ='3. Variance_Analysis'!C58 -> -1618 | C43: =C17*'4. Assumptions_FY2026'!D31 -> -1538.928 | D43: =IFERROR(C43/B43-1,"") -> -0.04887021
A44: Interest and dividends received | B44: ='3. Variance_Analysis'!C59 -> 205 | C44: =C16*'4. Assumptions_FY2026'!D32 -> 201.96 | D44: =IFERROR(C44/B44-1,"") -> -0.014829268
A45: Taxes paid | B45: ='3. Variance_Analysis'!C60 -> -2298 | C45: =C21*'4. Assumptions_FY2026'!D33 -> -2154.8829 | D45: =IFERROR(C45/B45-1,"") -> -0.062278999
A46: Dividends and interest from associates and joint ventures | B46: ='3. Variance_Analysis'!C61 -> 2754 | C46: =C20*'4. Assumptions_FY2026'!D34 -> 797.2425 | D46: =IFERROR(C46/B46-1,"") -> -0.71051471
A47: Operating Cash Flow | B47: ='3. Variance_Analysis'!C62 -> 15904 | C47: =C42+C43+C44+C45+C46 -> 14914.958 | D47: =IFERROR(C47/B47-1,"") -> -0.062188256
A49: INVESTING ACTIVITIES
A50: Capital expenditure | B50: ='3. Variance_Analysis'!C65 -> -4527 | C50: =-C5*'4. Assumptions_FY2026'!D35 -> -3871.1584 | D50: =IFERROR(C50/B50-1,"") -> -0.14487333
A51: Expenditure on intangible assets | B51: ='3. Variance_Analysis'!C66 -> -384 | C51: =-C5*'4. Assumptions_FY2026'!D36 -> -360.10776 | D51: =IFERROR(C51/B51-1,"") -> -0.062219375
A52: Acquisition/disposal of businesses, net | B52: ='3. Variance_Analysis'!C67 -> -156 | C52: ='4. Assumptions_FY2026'!D37 -> 126 | D52: =IFERROR(C52/B52-1,"") -> -1.8076923
A53: Investments (net) in associates and joint ventures | B53: ='3. Variance_Analysis'!C68 -> 208 | C53: =C5*'4. Assumptions_FY2026'!D38 -> 90.02694 | D53: =IFERROR(C53/B53-1,"") -> -0.56717817
A54: Divestments in associates and joint ventures | B54: ='3. Variance_Analysis'!C69 -> 0 | C54: ='4. Assumptions_FY2026'!D39 -> 0 | D54: =IFERROR(C54/B54-1,"")
A55: Treasury investments & other investing | B55: ='3. Variance_Analysis'!C70 -> 492 | C55: ='4. Assumptions_FY2026'!D40 -> -782 | D55: =IFERROR(C55/B55-1,"") -> -2.5894309
A56: Investing Cash Flow | B56: ='3. Variance_Analysis'!C71 -> -4367 | C56: =SUM(C50:C55) -> -4797.2392 | D56: =IFERROR(C56/B56-1,"") -> 0.09852055
A58: FINANCING ACTIVITIES
A59: Dividend paid to shareholders of the parent | B59: ='3. Variance_Analysis'!C74 -> -7849 | C59: =B59*(1+'4. Assumptions_FY2026'!D41) -> -7976 | D59: =IFERROR(C59/B59-1,"") -> 0.016180405
A60: Dividends paid to non-controlling interests | B60: ='3. Variance_Analysis'!C75 -> -172 | C60: ='4. Assumptions_FY2026'!D42 -> -180 | D60: =IFERROR(C60/B60-1,"") -> 0.046511628
A61: Acquisition of non-controlling interests | B61: ='3. Variance_Analysis'!C76 -> -1190 | C61: ='4. Assumptions_FY2026'!D43 -> -51 | D61: =IFERROR(C61/B61-1,"") -> -0.95714286
A62: Purchase of treasury shares | B62: ='3. Variance_Analysis'!C77 -> -213 | C62: ='4. Assumptions_FY2026'!D44 -> -60 | D62: =IFERROR(C62/B62-1,"") -> -0.71830986
A63: Inflows from bonds and other long-term financial debt | B63: ='3. Variance_Analysis'!C78 -> 2803 | C63: ='4. Assumptions_FY2026'!D45 -> 2500 | D63: =IFERROR(C63/B63-1,"") -> -0.10809847
A64: Outflows from bonds, lease liabilities and other long-term financial debt | B64: ='3. Variance_Analysis'!C79 -> -4408 | C64: ='4. Assumptions_FY2026'!D46 -> -5500 | D64: =IFERROR(C64/B64-1,"") -> 0.2477314
A65: Inflows/(outflows) from short-term financial debt | B65: ='3. Variance_Analysis'!C80 -> -1036 | C65: ='4. Assumptions_FY2026'!D47 -> 0 | D65: =IFERROR(C65/B65-1,"") -> -1
A66: Financing Cash Flow | B66: ='3. Variance_Analysis'!C81 -> -12065 | C66: =SUM(C59:C65) -> -11267 | D66: =IFERROR(C66/B66-1,"") -> -0.066141732
A68: CASH RECONCILIATION
A69: Currency retranslations | B69: ='3. Variance_Analysis'!C84 -> -435 | C69: ='4. Assumptions_FY2026'!D48 -> 0 | D69: =IFERROR(C69/B69-1,"") -> -1
A70: Increase/(Decrease) in Cash and Cash Equivalents | B70: ='3. Variance_Analysis'!C85 -> -963 | C70: =C47+C56+C66+C69 -> -1149.2813 | D70: =IFERROR(C70/B70-1,"") -> 0.19343849
A71: Cash and cash equivalents at beginning of year | B71: ='3. Variance_Analysis'!C86 -> 5558 | C71: =B72 -> 4595 | D71: =IFERROR(C71/B71-1,"") -> -0.17326376
A72: Cash and Cash Equivalents at End of Year | B72: ='3. Variance_Analysis'!C87 -> 4595 | C72: =C70+C71 -> 3445.7187 | D72: =IFERROR(C72/B72-1,"") -> -0.25011562
A74: MEMO: FREE CASH FLOW
A75: Free Cash Flow (derived: Operating CF − Capex − Intangible capex) | B75: ='3. Variance_Analysis'!C91 -> 10993 | C75: =C47+C50+C51 -> 10683.692 | D75: =IFERROR(C75/B75-1,"") -> -0.028136833
A76: Free Cash Flow Margin | B76: =IFERROR(B75/B5,"") -> 0.12284054 | C76: =IFERROR(C75/C5,"") -> 0.11867216 | D76: =IFERROR((C76-B76)*10000,"") -> -41.683768
A77: Free Cash Flow (as reported by Nestlé) | B77: ='3. Variance_Analysis'!C90 -> 9154
A79: FY2026 GUIDANCE CHECK — is the reforecast consistent with Nestlé's latest guidance (23-Jul-2026)?
A80: Measure | B80: FY2025 Actual | C80: FY2026 Reforecast | D80: Status | E80: Nestlé guidance / statement
A81: Organic growth | B81: ='3. Variance_Analysis'!C8 -> 0.035 | C81: ='4. Assumptions_FY2026'!D7 -> 0.035 | D81: =IF(AND(C81>='4. Assumptions_FY2026'!D51,C81<='4. Assumptions_FY2026'!D52),"Within range","Outside range") -> Within range | E81: Around 3% up to 4%
A82: Real internal growth (RIG) | B82: ='3. Variance_Analysis'!C6 -> 0.008 | C82: ='4. Assumptions_FY2026'!D5 -> 0.016 | D82: =IF(C82>B82,"Accelerating","Not accelerating") -> Accelerating | E82: RIG accelerating versus 2025
A83: FX impact on sales | B83: ='3. Variance_Analysis'!C10 -> -0.057 | C83: ='4. Assumptions_FY2026'!D9 -> -0.03 | D83: =IF(ABS(C83-'4. Assumptions_FY2026'!D56)<=0.005,"In line","Differs") -> In line | E83: "Approximately -3%" at current spot rates (23-Jul-2026)
A84: UTOP margin | B84: =B26 -> 0.16078891 | C84: =C26 -> 0.1655 | D84: =IF(C84>B84,"Improves","Does not improve") -> Improves | E84: Improve versus 2025
A85: UTOP margin vs H1-2026 (bps) | B85: ='4. Assumptions_FY2026'!D57 -> 0.164 | C85: =(C26-B85)*10000 -> 15 | D85: =IF(ABS(C85)<=30,"Broadly similar","Differs") -> Broadly similar | E85: H2 margin broadly similar to H1 (H1-2026: 16.4%)
A86: Free cash flow (FY2025 reported; FY2026 derived) | B86: =B77 -> 9154 | C86: =C75 -> 10683.692 | D86: =IF(C86>'4. Assumptions_FY2026'!D53,"Above","Below") -> Above | E86: Above CHF 9 billion
A87: Capex (% of sales) | B87: =-'3. Variance_Analysis'!C65/'3. Variance_Analysis'!C16 -> 0.050586658 | C87: ='4. Assumptions_FY2026'!D35 -> 0.043 | D87: =IF(AND(C87>='4. Assumptions_FY2026'!D54,C87<='4. Assumptions_FY2026'!D55),"Within range","Outside range") -> Within range | E87: Normalise within 4% to 5% of sales (Feb-2026)
A88: Approach: a full-year reforecast built on FY2025 actuals. Numbers Nestlé has guided or already reported (FX, the margin path, the H1 write-down, the dividend paid) are used as published — latest source: Half-Year Results 2026 (23-Jul-2026). Every other driver is a judgement informed by the FY2025 variance and the H1-2026 actuals.
A89: Free cash flow: the reforecast shows the derived measure (operating cash flow − capex − intangible capex). In FY2025 it exceeded Nestlé's reported figure (CHF 10,993m vs 9,154m), mainly because of about CHF 2.0bn of exceptional distributions from associates; the FY2026 reforecast assumes a normal level of associates dividends.
A90: The two drivers that moved FY2025 furthest from the budget — FX and COGS — are stress-tested in 4. Sensitivity_FY2026.

Sheet 4. Sensitivity_FY2026
A1: Nestlé — FY2026 Reforecast: Sensitivity Analysis on FX and COGS (CHF m unless stated)
A2: One driver is changed at a time (sections B–C), then both together (section D); every other assumption stays at the FY2026 Reforecast value. Test values are centred on the Base and move with it.
A4: A. WHY FX AND COGS — THE TWO LARGEST MISSES IN THE FY2025 VARIANCE ANALYSIS
A5: Driver | B5: FY2025 Budget | C5: FY2025 Actual | D5: Miss | E5: FY2026 Base | F5: Why it matters
A6: FX impact on sales | B6: ='2. Assumptions_FY2025'!C9 -> 0 | C6: ='3. Variance_Analysis'!C10 -> -0.057 | D6: =(C6-B6)*10000 -> -570 | E6: ='4. Assumptions_FY2026'!D9 -> -0.03 | F6: Largest single miss (-570 bps): it explains almost all of the gap between a planned +3.0% and an actual -2.0% reported sales growth, and it scales every sales-linked line.
A7: Cost of goods sold (% of sales) | B7: ='2. Assumptions_FY2025'!C12 -> 0.529 | C7: =-'3. Variance_Analysis'!C18/'3. Variance_Analysis'!C16 -> 0.54412784 | D7: =(C7-B7)*10000 -> 151.27836 | E7: ='4. Assumptions_FY2026'!D12 -> 0.536 | F7: Biggest cost driver (+151 bps): COGS is 54% of sales, so small ratio changes move UTOP margin and net profit the most; coffee and cocoa costs remain volatile.
A9: B. ONE-WAY SENSITIVITY — FX IMPACT ON SALES (all else at FY2026 Base)
A10: FX impact on sales | B10: ='4. Assumptions_FY2026'!$D$9-0.04 -> -0.07 | C10: ='4. Assumptions_FY2026'!$D$9-0.03 -> -0.06 | D10: ='4. Assumptions_FY2026'!$D$9-0.02 -> -0.05 | E10: ='4. Assumptions_FY2026'!$D$9-0.01 -> -0.04 | F10: ='4. Assumptions_FY2026'!$D$9+0 -> -0.03 | G10: ='4. Assumptions_FY2026'!$D$9+0.01 -> -0.02 | H10: ='4. Assumptions_FY2026'!$D$9+0.02 -> -0.01 | I10: ='4. Assumptions_FY2026'!$D$9+0.03 -> 0
B11: =IF(ROUND(B10-'4. Assumptions_FY2026'!$D$9,6)=0,"Base","") | C11: =IF(ROUND(C10-'4. Assumptions_FY2026'!$D$9,6)=0,"Base","") | D11: =IF(ROUND(D10-'4. Assumptions_FY2026'!$D$9,6)=0,"Base","") | E11: =IF(ROUND(E10-'4. Assumptions_FY2026'!$D$9,6)=0,"Base","") | F11: =IF(ROUND(F10-'4. Assumptions_FY2026'!$D$9,6)=0,"Base","") -> Base | G11: =IF(ROUND(G10-'4. Assumptions_FY2026'!$D$9,6)=0,"Base","") | H11: =IF(ROUND(H10-'4. Assumptions_FY2026'!$D$9,6)=0,"Base","") | I11: =IF(ROUND(I10-'4. Assumptions_FY2026'!$D$9,6)=0,"Base","")
A12: Sales | B12: ='4. Reforecast_FY2026'!$B$5*(1+'4. Assumptions_FY2026'!$D$7+'4. Assumptions_FY2026'!$D$8+B$10) -> 86447.34 | C12: ='4. Reforecast_FY2026'!$B$5*(1+'4. Assumptions_FY2026'!$D$7+'4. Assumptions_FY2026'!$D$8+C$10) -> 87342.24 | D12: ='4. Reforecast_FY2026'!$B$5*(1+'4. Assumptions_FY2026'!$D$7+'4. Assumptions_FY2026'!$D$8+D$10) -> 88237.14 | E12: ='4. Reforecast_FY2026'!$B$5*(1+'4. Assumptions_FY2026'!$D$7+'4. Assumptions_FY2026'!$D$8+E$10) -> 89132.04 | F12: ='4. Reforecast_FY2026'!$B$5*(1+'4. Assumptions_FY2026'!$D$7+'4. Assumptions_FY2026'!$D$8+F$10) -> 90026.94 | G12: ='4. Reforecast_FY2026'!$B$5*(1+'4. Assumptions_FY2026'!$D$7+'4. Assumptions_FY2026'!$D$8+G$10) -> 90921.84 | H12: ='4. Reforecast_FY2026'!$B$5*(1+'4. Assumptions_FY2026'!$D$7+'4. Assumptions_FY2026'!$D$8+H$10) -> 91816.74 | I12: ='4. Reforecast_FY2026'!$B$5*(1+'4. Assumptions_FY2026'!$D$7+'4. Assumptions_FY2026'!$D$8+I$10) -> 92711.64
A13: UTOP | B13: =B12*(1+'4. Assumptions_FY2026'!$D$11-'4. Assumptions_FY2026'!$D$12-'4. Assumptions_FY2026'!$D$13-'4. Assumptions_FY2026'!$D$14-'4. Assumptions_FY2026'!$D$15) -> 14307.035 | C13: =C12*(1+'4. Assumptions_FY2026'!$D$11-'4. Assumptions_FY2026'!$D$12-'4. Assumptions_FY2026'!$D$13-'4. Assumptions_FY2026'!$D$14-'4. Assumptions_FY2026'!$D$15) -> 14455.141 | D13: =D12*(1+'4. Assumptions_FY2026'!$D$11-'4. Assumptions_FY2026'!$D$12-'4. Assumptions_FY2026'!$D$13-'4. Assumptions_FY2026'!$D$14-'4. Assumptions_FY2026'!$D$15) -> 14603.247 | E13: =E12*(1+'4. Assumptions_FY2026'!$D$11-'4. Assumptions_FY2026'!$D$12-'4. Assumptions_FY2026'!$D$13-'4. Assumptions_FY2026'!$D$14-'4. Assumptions_FY2026'!$D$15) -> 14751.353 | F13: =F12*(1+'4. Assumptions_FY2026'!$D$11-'4. Assumptions_FY2026'!$D$12-'4. Assumptions_FY2026'!$D$13-'4. Assumptions_FY2026'!$D$14-'4. Assumptions_FY2026'!$D$15) -> 14899.459 | G13: =G12*(1+'4. Assumptions_FY2026'!$D$11-'4. Assumptions_FY2026'!$D$12-'4. Assumptions_FY2026'!$D$13-'4. Assumptions_FY2026'!$D$14-'4. Assumptions_FY2026'!$D$15) -> 15047.565 | H13: =H12*(1+'4. Assumptions_FY2026'!$D$11-'4. Assumptions_FY2026'!$D$12-'4. Assumptions_FY2026'!$D$13-'4. Assumptions_FY2026'!$D$14-'4. Assumptions_FY2026'!$D$15) -> 15195.67 | I13: =I12*(1+'4. Assumptions_FY2026'!$D$11-'4. Assumptions_FY2026'!$D$12-'4. Assumptions_FY2026'!$D$13-'4. Assumptions_FY2026'!$D$14-'4. Assumptions_FY2026'!$D$15) -> 15343.776
A14: UTOP margin | B14: =B13/B12 -> 0.1655 | C14: =C13/C12 -> 0.1655 | D14: =D13/D12 -> 0.1655 | E14: =E13/E12 -> 0.1655 | F14: =F13/F12 -> 0.1655 | G14: =G13/G12 -> 0.1655 | H14: =H13/H12 -> 0.1655 | I14: =I13/I12 -> 0.1655
A15: Operating profit | B15: =B13+B12*('4. Assumptions_FY2026'!$D$17+'4. Assumptions_FY2026'!$D$18) -> 11108.483 | C15: =C13+C12*('4. Assumptions_FY2026'!$D$17+'4. Assumptions_FY2026'!$D$18) -> 11223.478 | D15: =D13+D12*('4. Assumptions_FY2026'!$D$17+'4. Assumptions_FY2026'!$D$18) -> 11338.472 | E15: =E13+E12*('4. Assumptions_FY2026'!$D$17+'4. Assumptions_FY2026'!$D$18) -> 11453.467 | F15: =F13+F12*('4. Assumptions_FY2026'!$D$17+'4. Assumptions_FY2026'!$D$18) -> 11568.462 | G15: =G13+G12*('4. Assumptions_FY2026'!$D$17+'4. Assumptions_FY2026'!$D$18) -> 11683.456 | H15: =H13+H12*('4. Assumptions_FY2026'!$D$17+'4. Assumptions_FY2026'!$D$18) -> 11798.451 | I15: =I13+I12*('4. Assumptions_FY2026'!$D$17+'4. Assumptions_FY2026'!$D$18) -> 11913.446
A16: Profit before taxes & associates | B16: =B15+'4. Reforecast_FY2026'!$C$18 -> 9704.5632 | C16: =C15+'4. Reforecast_FY2026'!$C$18 -> 9819.5578 | D16: =D15+'4. Reforecast_FY2026'!$C$18 -> 9934.5525 | E16: =E15+'4. Reforecast_FY2026'!$C$18 -> 10049.547 | F16: =F15+'4. Reforecast_FY2026'!$C$18 -> 10164.542 | G16: =G15+'4. Reforecast_FY2026'!$C$18 -> 10279.536 | H16: =H15+'4. Reforecast_FY2026'!$C$18 -> 10394.531 | I16: =I15+'4. Reforecast_FY2026'!$C$18 -> 10509.526
A17: Taxes | B17: =-B16*'4. Assumptions_FY2026'!$D$22 -> -2571.7092 | C17: =-C16*'4. Assumptions_FY2026'!$D$22 -> -2602.1828 | D17: =-D16*'4. Assumptions_FY2026'!$D$22 -> -2632.6564 | E17: =-E16*'4. Assumptions_FY2026'!$D$22 -> -2663.13 | F17: =-F16*'4. Assumptions_FY2026'!$D$22 -> -2693.6036 | G17: =-G16*'4. Assumptions_FY2026'!$D$22 -> -2724.0772 | H17: =-H16*'4. Assumptions_FY2026'!$D$22 -> -2754.5507 | I17: =-I16*'4. Assumptions_FY2026'!$D$22 -> -2785.0243
A18: Net profit | B18: =(B16+'4. Reforecast_FY2026'!$C$20+B17)*(1-'4. Assumptions_FY2026'!$D$23) -> 7750.4008 | C18: =(C16+'4. Reforecast_FY2026'!$C$20+C17)*(1-'4. Assumptions_FY2026'!$D$23) -> 7832.3863 | D18: =(D16+'4. Reforecast_FY2026'!$C$20+D17)*(1-'4. Assumptions_FY2026'!$D$23) -> 7914.3717 | E18: =(E16+'4. Reforecast_FY2026'!$C$20+E17)*(1-'4. Assumptions_FY2026'!$D$23) -> 7996.3571 | F18: =(F16+'4. Reforecast_FY2026'!$C$20+F17)*(1-'4. Assumptions_FY2026'!$D$23) -> 8078.3426 | G18: =(G16+'4. Reforecast_FY2026'!$C$20+G17)*(1-'4. Assumptions_FY2026'!$D$23) -> 8160.328 | H18: =(H16+'4. Reforecast_FY2026'!$C$20+H17)*(1-'4. Assumptions_FY2026'!$D$23) -> 8242.3134 | I18: =(I16+'4. Reforecast_FY2026'!$C$20+I17)*(1-'4. Assumptions_FY2026'!$D$23) -> 8324.2989
A19: Basic EPS (CHF) | B19: =B18/'4. Assumptions_FY2026'!$D$24 -> 3.0133751 | C19: =C18/'4. Assumptions_FY2026'!$D$24 -> 3.0452513 | D19: =D18/'4. Assumptions_FY2026'!$D$24 -> 3.0771274 | E19: =E18/'4. Assumptions_FY2026'!$D$24 -> 3.1090036 | F19: =F18/'4. Assumptions_FY2026'!$D$24 -> 3.1408797 | G19: =G18/'4. Assumptions_FY2026'!$D$24 -> 3.1727558 | H19: =H18/'4. Assumptions_FY2026'!$D$24 -> 3.204632 | I19: =I18/'4. Assumptions_FY2026'!$D$24 -> 3.2365081
A20: Free cash flow (derived) | B20: =B15+B12*('4. Assumptions_FY2026'!$D$27-'4. Assumptions_FY2026'!$D$35-'4. Assumptions_FY2026'!$D$36)+'4. Reforecast_FY2026'!$C$38+'4. Reforecast_FY2026'!$C$39+'4. Reforecast_FY2026'!$C$41+'4. Reforecast_FY2026'!$C$43+'4. Reforecast_FY2026'!$C$44+'4. Reforecast_FY2026'!$C$46+B17*'4. Assumptions_FY2026'!$D$33 -> 10342.706 | C20: =C15+C12*('4. Assumptions_FY2026'!$D$27-'4. Assumptions_FY2026'!$D$35-'4. Assumptions_FY2026'!$D$36)+'4. Reforecast_FY2026'!$C$38+'4. Reforecast_FY2026'!$C$39+'4. Reforecast_FY2026'!$C$41+'4. Reforecast_FY2026'!$C$43+'4. Reforecast_FY2026'!$C$44+'4. Reforecast_FY2026'!$C$46+C17*'4. Assumptions_FY2026'!$D$33 -> 10427.953 | D20: =D15+D12*('4. Assumptions_FY2026'!$D$27-'4. Assumptions_FY2026'!$D$35-'4. Assumptions_FY2026'!$D$36)+'4. Reforecast_FY2026'!$C$38+'4. Reforecast_FY2026'!$C$39+'4. Reforecast_FY2026'!$C$41+'4. Reforecast_FY2026'!$C$43+'4. Reforecast_FY2026'!$C$44+'4. Reforecast_FY2026'!$C$46+D17*'4. Assumptions_FY2026'!$D$33 -> 10513.199 | E20: =E15+E12*('4. Assumptions_FY2026'!$D$27-'4. Assumptions_FY2026'!$D$35-'4. Assumptions_FY2026'!$D$36)+'4. Reforecast_FY2026'!$C$38+'4. Reforecast_FY2026'!$C$39+'4. Reforecast_FY2026'!$C$41+'4. Reforecast_FY2026'!$C$43+'4. Reforecast_FY2026'!$C$44+'4. Reforecast_FY2026'!$C$46+E17*'4. Assumptions_FY2026'!$D$33 -> 10598.445 | F20: =F15+F12*('4. Assumptions_FY2026'!$D$27-'4. Assumptions_FY2026'!$D$35-'4. Assumptions_FY2026'!$D$36)+'4. Reforecast_FY2026'!$C$38+'4. Reforecast_FY2026'!$C$39+'4. Reforecast_FY2026'!$C$41+'4. Reforecast_FY2026'!$C$43+'4. Reforecast_FY2026'!$C$44+'4. Reforecast_FY2026'!$C$46+F17*'4. Assumptions_FY2026'!$D$33 -> 10683.692 | G20: =G15+G12*('4. Assumptions_FY2026'!$D$27-'4. Assumptions_FY2026'!$D$35-'4. Assumptions_FY2026'!$D$36)+'4. Reforecast_FY2026'!$C$38+'4. Reforecast_FY2026'!$C$39+'4. Reforecast_FY2026'!$C$41+'4. Reforecast_FY2026'!$C$43+'4. Reforecast_FY2026'!$C$44+'4. Reforecast_FY2026'!$C$46+G17*'4. Assumptions_FY2026'!$D$33 -> 10768.938 | H20: =H15+H12*('4. Assumptions_FY2026'!$D$27-'4. Assumptions_FY2026'!$D$35-'4. Assumptions_FY2026'!$D$36)+'4. Reforecast_FY2026'!$C$38+'4. Reforecast_FY2026'!$C$39+'4. Reforecast_FY2026'!$C$41+'4. Reforecast_FY2026'!$C$43+'4. Reforecast_FY2026'!$C$44+'4. Reforecast_FY2026'!$C$46+H17*'4. Assumptions_FY2026'!$D$33 -> 10854.185 | I20: =I15+I12*('4. Assumptions_FY2026'!$D$27-'4. Assumptions_FY2026'!$D$35-'4. Assumptions_FY2026'!$D$36)+'4. Reforecast_FY2026'!$C$38+'4. Reforecast_FY2026'!$C$39+'4. Reforecast_FY2026'!$C$41+'4. Reforecast_FY2026'!$C$43+'4. Reforecast_FY2026'!$C$44+'4. Reforecast_FY2026'!$C$46+I17*'4. Assumptions_FY2026'!$D$33 -> 10939.431
A21: Net profit vs FY2026 Base | B21: =B18-'4. Reforecast_FY2026'!$C$24 -> -327.94174 | C21: =C18-'4. Reforecast_FY2026'!$C$24 -> -245.95631 | D21: =D18-'4. Reforecast_FY2026'!$C$24 -> -163.97087 | E21: =E18-'4. Reforecast_FY2026'!$C$24 -> -81.985436 | F21: =F18-'4. Reforecast_FY2026'!$C$24 -> 0 | G21: =G18-'4. Reforecast_FY2026'!$C$24 -> 81.985436 | H21: =H18-'4. Reforecast_FY2026'!$C$24 -> 163.97087 | I21: =I18-'4. Reforecast_FY2026'!$C$24 -> 245.95631
A22: Net profit vs FY2025 Actual | B22: =B18/'4. Reforecast_FY2026'!$B$24-1 -> -0.14199039 | C22: =C18/'4. Reforecast_FY2026'!$B$24-1 -> -0.13291417 | D22: =D18/'4. Reforecast_FY2026'!$B$24-1 -> -0.12383796 | E22: =E18/'4. Reforecast_FY2026'!$B$24-1 -> -0.11476175 | F22: =F18/'4. Reforecast_FY2026'!$B$24-1 -> -0.10568553 | G22: =G18/'4. Reforecast_FY2026'!$B$24-1 -> -0.096609321 | H22: =H18/'4. Reforecast_FY2026'!$B$24-1 -> -0.087533107 | I22: =I18/'4. Reforecast_FY2026'!$B$24-1 -> -0.078456894
A24: C. ONE-WAY SENSITIVITY — COGS AS % OF SALES (all else at FY2026 Base)
A25: COGS (% of sales) | B25: ='4. Assumptions_FY2026'!$D$12-0.015 -> 0.521 | C25: ='4. Assumptions_FY2026'!$D$12-0.01 -> 0.526 | D25: ='4. Assumptions_FY2026'!$D$12-0.005 -> 0.531 | E25: ='4. Assumptions_FY2026'!$D$12+0 -> 0.536 | F25: ='4. Assumptions_FY2026'!$D$12+0.005 -> 0.541 | G25: ='4. Assumptions_FY2026'!$D$12+0.01 -> 0.546 | H25: ='4. Assumptions_FY2026'!$D$12+0.015 -> 0.551
B26: =IF(ROUND(B25-'4. Assumptions_FY2026'!$D$12,6)=0,"Base","") | C26: =IF(ROUND(C25-'4. Assumptions_FY2026'!$D$12,6)=0,"Base","") | D26: =IF(ROUND(D25-'4. Assumptions_FY2026'!$D$12,6)=0,"Base","") | E26: =IF(ROUND(E25-'4. Assumptions_FY2026'!$D$12,6)=0,"Base","") -> Base | F26: =IF(ROUND(F25-'4. Assumptions_FY2026'!$D$12,6)=0,"Base","") | G26: =IF(ROUND(G25-'4. Assumptions_FY2026'!$D$12,6)=0,"Base","") | H26: =IF(ROUND(H25-'4. Assumptions_FY2026'!$D$12,6)=0,"Base","")
A27: Sales | B27: ='4. Reforecast_FY2026'!$B$5*(1+'4. Assumptions_FY2026'!$D$7+'4. Assumptions_FY2026'!$D$8+'4. Assumptions_FY2026'!$D$9) -> 90026.94 | C27: ='4. Reforecast_FY2026'!$B$5*(1+'4. Assumptions_FY2026'!$D$7+'4. Assumptions_FY2026'!$D$8+'4. Assumptions_FY2026'!$D$9) -> 90026.94 | D27: ='4. Reforecast_FY2026'!$B$5*(1+'4. Assumptions_FY2026'!$D$7+'4. Assumptions_FY2026'!$D$8+'4. Assumptions_FY2026'!$D$9) -> 90026.94 | E27: ='4. Reforecast_FY2026'!$B$5*(1+'4. Assumptions_FY2026'!$D$7+'4. Assumptions_FY2026'!$D$8+'4. Assumptions_FY2026'!$D$9) -> 90026.94 | F27: ='4. Reforecast_FY2026'!$B$5*(1+'4. Assumptions_FY2026'!$D$7+'4. Assumptions_FY2026'!$D$8+'4. Assumptions_FY2026'!$D$9) -> 90026.94 | G27: ='4. Reforecast_FY2026'!$B$5*(1+'4. Assumptions_FY2026'!$D$7+'4. Assumptions_FY2026'!$D$8+'4. Assumptions_FY2026'!$D$9) -> 90026.94 | H27: ='4. Reforecast_FY2026'!$B$5*(1+'4. Assumptions_FY2026'!$D$7+'4. Assumptions_FY2026'!$D$8+'4. Assumptions_FY2026'!$D$9) -> 90026.94
A28: UTOP | B28: =B27*(1+'4. Assumptions_FY2026'!$D$11-B$25-'4. Assumptions_FY2026'!$D$13-'4. Assumptions_FY2026'!$D$14-'4. Assumptions_FY2026'!$D$15) -> 16249.863 | C28: =C27*(1+'4. Assumptions_FY2026'!$D$11-C$25-'4. Assumptions_FY2026'!$D$13-'4. Assumptions_FY2026'!$D$14-'4. Assumptions_FY2026'!$D$15) -> 15799.728 | D28: =D27*(1+'4. Assumptions_FY2026'!$D$11-D$25-'4. Assumptions_FY2026'!$D$13-'4. Assumptions_FY2026'!$D$14-'4. Assumptions_FY2026'!$D$15) -> 15349.593 | E28: =E27*(1+'4. Assumptions_FY2026'!$D$11-E$25-'4. Assumptions_FY2026'!$D$13-'4. Assumptions_FY2026'!$D$14-'4. Assumptions_FY2026'!$D$15) -> 14899.459 | F28: =F27*(1+'4. Assumptions_FY2026'!$D$11-F$25-'4. Assumptions_FY2026'!$D$13-'4. Assumptions_FY2026'!$D$14-'4. Assumptions_FY2026'!$D$15) -> 14449.324 | G28: =G27*(1+'4. Assumptions_FY2026'!$D$11-G$25-'4. Assumptions_FY2026'!$D$13-'4. Assumptions_FY2026'!$D$14-'4. Assumptions_FY2026'!$D$15) -> 13999.189 | H28: =H27*(1+'4. Assumptions_FY2026'!$D$11-H$25-'4. Assumptions_FY2026'!$D$13-'4. Assumptions_FY2026'!$D$14-'4. Assumptions_FY2026'!$D$15) -> 13549.054
A29: UTOP margin | B29: =B28/B27 -> 0.1805 | C29: =C28/C27 -> 0.1755 | D29: =D28/D27 -> 0.1705 | E29: =E28/E27 -> 0.1655 | F29: =F28/F27 -> 0.1605 | G29: =G28/G27 -> 0.1555 | H29: =H28/H27 -> 0.1505
A30: Operating profit | B30: =B28+B27*('4. Assumptions_FY2026'!$D$17+'4. Assumptions_FY2026'!$D$18) -> 12918.866 | C30: =C28+C27*('4. Assumptions_FY2026'!$D$17+'4. Assumptions_FY2026'!$D$18) -> 12468.731 | D30: =D28+D27*('4. Assumptions_FY2026'!$D$17+'4. Assumptions_FY2026'!$D$18) -> 12018.596 | E30: =E28+E27*('4. Assumptions_FY2026'!$D$17+'4. Assumptions_FY2026'!$D$18) -> 11568.462 | F30: =F28+F27*('4. Assumptions_FY2026'!$D$17+'4. Assumptions_FY2026'!$D$18) -> 11118.327 | G30: =G28+G27*('4. Assumptions_FY2026'!$D$17+'4. Assumptions_FY2026'!$D$18) -> 10668.192 | H30: =H28+H27*('4. Assumptions_FY2026'!$D$17+'4. Assumptions_FY2026'!$D$18) -> 10218.058
A31: Profit before taxes & associates | B31: =B30+'4. Reforecast_FY2026'!$C$18 -> 11514.946 | C31: =C30+'4. Reforecast_FY2026'!$C$18 -> 11064.811 | D31: =D30+'4. Reforecast_FY2026'!$C$18 -> 10614.676 | E31: =E30+'4. Reforecast_FY2026'!$C$18 -> 10164.542 | F31: =F30+'4. Reforecast_FY2026'!$C$18 -> 9714.4071 | G31: =G30+'4. Reforecast_FY2026'!$C$18 -> 9264.2724 | H31: =H30+'4. Reforecast_FY2026'!$C$18 -> 8814.1377
A32: Taxes | B32: =-B31*'4. Assumptions_FY2026'!$D$22 -> -3051.4607 | C32: =-C31*'4. Assumptions_FY2026'!$D$22 -> -2932.175 | D32: =-D31*'4. Assumptions_FY2026'!$D$22 -> -2812.8893 | E32: =-E31*'4. Assumptions_FY2026'!$D$22 -> -2693.6036 | F32: =-F31*'4. Assumptions_FY2026'!$D$22 -> -2574.3179 | G32: =-G31*'4. Assumptions_FY2026'!$D$22 -> -2455.0322 | H32: =-H31*'4. Assumptions_FY2026'!$D$22 -> -2335.7465
A33: Net profit | B33: =(B31+'4. Reforecast_FY2026'!$C$20+B32)*(1-'4. Assumptions_FY2026'!$D$23) -> 9041.1132 | C33: =(C31+'4. Reforecast_FY2026'!$C$20+C32)*(1-'4. Assumptions_FY2026'!$D$23) -> 8720.1896 | D33: =(D31+'4. Reforecast_FY2026'!$C$20+D32)*(1-'4. Assumptions_FY2026'!$D$23) -> 8399.2661 | E33: =(E31+'4. Reforecast_FY2026'!$C$20+E32)*(1-'4. Assumptions_FY2026'!$D$23) -> 8078.3426 | F33: =(F31+'4. Reforecast_FY2026'!$C$20+F32)*(1-'4. Assumptions_FY2026'!$D$23) -> 7757.419 | G33: =(G31+'4. Reforecast_FY2026'!$C$20+G32)*(1-'4. Assumptions_FY2026'!$D$23) -> 7436.4955 | H33: =(H31+'4. Reforecast_FY2026'!$C$20+H32)*(1-'4. Assumptions_FY2026'!$D$23) -> 7115.572
A34: Basic EPS (CHF) | B34: =B33/'4. Assumptions_FY2026'!$D$24 -> 3.5152073 | C34: =C33/'4. Assumptions_FY2026'!$D$24 -> 3.3904314 | D34: =D33/'4. Assumptions_FY2026'!$D$24 -> 3.2656556 | E34: =E33/'4. Assumptions_FY2026'!$D$24 -> 3.1408797 | F34: =F33/'4. Assumptions_FY2026'!$D$24 -> 3.0161038 | G34: =G33/'4. Assumptions_FY2026'!$D$24 -> 2.891328 | H34: =H33/'4. Assumptions_FY2026'!$D$24 -> 2.7665521
A35: Free cash flow (derived) | B35: =B30+B27*('4. Assumptions_FY2026'!$D$27-'4. Assumptions_FY2026'!$D$35-'4. Assumptions_FY2026'!$D$36)+'4. Reforecast_FY2026'!$C$38+'4. Reforecast_FY2026'!$C$39+'4. Reforecast_FY2026'!$C$41+'4. Reforecast_FY2026'!$C$43+'4. Reforecast_FY2026'!$C$44+'4. Reforecast_FY2026'!$C$46+B32*'4. Assumptions_FY2026'!$D$33 -> 11747.81 | C35: =C30+C27*('4. Assumptions_FY2026'!$D$27-'4. Assumptions_FY2026'!$D$35-'4. Assumptions_FY2026'!$D$36)+'4. Reforecast_FY2026'!$C$38+'4. Reforecast_FY2026'!$C$39+'4. Reforecast_FY2026'!$C$41+'4. Reforecast_FY2026'!$C$43+'4. Reforecast_FY2026'!$C$44+'4. Reforecast_FY2026'!$C$46+C32*'4. Assumptions_FY2026'!$D$33 -> 11393.104 | D35: =D30+D27*('4. Assumptions_FY2026'!$D$27-'4. Assumptions_FY2026'!$D$35-'4. Assumptions_FY2026'!$D$36)+'4. Reforecast_FY2026'!$C$38+'4. Reforecast_FY2026'!$C$39+'4. Reforecast_FY2026'!$C$41+'4. Reforecast_FY2026'!$C$43+'4. Reforecast_FY2026'!$C$44+'4. Reforecast_FY2026'!$C$46+D32*'4. Assumptions_FY2026'!$D$33 -> 11038.398 | E35: =E30+E27*('4. Assumptions_FY2026'!$D$27-'4. Assumptions_FY2026'!$D$35-'4. Assumptions_FY2026'!$D$36)+'4. Reforecast_FY2026'!$C$38+'4. Reforecast_FY2026'!$C$39+'4. Reforecast_FY2026'!$C$41+'4. Reforecast_FY2026'!$C$43+'4. Reforecast_FY2026'!$C$44+'4. Reforecast_FY2026'!$C$46+E32*'4. Assumptions_FY2026'!$D$33 -> 10683.692 | F35: =F30+F27*('4. Assumptions_FY2026'!$D$27-'4. Assumptions_FY2026'!$D$35-'4. Assumptions_FY2026'!$D$36)+'4. Reforecast_FY2026'!$C$38+'4. Reforecast_FY2026'!$C$39+'4. Reforecast_FY2026'!$C$41+'4. Reforecast_FY2026'!$C$43+'4. Reforecast_FY2026'!$C$44+'4. Reforecast_FY2026'!$C$46+F32*'4. Assumptions_FY2026'!$D$33 -> 10328.986 | G35: =G30+G27*('4. Assumptions_FY2026'!$D$27-'4. Assumptions_FY2026'!$D$35-'4. Assumptions_FY2026'!$D$36)+'4. Reforecast_FY2026'!$C$38+'4. Reforecast_FY2026'!$C$39+'4. Reforecast_FY2026'!$C$41+'4. Reforecast_FY2026'!$C$43+'4. Reforecast_FY2026'!$C$44+'4. Reforecast_FY2026'!$C$46+G32*'4. Assumptions_FY2026'!$D$33 -> 9974.2795 | H35: =H30+H27*('4. Assumptions_FY2026'!$D$27-'4. Assumptions_FY2026'!$D$35-'4. Assumptions_FY2026'!$D$36)+'4. Reforecast_FY2026'!$C$38+'4. Reforecast_FY2026'!$C$39+'4. Reforecast_FY2026'!$C$41+'4. Reforecast_FY2026'!$C$43+'4. Reforecast_FY2026'!$C$44+'4. Reforecast_FY2026'!$C$46+H32*'4. Assumptions_FY2026'!$D$33 -> 9619.5734
A36: Net profit vs FY2026 Base | B36: =B33-'4. Reforecast_FY2026'!$C$24 -> 962.7706 | C36: =C33-'4. Reforecast_FY2026'!$C$24 -> 641.84707 | D36: =D33-'4. Reforecast_FY2026'!$C$24 -> 320.92353 | E36: =E33-'4. Reforecast_FY2026'!$C$24 -> 0 | F36: =F33-'4. Reforecast_FY2026'!$C$24 -> -320.92353 | G36: =G33-'4. Reforecast_FY2026'!$C$24 -> -641.84707 | H36: =H33-'4. Reforecast_FY2026'!$C$24 -> -962.7706
A37: Net profit vs FY2025 Actual | B37: =B33/'4. Reforecast_FY2026'!$B$24-1 -> 0.0008981703 | C37: =C33/'4. Reforecast_FY2026'!$B$24-1 -> -0.034629731 | D37: =D33/'4. Reforecast_FY2026'!$B$24-1 -> -0.070157633 | E37: =E33/'4. Reforecast_FY2026'!$B$24-1 -> -0.10568553 | F37: =F33/'4. Reforecast_FY2026'!$B$24-1 -> -0.14121344 | G37: =G33/'4. Reforecast_FY2026'!$B$24-1 -> -0.17674134 | H37: =H33/'4. Reforecast_FY2026'!$B$24-1 -> -0.21226924
A39: D. TWO-WAY SENSITIVITY — FY2026 NET PROFIT (CHF m) FOR FX (rows) × COGS % OF SALES (columns)
A40: FX impact on sales ↓ / COGS % of sales → | B40: ='4. Assumptions_FY2026'!$D$12-0.015 -> 0.521 | C40: ='4. Assumptions_FY2026'!$D$12-0.01 -> 0.526 | D40: ='4. Assumptions_FY2026'!$D$12-0.005 -> 0.531 | E40: ='4. Assumptions_FY2026'!$D$12+0 -> 0.536 | F40: ='4. Assumptions_FY2026'!$D$12+0.005 -> 0.541 | G40: ='4. Assumptions_FY2026'!$D$12+0.01 -> 0.546 | H40: ='4. Assumptions_FY2026'!$D$12+0.015 -> 0.551
A41: ='4. Assumptions_FY2026'!$D$9-0.04 -> -0.07 | B41: =(('4. Reforecast_FY2026'!$B$5*(1+'4. Assumptions_FY2026'!$D$7+'4. Assumptions_FY2026'!$D$8+$A41)*(1+'4. Assumptions_FY2026'!$D$11-B$40-'4. Assumptions_FY2026'!$D$13-'4. Assumptions_FY2026'!$D$14-'4. Assumptions_FY2026'!$D$15+'4. Assumptions_FY2026'!$D$17+'4. Assumptions_FY2026'!$D$18)+'4. Reforecast_FY2026'!$C$18)*(1-'4. Assumptions_FY2026'!$D$22)+'4. Reforecast_FY2026'!$C$20)*(1-'4. Assumptions_FY2026'!$D$23) -> 8674.8903 | C41: =(('4. Reforecast_FY2026'!$B$5*(1+'4. Assumptions_FY2026'!$D$7+'4. Assumptions_FY2026'!$D$8+$A41)*(1+'4. Assumptions_FY2026'!$D$11-C$40-'4. Assumptions_FY2026'!$D$13-'4. Assumptions_FY2026'!$D$14-'4. Assumptions_FY2026'!$D$15+'4. Assumptions_FY2026'!$D$17+'4. Assumptions_FY2026'!$D$18)+'4. Reforecast_FY2026'!$C$18)*(1-'4. Assumptions_FY2026'!$D$22)+'4. Reforecast_FY2026'!$C$20)*(1-'4. Assumptions_FY2026'!$D$23) -> 8366.7271 | D41: =(('4. Reforecast_FY2026'!$B$5*(1+'4. Assumptions_FY2026'!$D$7+'4. Assumptions_FY2026'!$D$8+$A41)*(1+'4. Assumptions_FY2026'!$D$11-D$40-'4. Assumptions_FY2026'!$D$13-'4. Assumptions_FY2026'!$D$14-'4. Assumptions_FY2026'!$D$15+'4. Assumptions_FY2026'!$D$17+'4. Assumptions_FY2026'!$D$18)+'4. Reforecast_FY2026'!$C$18)*(1-'4. Assumptions_FY2026'!$D$22)+'4. Reforecast_FY2026'!$C$20)*(1-'4. Assumptions_FY2026'!$D$23) -> 8058.564 | E41: =(('4. Reforecast_FY2026'!$B$5*(1+'4. Assumptions_FY2026'!$D$7+'4. Assumptions_FY2026'!$D$8+$A41)*(1+'4. Assumptions_FY2026'!$D$11-E$40-'4. Assumptions_FY2026'!$D$13-'4. Assumptions_FY2026'!$D$14-'4. Assumptions_FY2026'!$D$15+'4. Assumptions_FY2026'!$D$17+'4. Assumptions_FY2026'!$D$18)+'4. Reforecast_FY2026'!$C$18)*(1-'4. Assumptions_FY2026'!$D$22)+'4. Reforecast_FY2026'!$C$20)*(1-'4. Assumptions_FY2026'!$D$23) -> 7750.4008 | F41: =(('4. Reforecast_FY2026'!$B$5*(1+'4. Assumptions_FY2026'!$D$7+'4. Assumptions_FY2026'!$D$8+$A41)*(1+'4. Assumptions_FY2026'!$D$11-F$40-'4. Assumptions_FY2026'!$D$13-'4. Assumptions_FY2026'!$D$14-'4. Assumptions_FY2026'!$D$15+'4. Assumptions_FY2026'!$D$17+'4. Assumptions_FY2026'!$D$18)+'4. Reforecast_FY2026'!$C$18)*(1-'4. Assumptions_FY2026'!$D$22)+'4. Reforecast_FY2026'!$C$20)*(1-'4. Assumptions_FY2026'!$D$23) -> 7442.2377 | G41: =(('4. Reforecast_FY2026'!$B$5*(1+'4. Assumptions_FY2026'!$D$7+'4. Assumptions_FY2026'!$D$8+$A41)*(1+'4. Assumptions_FY2026'!$D$11-G$40-'4. Assumptions_FY2026'!$D$13-'4. Assumptions_FY2026'!$D$14-'4. Assumptions_FY2026'!$D$15+'4. Assumptions_FY2026'!$D$17+'4. Assumptions_FY2026'!$D$18)+'4. Reforecast_FY2026'!$C$18)*(1-'4. Assumptions_FY2026'!$D$22)+'4. Reforecast_FY2026'!$C$20)*(1-'4. Assumptions_FY2026'!$D$23) -> 7134.0745 | H41: =(('4. Reforecast_FY2026'!$B$5*(1+'4. Assumptions_FY2026'!$D$7+'4. Assumptions_FY2026'!$D$8+$A41)*(1+'4. Assumptions_FY2026'!$D$11-H$40-'4. Assumptions_FY2026'!$D$13-'4. Assumptions_FY2026'!$D$14-'4. Assumptions_FY2026'!$D$15+'4. Assumptions_FY2026'!$D$17+'4. Assumptions_FY2026'!$D$18)+'4. Reforecast_FY2026'!$C$18)*(1-'4. Assumptions_FY2026'!$D$22)+'4. Reforecast_FY2026'!$C$20)*(1-'4. Assumptions_FY2026'!$D$23) -> 6825.9114
A42: ='4. Assumptions_FY2026'!$D$9-0.03 -> -0.06 | B42: =(('4. Reforecast_FY2026'!$B$5*(1+'4. Assumptions_FY2026'!$D$7+'4. Assumptions_FY2026'!$D$8+$A42)*(1+'4. Assumptions_FY2026'!$D$11-B$40-'4. Assumptions_FY2026'!$D$13-'4. Assumptions_FY2026'!$D$14-'4. Assumptions_FY2026'!$D$15+'4. Assumptions_FY2026'!$D$17+'4. Assumptions_FY2026'!$D$18)+'4. Reforecast_FY2026'!$C$18)*(1-'4. Assumptions_FY2026'!$D$22)+'4. Reforecast_FY2026'!$C$20)*(1-'4. Assumptions_FY2026'!$D$23) -> 8766.446 | C42: =(('4. Reforecast_FY2026'!$B$5*(1+'4. Assumptions_FY2026'!$D$7+'4. Assumptions_FY2026'!$D$8+$A42)*(1+'4. Assumptions_FY2026'!$D$11-C$40-'4. Assumptions_FY2026'!$D$13-'4. Assumptions_FY2026'!$D$14-'4. Assumptions_FY2026'!$D$15+'4. Assumptions_FY2026'!$D$17+'4. Assumptions_FY2026'!$D$18)+'4. Reforecast_FY2026'!$C$18)*(1-'4. Assumptions_FY2026'!$D$22)+'4. Reforecast_FY2026'!$C$20)*(1-'4. Assumptions_FY2026'!$D$23) -> 8455.0928 | D42: =(('4. Reforecast_FY2026'!$B$5*(1+'4. Assumptions_FY2026'!$D$7+'4. Assumptions_FY2026'!$D$8+$A42)*(1+'4. Assumptions_FY2026'!$D$11-D$40-'4. Assumptions_FY2026'!$D$13-'4. Assumptions_FY2026'!$D$14-'4. Assumptions_FY2026'!$D$15+'4. Assumptions_FY2026'!$D$17+'4. Assumptions_FY2026'!$D$18)+'4. Reforecast_FY2026'!$C$18)*(1-'4. Assumptions_FY2026'!$D$22)+'4. Reforecast_FY2026'!$C$20)*(1-'4. Assumptions_FY2026'!$D$23) -> 8143.7395 | E42: =(('4. Reforecast_FY2026'!$B$5*(1+'4. Assumptions_FY2026'!$D$7+'4. Assumptions_FY2026'!$D$8+$A42)*(1+'4. Assumptions_FY2026'!$D$11-E$40-'4. Assumptions_FY2026'!$D$13-'4. Assumptions_FY2026'!$D$14-'4. Assumptions_FY2026'!$D$15+'4. Assumptions_FY2026'!$D$17+'4. Assumptions_FY2026'!$D$18)+'4. Reforecast_FY2026'!$C$18)*(1-'4. Assumptions_FY2026'!$D$22)+'4. Reforecast_FY2026'!$C$20)*(1-'4. Assumptions_FY2026'!$D$23) -> 7832.3863 | F42: =(('4. Reforecast_FY2026'!$B$5*(1+'4. Assumptions_FY2026'!$D$7+'4. Assumptions_FY2026'!$D$8+$A42)*(1+'4. Assumptions_FY2026'!$D$11-F$40-'4. Assumptions_FY2026'!$D$13-'4. Assumptions_FY2026'!$D$14-'4. Assumptions_FY2026'!$D$15+'4. Assumptions_FY2026'!$D$17+'4. Assumptions_FY2026'!$D$18)+'4. Reforecast_FY2026'!$C$18)*(1-'4. Assumptions_FY2026'!$D$22)+'4. Reforecast_FY2026'!$C$20)*(1-'4. Assumptions_FY2026'!$D$23) -> 7521.033 | G42: =(('4. Reforecast_FY2026'!$B$5*(1+'4. Assumptions_FY2026'!$D$7+'4. Assumptions_FY2026'!$D$8+$A42)*(1+'4. Assumptions_FY2026'!$D$11-G$40-'4. Assumptions_FY2026'!$D$13-'4. Assumptions_FY2026'!$D$14-'4. Assumptions_FY2026'!$D$15+'4. Assumptions_FY2026'!$D$17+'4. Assumptions_FY2026'!$D$18)+'4. Reforecast_FY2026'!$C$18)*(1-'4. Assumptions_FY2026'!$D$22)+'4. Reforecast_FY2026'!$C$20)*(1-'4. Assumptions_FY2026'!$D$23) -> 7209.6798 | H42: =(('4. Reforecast_FY2026'!$B$5*(1+'4. Assumptions_FY2026'!$D$7+'4. Assumptions_FY2026'!$D$8+$A42)*(1+'4. Assumptions_FY2026'!$D$11-H$40-'4. Assumptions_FY2026'!$D$13-'4. Assumptions_FY2026'!$D$14-'4. Assumptions_FY2026'!$D$15+'4. Assumptions_FY2026'!$D$17+'4. Assumptions_FY2026'!$D$18)+'4. Reforecast_FY2026'!$C$18)*(1-'4. Assumptions_FY2026'!$D$22)+'4. Reforecast_FY2026'!$C$20)*(1-'4. Assumptions_FY2026'!$D$23) -> 6898.3265
A43: ='4. Assumptions_FY2026'!$D$9-0.02 -> -0.05 | B43: =(('4. Reforecast_FY2026'!$B$5*(1+'4. Assumptions_FY2026'!$D$7+'4. Assumptions_FY2026'!$D$8+$A43)*(1+'4. Assumptions_FY2026'!$D$11-B$40-'4. Assumptions_FY2026'!$D$13-'4. Assumptions_FY2026'!$D$14-'4. Assumptions_FY2026'!$D$15+'4. Assumptions_FY2026'!$D$17+'4. Assumptions_FY2026'!$D$18)+'4. Reforecast_FY2026'!$C$18)*(1-'4. Assumptions_FY2026'!$D$22)+'4. Reforecast_FY2026'!$C$20)*(1-'4. Assumptions_FY2026'!$D$23) -> 8858.0017 | C43: =(('4. Reforecast_FY2026'!$B$5*(1+'4. Assumptions_FY2026'!$D$7+'4. Assumptions_FY2026'!$D$8+$A43)*(1+'4. Assumptions_FY2026'!$D$11-C$40-'4. Assumptions_FY2026'!$D$13-'4. Assumptions_FY2026'!$D$14-'4. Assumptions_FY2026'!$D$15+'4. Assumptions_FY2026'!$D$17+'4. Assumptions_FY2026'!$D$18)+'4. Reforecast_FY2026'!$C$18)*(1-'4. Assumptions_FY2026'!$D$22)+'4. Reforecast_FY2026'!$C$20)*(1-'4. Assumptions_FY2026'!$D$23) -> 8543.4584 | D43: =(('4. Reforecast_FY2026'!$B$5*(1+'4. Assumptions_FY2026'!$D$7+'4. Assumptions_FY2026'!$D$8+$A43)*(1+'4. Assumptions_FY2026'!$D$11-D$40-'4. Assumptions_FY2026'!$D$13-'4. Assumptions_FY2026'!$D$14-'4. Assumptions_FY2026'!$D$15+'4. Assumptions_FY2026'!$D$17+'4. Assumptions_FY2026'!$D$18)+'4. Reforecast_FY2026'!$C$18)*(1-'4. Assumptions_FY2026'!$D$22)+'4. Reforecast_FY2026'!$C$20)*(1-'4. Assumptions_FY2026'!$D$23) -> 8228.915 | E43: =(('4. Reforecast_FY2026'!$B$5*(1+'4. Assumptions_FY2026'!$D$7+'4. Assumptions_FY2026'!$D$8+$A43)*(1+'4. Assumptions_FY2026'!$D$11-E$40-'4. Assumptions_FY2026'!$D$13-'4. Assumptions_FY2026'!$D$14-'4. Assumptions_FY2026'!$D$15+'4. Assumptions_FY2026'!$D$17+'4. Assumptions_FY2026'!$D$18)+'4. Reforecast_FY2026'!$C$18)*(1-'4. Assumptions_FY2026'!$D$22)+'4. Reforecast_FY2026'!$C$20)*(1-'4. Assumptions_FY2026'!$D$23) -> 7914.3717 | F43: =(('4. Reforecast_FY2026'!$B$5*(1+'4. Assumptions_FY2026'!$D$7+'4. Assumptions_FY2026'!$D$8+$A43)*(1+'4. Assumptions_FY2026'!$D$11-F$40-'4. Assumptions_FY2026'!$D$13-'4. Assumptions_FY2026'!$D$14-'4. Assumptions_FY2026'!$D$15+'4. Assumptions_FY2026'!$D$17+'4. Assumptions_FY2026'!$D$18)+'4. Reforecast_FY2026'!$C$18)*(1-'4. Assumptions_FY2026'!$D$22)+'4. Reforecast_FY2026'!$C$20)*(1-'4. Assumptions_FY2026'!$D$23) -> 7599.8284 | G43: =(('4. Reforecast_FY2026'!$B$5*(1+'4. Assumptions_FY2026'!$D$7+'4. Assumptions_FY2026'!$D$8+$A43)*(1+'4. Assumptions_FY2026'!$D$11-G$40-'4. Assumptions_FY2026'!$D$13-'4. Assumptions_FY2026'!$D$14-'4. Assumptions_FY2026'!$D$15+'4. Assumptions_FY2026'!$D$17+'4. Assumptions_FY2026'!$D$18)+'4. Reforecast_FY2026'!$C$18)*(1-'4. Assumptions_FY2026'!$D$22)+'4. Reforecast_FY2026'!$C$20)*(1-'4. Assumptions_FY2026'!$D$23) -> 7285.285 | H43: =(('4. Reforecast_FY2026'!$B$5*(1+'4. Assumptions_FY2026'!$D$7+'4. Assumptions_FY2026'!$D$8+$A43)*(1+'4. Assumptions_FY2026'!$D$11-H$40-'4. Assumptions_FY2026'!$D$13-'4. Assumptions_FY2026'!$D$14-'4. Assumptions_FY2026'!$D$15+'4. Assumptions_FY2026'!$D$17+'4. Assumptions_FY2026'!$D$18)+'4. Reforecast_FY2026'!$C$18)*(1-'4. Assumptions_FY2026'!$D$22)+'4. Reforecast_FY2026'!$C$20)*(1-'4. Assumptions_FY2026'!$D$23) -> 6970.7417
A44: ='4. Assumptions_FY2026'!$D$9-0.01 -> -0.04 | B44: =(('4. Reforecast_FY2026'!$B$5*(1+'4. Assumptions_FY2026'!$D$7+'4. Assumptions_FY2026'!$D$8+$A44)*(1+'4. Assumptions_FY2026'!$D$11-B$40-'4. Assumptions_FY2026'!$D$13-'4. Assumptions_FY2026'!$D$14-'4. Assumptions_FY2026'!$D$15+'4. Assumptions_FY2026'!$D$17+'4. Assumptions_FY2026'!$D$18)+'4. Reforecast_FY2026'!$C$18)*(1-'4. Assumptions_FY2026'!$D$22)+'4. Reforecast_FY2026'!$C$20)*(1-'4. Assumptions_FY2026'!$D$23) -> 8949.5575 | C44: =(('4. Reforecast_FY2026'!$B$5*(1+'4. Assumptions_FY2026'!$D$7+'4. Assumptions_FY2026'!$D$8+$A44)*(1+'4. Assumptions_FY2026'!$D$11-C$40-'4. Assumptions_FY2026'!$D$13-'4. Assumptions_FY2026'!$D$14-'4. Assumptions_FY2026'!$D$15+'4. Assumptions_FY2026'!$D$17+'4. Assumptions_FY2026'!$D$18)+'4. Reforecast_FY2026'!$C$18)*(1-'4. Assumptions_FY2026'!$D$22)+'4. Reforecast_FY2026'!$C$20)*(1-'4. Assumptions_FY2026'!$D$23) -> 8631.824 | D44: =(('4. Reforecast_FY2026'!$B$5*(1+'4. Assumptions_FY2026'!$D$7+'4. Assumptions_FY2026'!$D$8+$A44)*(1+'4. Assumptions_FY2026'!$D$11-D$40-'4. Assumptions_FY2026'!$D$13-'4. Assumptions_FY2026'!$D$14-'4. Assumptions_FY2026'!$D$15+'4. Assumptions_FY2026'!$D$17+'4. Assumptions_FY2026'!$D$18)+'4. Reforecast_FY2026'!$C$18)*(1-'4. Assumptions_FY2026'!$D$22)+'4. Reforecast_FY2026'!$C$20)*(1-'4. Assumptions_FY2026'!$D$23) -> 8314.0906 | E44: =(('4. Reforecast_FY2026'!$B$5*(1+'4. Assumptions_FY2026'!$D$7+'4. Assumptions_FY2026'!$D$8+$A44)*(1+'4. Assumptions_FY2026'!$D$11-E$40-'4. Assumptions_FY2026'!$D$13-'4. Assumptions_FY2026'!$D$14-'4. Assumptions_FY2026'!$D$15+'4. Assumptions_FY2026'!$D$17+'4. Assumptions_FY2026'!$D$18)+'4. Reforecast_FY2026'!$C$18)*(1-'4. Assumptions_FY2026'!$D$22)+'4. Reforecast_FY2026'!$C$20)*(1-'4. Assumptions_FY2026'!$D$23) -> 7996.3571 | F44: =(('4. Reforecast_FY2026'!$B$5*(1+'4. Assumptions_FY2026'!$D$7+'4. Assumptions_FY2026'!$D$8+$A44)*(1+'4. Assumptions_FY2026'!$D$11-F$40-'4. Assumptions_FY2026'!$D$13-'4. Assumptions_FY2026'!$D$14-'4. Assumptions_FY2026'!$D$15+'4. Assumptions_FY2026'!$D$17+'4. Assumptions_FY2026'!$D$18)+'4. Reforecast_FY2026'!$C$18)*(1-'4. Assumptions_FY2026'!$D$22)+'4. Reforecast_FY2026'!$C$20)*(1-'4. Assumptions_FY2026'!$D$23) -> 7678.6237 | G44: =(('4. Reforecast_FY2026'!$B$5*(1+'4. Assumptions_FY2026'!$D$7+'4. Assumptions_FY2026'!$D$8+$A44)*(1+'4. Assumptions_FY2026'!$D$11-G$40-'4. Assumptions_FY2026'!$D$13-'4. Assumptions_FY2026'!$D$14-'4. Assumptions_FY2026'!$D$15+'4. Assumptions_FY2026'!$D$17+'4. Assumptions_FY2026'!$D$18)+'4. Reforecast_FY2026'!$C$18)*(1-'4. Assumptions_FY2026'!$D$22)+'4. Reforecast_FY2026'!$C$20)*(1-'4. Assumptions_FY2026'!$D$23) -> 7360.8903 | H44: =(('4. Reforecast_FY2026'!$B$5*(1+'4. Assumptions_FY2026'!$D$7+'4. Assumptions_FY2026'!$D$8+$A44)*(1+'4. Assumptions_FY2026'!$D$11-H$40-'4. Assumptions_FY2026'!$D$13-'4. Assumptions_FY2026'!$D$14-'4. Assumptions_FY2026'!$D$15+'4. Assumptions_FY2026'!$D$17+'4. Assumptions_FY2026'!$D$18)+'4. Reforecast_FY2026'!$C$18)*(1-'4. Assumptions_FY2026'!$D$22)+'4. Reforecast_FY2026'!$C$20)*(1-'4. Assumptions_FY2026'!$D$23) -> 7043.1568
A45: ='4. Assumptions_FY2026'!$D$9+0 -> -0.03 | B45: =(('4. Reforecast_FY2026'!$B$5*(1+'4. Assumptions_FY2026'!$D$7+'4. Assumptions_FY2026'!$D$8+$A45)*(1+'4. Assumptions_FY2026'!$D$11-B$40-'4. Assumptions_FY2026'!$D$13-'4. Assumptions_FY2026'!$D$14-'4. Assumptions_FY2026'!$D$15+'4. Assumptions_FY2026'!$D$17+'4. Assumptions_FY2026'!$D$18)+'4. Reforecast_FY2026'!$C$18)*(1-'4. Assumptions_FY2026'!$D$22)+'4. Reforecast_FY2026'!$C$20)*(1-'4. Assumptions_FY2026'!$D$23) -> 9041.1132 | C45: =(('4. Reforecast_FY2026'!$B$5*(1+'4. Assumptions_FY2026'!$D$7+'4. Assumptions_FY2026'!$D$8+$A45)*(1+'4. Assumptions_FY2026'!$D$11-C$40-'4. Assumptions_FY2026'!$D$13-'4. Assumptions_FY2026'!$D$14-'4. Assumptions_FY2026'!$D$15+'4. Assumptions_FY2026'!$D$17+'4. Assumptions_FY2026'!$D$18)+'4. Reforecast_FY2026'!$C$18)*(1-'4. Assumptions_FY2026'!$D$22)+'4. Reforecast_FY2026'!$C$20)*(1-'4. Assumptions_FY2026'!$D$23) -> 8720.1896 | D45: =(('4. Reforecast_FY2026'!$B$5*(1+'4. Assumptions_FY2026'!$D$7+'4. Assumptions_FY2026'!$D$8+$A45)*(1+'4. Assumptions_FY2026'!$D$11-D$40-'4. Assumptions_FY2026'!$D$13-'4. Assumptions_FY2026'!$D$14-'4. Assumptions_FY2026'!$D$15+'4. Assumptions_FY2026'!$D$17+'4. Assumptions_FY2026'!$D$18)+'4. Reforecast_FY2026'!$C$18)*(1-'4. Assumptions_FY2026'!$D$22)+'4. Reforecast_FY2026'!$C$20)*(1-'4. Assumptions_FY2026'!$D$23) -> 8399.2661 | E45: =(('4. Reforecast_FY2026'!$B$5*(1+'4. Assumptions_FY2026'!$D$7+'4. Assumptions_FY2026'!$D$8+$A45)*(1+'4. Assumptions_FY2026'!$D$11-E$40-'4. Assumptions_FY2026'!$D$13-'4. Assumptions_FY2026'!$D$14-'4. Assumptions_FY2026'!$D$15+'4. Assumptions_FY2026'!$D$17+'4. Assumptions_FY2026'!$D$18)+'4. Reforecast_FY2026'!$C$18)*(1-'4. Assumptions_FY2026'!$D$22)+'4. Reforecast_FY2026'!$C$20)*(1-'4. Assumptions_FY2026'!$D$23) -> 8078.3426 | F45: =(('4. Reforecast_FY2026'!$B$5*(1+'4. Assumptions_FY2026'!$D$7+'4. Assumptions_FY2026'!$D$8+$A45)*(1+'4. Assumptions_FY2026'!$D$11-F$40-'4. Assumptions_FY2026'!$D$13-'4. Assumptions_FY2026'!$D$14-'4. Assumptions_FY2026'!$D$15+'4. Assumptions_FY2026'!$D$17+'4. Assumptions_FY2026'!$D$18)+'4. Reforecast_FY2026'!$C$18)*(1-'4. Assumptions_FY2026'!$D$22)+'4. Reforecast_FY2026'!$C$20)*(1-'4. Assumptions_FY2026'!$D$23) -> 7757.419 | G45: =(('4. Reforecast_FY2026'!$B$5*(1+'4. Assumptions_FY2026'!$D$7+'4. Assumptions_FY2026'!$D$8+$A45)*(1+'4. Assumptions_FY2026'!$D$11-G$40-'4. Assumptions_FY2026'!$D$13-'4. Assumptions_FY2026'!$D$14-'4. Assumptions_FY2026'!$D$15+'4. Assumptions_FY2026'!$D$17+'4. Assumptions_FY2026'!$D$18)+'4. Reforecast_FY2026'!$C$18)*(1-'4. Assumptions_FY2026'!$D$22)+'4. Reforecast_FY2026'!$C$20)*(1-'4. Assumptions_FY2026'!$D$23) -> 7436.4955 | H45: =(('4. Reforecast_FY2026'!$B$5*(1+'4. Assumptions_FY2026'!$D$7+'4. Assumptions_FY2026'!$D$8+$A45)*(1+'4. Assumptions_FY2026'!$D$11-H$40-'4. Assumptions_FY2026'!$D$13-'4. Assumptions_FY2026'!$D$14-'4. Assumptions_FY2026'!$D$15+'4. Assumptions_FY2026'!$D$17+'4. Assumptions_FY2026'!$D$18)+'4. Reforecast_FY2026'!$C$18)*(1-'4. Assumptions_FY2026'!$D$22)+'4. Reforecast_FY2026'!$C$20)*(1-'4. Assumptions_FY2026'!$D$23) -> 7115.572
A46: ='4. Assumptions_FY2026'!$D$9+0.01 -> -0.02 | B46: =(('4. Reforecast_FY2026'!$B$5*(1+'4. Assumptions_FY2026'!$D$7+'4. Assumptions_FY2026'!$D$8+$A46)*(1+'4. Assumptions_FY2026'!$D$11-B$40-'4. Assumptions_FY2026'!$D$13-'4. Assumptions_FY2026'!$D$14-'4. Assumptions_FY2026'!$D$15+'4. Assumptions_FY2026'!$D$17+'4. Assumptions_FY2026'!$D$18)+'4. Reforecast_FY2026'!$C$18)*(1-'4. Assumptions_FY2026'!$D$22)+'4. Reforecast_FY2026'!$C$20)*(1-'4. Assumptions_FY2026'!$D$23) -> 9132.6689 | C46: =(('4. Reforecast_FY2026'!$B$5*(1+'4. Assumptions_FY2026'!$D$7+'4. Assumptions_FY2026'!$D$8+$A46)*(1+'4. Assumptions_FY2026'!$D$11-C$40-'4. Assumptions_FY2026'!$D$13-'4. Assumptions_FY2026'!$D$14-'4. Assumptions_FY2026'!$D$15+'4. Assumptions_FY2026'!$D$17+'4. Assumptions_FY2026'!$D$18)+'4. Reforecast_FY2026'!$C$18)*(1-'4. Assumptions_FY2026'!$D$22)+'4. Reforecast_FY2026'!$C$20)*(1-'4. Assumptions_FY2026'!$D$23) -> 8808.5553 | D46: =(('4. Reforecast_FY2026'!$B$5*(1+'4. Assumptions_FY2026'!$D$7+'4. Assumptions_FY2026'!$D$8+$A46)*(1+'4. Assumptions_FY2026'!$D$11-D$40-'4. Assumptions_FY2026'!$D$13-'4. Assumptions_FY2026'!$D$14-'4. Assumptions_FY2026'!$D$15+'4. Assumptions_FY2026'!$D$17+'4. Assumptions_FY2026'!$D$18)+'4. Reforecast_FY2026'!$C$18)*(1-'4. Assumptions_FY2026'!$D$22)+'4. Reforecast_FY2026'!$C$20)*(1-'4. Assumptions_FY2026'!$D$23) -> 8484.4416 | E46: =(('4. Reforecast_FY2026'!$B$5*(1+'4. Assumptions_FY2026'!$D$7+'4. Assumptions_FY2026'!$D$8+$A46)*(1+'4. Assumptions_FY2026'!$D$11-E$40-'4. Assumptions_FY2026'!$D$13-'4. Assumptions_FY2026'!$D$14-'4. Assumptions_FY2026'!$D$15+'4. Assumptions_FY2026'!$D$17+'4. Assumptions_FY2026'!$D$18)+'4. Reforecast_FY2026'!$C$18)*(1-'4. Assumptions_FY2026'!$D$22)+'4. Reforecast_FY2026'!$C$20)*(1-'4. Assumptions_FY2026'!$D$23) -> 8160.328 | F46: =(('4. Reforecast_FY2026'!$B$5*(1+'4. Assumptions_FY2026'!$D$7+'4. Assumptions_FY2026'!$D$8+$A46)*(1+'4. Assumptions_FY2026'!$D$11-F$40-'4. Assumptions_FY2026'!$D$13-'4. Assumptions_FY2026'!$D$14-'4. Assumptions_FY2026'!$D$15+'4. Assumptions_FY2026'!$D$17+'4. Assumptions_FY2026'!$D$18)+'4. Reforecast_FY2026'!$C$18)*(1-'4. Assumptions_FY2026'!$D$22)+'4. Reforecast_FY2026'!$C$20)*(1-'4. Assumptions_FY2026'!$D$23) -> 7836.2144 | G46: =(('4. Reforecast_FY2026'!$B$5*(1+'4. Assumptions_FY2026'!$D$7+'4. Assumptions_FY2026'!$D$8+$A46)*(1+'4. Assumptions_FY2026'!$D$11-G$40-'4. Assumptions_FY2026'!$D$13-'4. Assumptions_FY2026'!$D$14-'4. Assumptions_FY2026'!$D$15+'4. Assumptions_FY2026'!$D$17+'4. Assumptions_FY2026'!$D$18)+'4. Reforecast_FY2026'!$C$18)*(1-'4. Assumptions_FY2026'!$D$22)+'4. Reforecast_FY2026'!$C$20)*(1-'4. Assumptions_FY2026'!$D$23) -> 7512.1007 | H46: =(('4. Reforecast_FY2026'!$B$5*(1+'4. Assumptions_FY2026'!$D$7+'4. Assumptions_FY2026'!$D$8+$A46)*(1+'4. Assumptions_FY2026'!$D$11-H$40-'4. Assumptions_FY2026'!$D$13-'4. Assumptions_FY2026'!$D$14-'4. Assumptions_FY2026'!$D$15+'4. Assumptions_FY2026'!$D$17+'4. Assumptions_FY2026'!$D$18)+'4. Reforecast_FY2026'!$C$18)*(1-'4. Assumptions_FY2026'!$D$22)+'4. Reforecast_FY2026'!$C$20)*(1-'4. Assumptions_FY2026'!$D$23) -> 7187.9871
A47: ='4. Assumptions_FY2026'!$D$9+0.02 -> -0.01 | B47: =(('4. Reforecast_FY2026'!$B$5*(1+'4. Assumptions_FY2026'!$D$7+'4. Assumptions_FY2026'!$D$8+$A47)*(1+'4. Assumptions_FY2026'!$D$11-B$40-'4. Assumptions_FY2026'!$D$13-'4. Assumptions_FY2026'!$D$14-'4. Assumptions_FY2026'!$D$15+'4. Assumptions_FY2026'!$D$17+'4. Assumptions_FY2026'!$D$18)+'4. Reforecast_FY2026'!$C$18)*(1-'4. Assumptions_FY2026'!$D$22)+'4. Reforecast_FY2026'!$C$20)*(1-'4. Assumptions_FY2026'!$D$23) -> 9224.2246 | C47: =(('4. Reforecast_FY2026'!$B$5*(1+'4. Assumptions_FY2026'!$D$7+'4. Assumptions_FY2026'!$D$8+$A47)*(1+'4. Assumptions_FY2026'!$D$11-C$40-'4. Assumptions_FY2026'!$D$13-'4. Assumptions_FY2026'!$D$14-'4. Assumptions_FY2026'!$D$15+'4. Assumptions_FY2026'!$D$17+'4. Assumptions_FY2026'!$D$18)+'4. Reforecast_FY2026'!$C$18)*(1-'4. Assumptions_FY2026'!$D$22)+'4. Reforecast_FY2026'!$C$20)*(1-'4. Assumptions_FY2026'!$D$23) -> 8896.9209 | D47: =(('4. Reforecast_FY2026'!$B$5*(1+'4. Assumptions_FY2026'!$D$7+'4. Assumptions_FY2026'!$D$8+$A47)*(1+'4. Assumptions_FY2026'!$D$11-D$40-'4. Assumptions_FY2026'!$D$13-'4. Assumptions_FY2026'!$D$14-'4. Assumptions_FY2026'!$D$15+'4. Assumptions_FY2026'!$D$17+'4. Assumptions_FY2026'!$D$18)+'4. Reforecast_FY2026'!$C$18)*(1-'4. Assumptions_FY2026'!$D$22)+'4. Reforecast_FY2026'!$C$20)*(1-'4. Assumptions_FY2026'!$D$23) -> 8569.6172 | E47: =(('4. Reforecast_FY2026'!$B$5*(1+'4. Assumptions_FY2026'!$D$7+'4. Assumptions_FY2026'!$D$8+$A47)*(1+'4. Assumptions_FY2026'!$D$11-E$40-'4. Assumptions_FY2026'!$D$13-'4. Assumptions_FY2026'!$D$14-'4. Assumptions_FY2026'!$D$15+'4. Assumptions_FY2026'!$D$17+'4. Assumptions_FY2026'!$D$18)+'4. Reforecast_FY2026'!$C$18)*(1-'4. Assumptions_FY2026'!$D$22)+'4. Reforecast_FY2026'!$C$20)*(1-'4. Assumptions_FY2026'!$D$23) -> 8242.3134 | F47: =(('4. Reforecast_FY2026'!$B$5*(1+'4. Assumptions_FY2026'!$D$7+'4. Assumptions_FY2026'!$D$8+$A47)*(1+'4. Assumptions_FY2026'!$D$11-F$40-'4. Assumptions_FY2026'!$D$13-'4. Assumptions_FY2026'!$D$14-'4. Assumptions_FY2026'!$D$15+'4. Assumptions_FY2026'!$D$17+'4. Assumptions_FY2026'!$D$18)+'4. Reforecast_FY2026'!$C$18)*(1-'4. Assumptions_FY2026'!$D$22)+'4. Reforecast_FY2026'!$C$20)*(1-'4. Assumptions_FY2026'!$D$23) -> 7915.0097 | G47: =(('4. Reforecast_FY2026'!$B$5*(1+'4. Assumptions_FY2026'!$D$7+'4. Assumptions_FY2026'!$D$8+$A47)*(1+'4. Assumptions_FY2026'!$D$11-G$40-'4. Assumptions_FY2026'!$D$13-'4. Assumptions_FY2026'!$D$14-'4. Assumptions_FY2026'!$D$15+'4. Assumptions_FY2026'!$D$17+'4. Assumptions_FY2026'!$D$18)+'4. Reforecast_FY2026'!$C$18)*(1-'4. Assumptions_FY2026'!$D$22)+'4. Reforecast_FY2026'!$C$20)*(1-'4. Assumptions_FY2026'!$D$23) -> 7587.706 | H47: =(('4. Reforecast_FY2026'!$B$5*(1+'4. Assumptions_FY2026'!$D$7+'4. Assumptions_FY2026'!$D$8+$A47)*(1+'4. Assumptions_FY2026'!$D$11-H$40-'4. Assumptions_FY2026'!$D$13-'4. Assumptions_FY2026'!$D$14-'4. Assumptions_FY2026'!$D$15+'4. Assumptions_FY2026'!$D$17+'4. Assumptions_FY2026'!$D$18)+'4. Reforecast_FY2026'!$C$18)*(1-'4. Assumptions_FY2026'!$D$22)+'4. Reforecast_FY2026'!$C$20)*(1-'4. Assumptions_FY2026'!$D$23) -> 7260.4023
A48: ='4. Assumptions_FY2026'!$D$9+0.03 -> 0 | B48: =(('4. Reforecast_FY2026'!$B$5*(1+'4. Assumptions_FY2026'!$D$7+'4. Assumptions_FY2026'!$D$8+$A48)*(1+'4. Assumptions_FY2026'!$D$11-B$40-'4. Assumptions_FY2026'!$D$13-'4. Assumptions_FY2026'!$D$14-'4. Assumptions_FY2026'!$D$15+'4. Assumptions_FY2026'!$D$17+'4. Assumptions_FY2026'!$D$18)+'4. Reforecast_FY2026'!$C$18)*(1-'4. Assumptions_FY2026'!$D$22)+'4. Reforecast_FY2026'!$C$20)*(1-'4. Assumptions_FY2026'!$D$23) -> 9315.7803 | C48: =(('4. Reforecast_FY2026'!$B$5*(1+'4. Assumptions_FY2026'!$D$7+'4. Assumptions_FY2026'!$D$8+$A48)*(1+'4. Assumptions_FY2026'!$D$11-C$40-'4. Assumptions_FY2026'!$D$13-'4. Assumptions_FY2026'!$D$14-'4. Assumptions_FY2026'!$D$15+'4. Assumptions_FY2026'!$D$17+'4. Assumptions_FY2026'!$D$18)+'4. Reforecast_FY2026'!$C$18)*(1-'4. Assumptions_FY2026'!$D$22)+'4. Reforecast_FY2026'!$C$20)*(1-'4. Assumptions_FY2026'!$D$23) -> 8985.2865 | D48: =(('4. Reforecast_FY2026'!$B$5*(1+'4. Assumptions_FY2026'!$D$7+'4. Assumptions_FY2026'!$D$8+$A48)*(1+'4. Assumptions_FY2026'!$D$11-D$40-'4. Assumptions_FY2026'!$D$13-'4. Assumptions_FY2026'!$D$14-'4. Assumptions_FY2026'!$D$15+'4. Assumptions_FY2026'!$D$17+'4. Assumptions_FY2026'!$D$18)+'4. Reforecast_FY2026'!$C$18)*(1-'4. Assumptions_FY2026'!$D$22)+'4. Reforecast_FY2026'!$C$20)*(1-'4. Assumptions_FY2026'!$D$23) -> 8654.7927 | E48: =(('4. Reforecast_FY2026'!$B$5*(1+'4. Assumptions_FY2026'!$D$7+'4. Assumptions_FY2026'!$D$8+$A48)*(1+'4. Assumptions_FY2026'!$D$11-E$40-'4. Assumptions_FY2026'!$D$13-'4. Assumptions_FY2026'!$D$14-'4. Assumptions_FY2026'!$D$15+'4. Assumptions_FY2026'!$D$17+'4. Assumptions_FY2026'!$D$18)+'4. Reforecast_FY2026'!$C$18)*(1-'4. Assumptions_FY2026'!$D$22)+'4. Reforecast_FY2026'!$C$20)*(1-'4. Assumptions_FY2026'!$D$23) -> 8324.2989 | F48: =(('4. Reforecast_FY2026'!$B$5*(1+'4. Assumptions_FY2026'!$D$7+'4. Assumptions_FY2026'!$D$8+$A48)*(1+'4. Assumptions_FY2026'!$D$11-F$40-'4. Assumptions_FY2026'!$D$13-'4. Assumptions_FY2026'!$D$14-'4. Assumptions_FY2026'!$D$15+'4. Assumptions_FY2026'!$D$17+'4. Assumptions_FY2026'!$D$18)+'4. Reforecast_FY2026'!$C$18)*(1-'4. Assumptions_FY2026'!$D$22)+'4. Reforecast_FY2026'!$C$20)*(1-'4. Assumptions_FY2026'!$D$23) -> 7993.8051 | G48: =(('4. Reforecast_FY2026'!$B$5*(1+'4. Assumptions_FY2026'!$D$7+'4. Assumptions_FY2026'!$D$8+$A48)*(1+'4. Assumptions_FY2026'!$D$11-G$40-'4. Assumptions_FY2026'!$D$13-'4. Assumptions_FY2026'!$D$14-'4. Assumptions_FY2026'!$D$15+'4. Assumptions_FY2026'!$D$17+'4. Assumptions_FY2026'!$D$18)+'4. Reforecast_FY2026'!$C$18)*(1-'4. Assumptions_FY2026'!$D$22)+'4. Reforecast_FY2026'!$C$20)*(1-'4. Assumptions_FY2026'!$D$23) -> 7663.3112 | H48: =(('4. Reforecast_FY2026'!$B$5*(1+'4. Assumptions_FY2026'!$D$7+'4. Assumptions_FY2026'!$D$8+$A48)*(1+'4. Assumptions_FY2026'!$D$11-H$40-'4. Assumptions_FY2026'!$D$13-'4. Assumptions_FY2026'!$D$14-'4. Assumptions_FY2026'!$D$15+'4. Assumptions_FY2026'!$D$17+'4. Assumptions_FY2026'!$D$18)+'4. Reforecast_FY2026'!$C$18)*(1-'4. Assumptions_FY2026'!$D$22)+'4. Reforecast_FY2026'!$C$20)*(1-'4. Assumptions_FY2026'!$D$23) -> 7332.8174
A49: Dark cell = FY2026 Base. Green = net profit at or above FY2025 actual (CHF 9,033m); red = below it. Grid formula = the reforecast's own P&L logic in one line (sales × margin, plus fixed financial items and associates, taxed at the Base rate).
A51: E. RULES OF THUMB AND BREAK-EVENS
A52: Each +1 pp of FX (e.g. -3% → -2%): change in sales | C52: =G12-F12 -> 894.9
A53: Each +1 pp of FX: change in net profit | C53: =G18-F18 -> 81.985436
A54: Each +10 bps of COGS: change in net profit | C54: =(F33-E33)/5 -> -64.184707
A55: FX move with the same net profit effect as 10 bps of COGS | C55: =ABS(C54/C53) -> 0.78287938
A56: Net profit at February's FX estimate (about -6%) | C56: =(('4. Reforecast_FY2026'!$B$5*(1+'4. Assumptions_FY2026'!$D$7+'4. Assumptions_FY2026'!$D$8+'4. Assumptions_FY2026'!$D$58)*(1+'4. Assumptions_FY2026'!$D$11-'4. Assumptions_FY2026'!$D$12-'4. Assumptions_FY2026'!$D$13-'4. Assumptions_FY2026'!$D$14-'4. Assumptions_FY2026'!$D$15+'4. Assumptions_FY2026'!$D$17+'4. Assumptions_FY2026'!$D$18)+'4. Reforecast_FY2026'!$C$18)*(1-'4. Assumptions_FY2026'!$D$22)+'4. Reforecast_FY2026'!$C$20)*(1-'4. Assumptions_FY2026'!$D$23) -> 7832.3863
A57: … i.e. value of the July FX update to net profit | C57: ='4. Reforecast_FY2026'!$C$24-C56 -> 245.95631
A58: COGS % at which the UTOP margin stops improving on FY2025 | C58: ='4. Assumptions_FY2026'!$D$12+('4. Reforecast_FY2026'!$C$26-'4. Reforecast_FY2026'!$B$26) -> 0.54071109
A59: COGS % at which free cash flow falls to the CHF 9bn guidance floor | C59: ='4. Assumptions_FY2026'!$D$12+('4. Assumptions_FY2026'!$D$53-'4. Reforecast_FY2026'!$C$75)/((F35-E35)/5)/1000 -> 0.55973361
A60: FX at which free cash flow falls to the CHF 9bn guidance floor | C60: ='4. Assumptions_FY2026'!$D$9+('4. Assumptions_FY2026'!$D$53-'4. Reforecast_FY2026'!$C$75)/(G20-F20)/100 -> -0.22750888
A61: Check: model at Base inputs − reforecast net profit | C61: =ROUND((('4. Reforecast_FY2026'!$B$5*(1+'4. Assumptions_FY2026'!$D$7+'4. Assumptions_FY2026'!$D$8+'4. Assumptions_FY2026'!$D$9)*(1+'4. Assumptions_FY2026'!$D$11-'4. Assumptions_FY2026'!$D$12-'4. Assumptions_FY2026'!$D$13-'4. Assumptions_FY2026'!$D$14-'4. Assumptions_FY2026'!$D$15+'4. Assumptions_FY2026'!$D$17+'4. Assumptions_FY2026'!$D$18)+'4. Reforecast_FY2026'!$C$18)*(1-'4. Assumptions_FY2026'!$D$22)+'4. Reforecast_FY2026'!$C$20)*(1-'4. Assumptions_FY2026'!$D$23)-'4. Reforecast_FY2026'!$C$24,2) -> 0
A63: How to read it
A64: FX here is translation: it scales sales and every sales-linked cost, so it moves profit in CHF but not the UTOP margin. Financial items, associates income, impairment and working capital are held at Base, so the tables slightly overstate FX sensitivity (in reality part of Nestlé's debt and associates income is also in foreign currencies).
A65: COGS changes the margin itself, so it is the bigger lever: 10 bps of COGS moves net profit about as much as 0.8 pp of FX (about CHF 64m vs CHF 82m per pp). Nestlé's move from about -6% (February) to about -3% (July) in its FX estimate is worth roughly CHF 250m of FY2026 net profit.
A66: Guidance headroom: the UTOP margin still improves on FY2025 only while COGS stays below about 54.1% of sales — roughly 50 bps above the Base, less than a third of the FY2025 COGS miss. Free cash flow stays above CHF 9bn unless COGS rises above about 56%; FX alone would have to fall below -20% to breach it.
